Workbook
Name aa: INDEX(#REF!,MATCH(#REF!,#REF!,0),1):INDEX(#REF!,MATCH(#REF!,#REF!,0),1)
Name aaaa: INDEX(#REF!,MATCH(#REF!,#REF!,0),1):INDEX(#REF!,MATCH(#REF!,#REF!,0),1)
Name adwadwq: #REF!
Name Amazon_IST: INDEX(#REF!,MATCH(#REF!,#REF!,0),1):INDEX(#REF!,MATCH(#REF!,#REF!,0),1)
Name Amazon_Soll: INDEX(#REF!,MATCH(#REF!,#REF!,0),1):INDEX(#REF!,MATCH(#REF!,#REF!,0),1)
Name Anzeigewoche: #REF!
Name Artikelliste: #REF!
Name asdad: #REF!
Name asdadaqqwds: INDEX(#REF!,MATCH(#REF!,#REF!,0),1):INDEX(#REF!,MATCH(#REF!,#REF!,0),1)
Name asdasd: INDEX(#REF!,MATCH(#REF!,#REF!,0),1):INDEX(#REF!,COUNTA(#REF!),1)
Name asdasdad: INDEX(#REF!,MATCH(#REF!,#REF!,0),1):INDEX(#REF!,MATCH(#REF!,#REF!,0),1)
Name asdasdas: INDEX(#REF!,MATCH(#REF!,#REF!,0),1):INDEX(#REF!,MATCH(#REF!,#REF!,0),1)
Name asdasdasd: INDEX(#REF!,MATCH(#REF!,#REF!,0),1):INDEX(#REF!,MATCH(#REF!,#REF!,0),1)
Name asdawdqwf: INDEX(#REF!,MATCH(#REF!,#REF!,0),1):INDEX(#REF!,MATCH(#REF!,#REF!,0),1)
Name asdqwd: INDEX(#REF!,MATCH(#REF!,#REF!,0),1):INDEX(#REF!,MATCH(#REF!,#REF!,0),1)
Name asdqwdsqd: INDEX(#REF!,MATCH(#REF!,#REF!,0),1):INDEX(#REF!,MATCH(#REF!,#REF!,0),1)
Name asss: INDEX(#REF!,MATCH(#REF!,#REF!,0),1):INDEX(#REF!,MATCH(#REF!,#REF!,0),1)
Name BadRevAnteil: #REF!
Name BadSeasonHart: #REF!
Name BadSeasonWeich: #REF!
Name Batteries: #REF!
Name Battery: #REF!
Name CatL1: #REF!
Name CatL3: #REF!
Name circ: #REF!
Name cJahr: #REF!
Name cMonat: #REF!
Name ddda: #REF!:INDEX(#REF!,MATCH(#REF!,#REF!,0),1)
Name dddd: INDEX(#REF!,MATCH(#REF!,#REF!,0),1):INDEX(#REF!,MATCH(#REF!,#REF!,0),1)
Name EndeMonat: INDEX(#REF!,MATCH(#REF!,#REF!,0),1):INDEX(#REF!,COUNTA(#REF!),1)
Name Export_List_Ak: #REF!
Name Export_SKU_SAP: #REF!
Name Gesamt_Ist: INDEX(#REF!,MATCH(#REF!,#REF!,0),1):INDEX(#REF!,MATCH(#REF!,#REF!,0),1)
Name Gesamt_Soll: INDEX(#REF!,MATCH(#REF!,#REF!,0),1):INDEX(#REF!,MATCH(#REF!,#REF!,0),1)
Name Großkunden_Ist: INDEX(#REF!,MATCH(#REF!,#REF!,0),1):INDEX(#REF!,MATCH(#REF!,#REF!,0),1)
Name Großkunden_Soll: INDEX(#REF!,MATCH(#REF!,#REF!,0),1):INDEX(#REF!,MATCH(#REF!,#REF!,0),1)
Name hello: #REF!
Name HighPriceAnteil: #REF!
Name increments: #REF!
Name IoT: #REF!
Name IPX_Rating: #REF!
Name Jahr: #REF!
Name Kategorieliste: #REF!
Name Kennzeichnungs_Prozentsatz: #REF!
Name kjvcksaghdf: #REF!
Name Kleinkunden_Ceotra_Ist: INDEX(#REF!,MATCH(#REF!,#REF!,0),1):INDEX(#REF!,MATCH(#REF!,#REF!,0),1)
Name Kleinkunden_Ceotra_Soll: INDEX(#REF!,MATCH(#REF!,#REF!,0),1):INDEX(#REF!,MATCH(#REF!,#REF!,0),1)
Name Kleinkunden_Chaltec_Ist: INDEX(#REF!,MATCH(#REF!,#REF!,0),1):INDEX(#REF!,MATCH(#REF!,#REF!,0),1)
Name KleinkundenChal_Tec_Soll: INDEX(#REF!,MATCH(#REF!,#REF!,0),1):INDEX(#REF!,MATCH(#REF!,#REF!,0),1)
Name KT_Consulting_Soll: INDEX(#REF!,MATCH(#REF!,#REF!,0),1):INDEX(#REF!,MATCH(#REF!,#REF!,0),1)
Name KTConsulting_Ist: INDEX(#REF!,MATCH(#REF!,#REF!,0),1):INDEX(#REF!,MATCH(#REF!,#REF!,0),1)
Name L1Cat: #REF!
Name L3Cat: #REF!
Name list: #REF!
Name MA_Brand: OFFSET(#REF!,1,0,COUNTA(#REF!)-1)
Name Mitarbeiterliste: #REF!
Name Monat: #REF!
Name Monate: INDEX(#REF!,MATCH(#REF!,#REF!,0),1):INDEX(#REF!,MATCH(#REF!,#REF!,0),1)
Name OGP_Ist: INDEX(#REF!,MATCH(#REF!,#REF!,0),1):INDEX(#REF!,MATCH(#REF!,#REF!,0),1)
Name OGP_Soll: INDEX(#REF!,MATCH(#REF!,#REF!,0),1):INDEX(#REF!,MATCH(#REF!,#REF!,0),1)

Sheet Category Tree 5.0
B1: KLARSTEIN | Portfolio Planning v05 | Category Tree 5.0
B4: L1 | C4: L2 | D4: L3 | E4: L4 | F4: Index 5.0 | G4: PM | H4: Attributes File | I4: Part of Scope
B5: Climate | F5: =_xlfn.TEXTJOIN("-",TRUE,CatTree50[[#This Row],[L1]],CatTree50[[#This Row],[L2]],CatTree50[[#This Row],[L3]],CatTree50[[#This Row],[L4]]) -> Climate | H5: =_xlfn.XLOOKUP(CatTree50[[#This Row],[Index 5.0]],'Category List'!B:B,'Category List'!C:C,"")
B6: Climate | C6: Cooling | F6: =_xlfn.TEXTJOIN("-",TRUE,CatTree50[[#This Row],[L1]],CatTree50[[#This Row],[L2]],CatTree50[[#This Row],[L3]],CatTree50[[#This Row],[L4]]) -> Climate-Cooling | G6: Raquel Gonzalez Rodriguez | H6: =_xlfn.XLOOKUP(CatTree50[[#This Row],[Index 5.0]],'Category List'!B:B,'Category List'!C:C,"")
B7: Climate | C7: Cooling | D7: Accessories for Cooling | F7: =_xlfn.TEXTJOIN("-",TRUE,CatTree50[[#This Row],[L1]],CatTree50[[#This Row],[L2]],CatTree50[[#This Row],[L3]],CatTree50[[#This Row],[L4]]) -> Climate-Cooling-Accessories for Cooling | G7: Raquel Gonzalez Rodriguez | H7: =_xlfn.XLOOKUP(CatTree50[[#This Row],[Index 5.0]],'Category List'!B:B,'Category List'!C:C,"")
B8: Climate | C8: Cooling | D8: Mobile Air Conditioners | F8: =_xlfn.TEXTJOIN("-",TRUE,CatTree50[[#This Row],[L1]],CatTree50[[#This Row],[L2]],CatTree50[[#This Row],[L3]],CatTree50[[#This Row],[L4]]) -> Climate-Cooling-Mobile Air Conditioners | G8: Raquel Gonzalez Rodriguez | H8: =_xlfn.XLOOKUP(CatTree50[[#This Row],[Index 5.0]],'Category List'!B:B,'Category List'!C:C,"") -> Mobile Air Conditioners - Attributes V3.0.xlsx
B9: Climate | C9: Cooling | D9: Pedestal Fans | F9: =_xlfn.TEXTJOIN("-",TRUE,CatTree50[[#This Row],[L1]],CatTree50[[#This Row],[L2]],CatTree50[[#This Row],[L3]],CatTree50[[#This Row],[L4]]) -> Climate-Cooling-Pedestal Fans | G9: Raquel Gonzalez Rodriguez | H9: =_xlfn.XLOOKUP(CatTree50[[#This Row],[Index 5.0]],'Category List'!B:B,'Category List'!C:C,"") | I9: Done
B10: Climate | C10: Cooling | D10: Split Air Conditioners | F10: =_xlfn.TEXTJOIN("-",TRUE,CatTree50[[#This Row],[L1]],CatTree50[[#This Row],[L2]],CatTree50[[#This Row],[L3]],CatTree50[[#This Row],[L4]]) -> Climate-Cooling-Split Air Conditioners | G10: Raquel Gonzalez Rodriguez | H10: =_xlfn.XLOOKUP(CatTree50[[#This Row],[Index 5.0]],'Category List'!B:B,'Category List'!C:C,"")
B11: Climate | C11: Cooling | D11: Tower Fans | F11: =_xlfn.TEXTJOIN("-",TRUE,CatTree50[[#This Row],[L1]],CatTree50[[#This Row],[L2]],CatTree50[[#This Row],[L3]],CatTree50[[#This Row],[L4]]) -> Climate-Cooling-Tower Fans | G11: Raquel Gonzalez Rodriguez | H11: =_xlfn.XLOOKUP(CatTree50[[#This Row],[Index 5.0]],'Category List'!B:B,'Category List'!C:C,"") | I11: Done
B12: Climate | C12: Dehumidifiers | F12: =_xlfn.TEXTJOIN("-",TRUE,CatTree50[[#This Row],[L1]],CatTree50[[#This Row],[L2]],CatTree50[[#This Row],[L3]],CatTree50[[#This Row],[L4]]) -> Climate-Dehumidifiers | G12: Raquel Gonzalez Rodriguez | H12: =_xlfn.XLOOKUP(CatTree50[[#This Row],[Index 5.0]],'Category List'!B:B,'Category List'!C:C,"") | I12: Done
B13: Climate | C13: Indoor Heaters | F13: =_xlfn.TEXTJOIN("-",TRUE,CatTree50[[#This Row],[L1]],CatTree50[[#This Row],[L2]],CatTree50[[#This Row],[L3]],CatTree50[[#This Row],[L4]]) -> Climate-Indoor Heaters | G13: Raquel Gonzalez Rodriguez | H13: =_xlfn.XLOOKUP(CatTree50[[#This Row],[Index 5.0]],'Category List'!B:B,'Category List'!C:C,"") | I13: Exclude
B14: Climate | C14: Indoor Heaters | D14: Accessories for Indoor Heaters | F14: =_xlfn.TEXTJOIN("-",TRUE,CatTree50[[#This Row],[L1]],CatTree50[[#This Row],[L2]],CatTree50[[#This Row],[L3]],CatTree50[[#This Row],[L4]]) -> Climate-Indoor Heaters-Accessories for Indoor Heaters | G14: Raquel Gonzalez Rodriguez | H14: =_xlfn.XLOOKUP(CatTree50[[#This Row],[Index 5.0]],'Category List'!B:B,'Category List'!C:C,"") | I14: Exclude
B15: Climate | C15: Indoor Heaters | D15: Bathroom Radiators | F15: =_xlfn.TEXTJOIN("-",TRUE,CatTree50[[#This Row],[L1]],CatTree50[[#This Row],[L2]],CatTree50[[#This Row],[L3]],CatTree50[[#This Row],[L4]]) -> Climate-Indoor Heaters-Bathroom Radiators | G15: Raquel Gonzalez Rodriguez | H15: =_xlfn.XLOOKUP(CatTree50[[#This Row],[Index 5.0]],'Category List'!B:B,'Category List'!C:C,"") | I15: Exclude
B16: Climate | C16: Indoor Heaters | D16: Bathroom Radiators | E16: Infrared Radiators | F16: =_xlfn.TEXTJOIN("-",TRUE,CatTree50[[#This Row],[L1]],CatTree50[[#This Row],[L2]],CatTree50[[#This Row],[L3]],CatTree50[[#This Row],[L4]]) -> Climate-Indoor Heaters-Bathroom Radiators-Infrared Radiators | G16: Raquel Gonzalez Rodriguez | H16: =_xlfn.XLOOKUP(CatTree50[[#This Row],[Index 5.0]],'Category List'!B:B,'Category List'!C:C,"") -> Infrared Radiators - Attributes V3.0.xlsx | I16: Done
B17: Climate | C17: Indoor Heaters | D17: Bathroom Radiators | E17: Towel Radiators | F17: =_xlfn.TEXTJOIN("-",TRUE,CatTree50[[#This Row],[L1]],CatTree50[[#This Row],[L2]],CatTree50[[#This Row],[L3]],CatTree50[[#This Row],[L4]]) -> Climate-Indoor Heaters-Bathroom Radiators-Towel Radiators | G17: Raquel Gonzalez Rodriguez | H17: =_xlfn.XLOOKUP(CatTree50[[#This Row],[Index 5.0]],'Category List'!B:B,'Category List'!C:C,"") | I17: Done
B18: Climate | C18: Indoor Heaters | D18: Designer Radiators | F18: =_xlfn.TEXTJOIN("-",TRUE,CatTree50[[#This Row],[L1]],CatTree50[[#This Row],[L2]],CatTree50[[#This Row],[L3]],CatTree50[[#This Row],[L4]]) -> Climate-Indoor Heaters-Designer Radiators | G18: Raquel Gonzalez Rodriguez | H18: =_xlfn.XLOOKUP(CatTree50[[#This Row],[Index 5.0]],'Category List'!B:B,'Category List'!C:C,"") | I18: Done
B19: Climate | C19: Indoor Heaters | D19: Gas Heaters | F19: =_xlfn.TEXTJOIN("-",TRUE,CatTree50[[#This Row],[L1]],CatTree50[[#This Row],[L2]],CatTree50[[#This Row],[L3]],CatTree50[[#This Row],[L4]]) -> Climate-Indoor Heaters-Gas Heaters | G19: Raquel Gonzalez Rodriguez | H19: =_xlfn.XLOOKUP(CatTree50[[#This Row],[Index 5.0]],'Category List'!B:B,'Category List'!C:C,"") | I19: Done
B20: Climate | C20: Indoor Heaters | D20: Heating Blankets | F20: =_xlfn.TEXTJOIN("-",TRUE,CatTree50[[#This Row],[L1]],CatTree50[[#This Row],[L2]],CatTree50[[#This Row],[L3]],CatTree50[[#This Row],[L4]]) -> Climate-Indoor Heaters-Heating Blankets | G20: Raquel Gonzalez Rodriguez | H20: =_xlfn.XLOOKUP(CatTree50[[#This Row],[Index 5.0]],'Category List'!B:B,'Category List'!C:C,"") | I20: Done
B21: Climate | C21: Outdoor Heaters | F21: =_xlfn.TEXTJOIN("-",TRUE,CatTree50[[#This Row],[L1]],CatTree50[[#This Row],[L2]],CatTree50[[#This Row],[L3]],CatTree50[[#This Row],[L4]]) -> Climate-Outdoor Heaters | G21: Raquel Gonzalez Rodriguez | H21: =_xlfn.XLOOKUP(CatTree50[[#This Row],[Index 5.0]],'Category List'!B:B,'Category List'!C:C,"") | I21: Exclude
B22: Climate | C22: Outdoor Heaters | D22: Accessories for Outdoor Heaters | F22: =_xlfn.TEXTJOIN("-",TRUE,CatTree50[[#This Row],[L1]],CatTree50[[#This Row],[L2]],CatTree50[[#This Row],[L3]],CatTree50[[#This Row],[L4]]) -> Climate-Outdoor Heaters-Accessories for Outdoor Heaters | G22: Raquel Gonzalez Rodriguez | H22: =_xlfn.XLOOKUP(CatTree50[[#This Row],[Index 5.0]],'Category List'!B:B,'Category List'!C:C,"") | I22: Exclude
B23: Climate | C23: Outdoor Heaters | D23: Ethanol Heaters | F23: =_xlfn.TEXTJOIN("-",TRUE,CatTree50[[#This Row],[L1]],CatTree50[[#This Row],[L2]],CatTree50[[#This Row],[L3]],CatTree50[[#This Row],[L4]]) -> Climate-Outdoor Heaters-Ethanol Heaters | G23: Raquel Gonzalez Rodriguez | H23: =_xlfn.XLOOKUP(CatTree50[[#This Row],[Index 5.0]],'Category List'!B:B,'Category List'!C:C,"") | I23: Not sure
B24: Garden | F24: =_xlfn.TEXTJOIN("-",TRUE,CatTree50[[#This Row],[L1]],CatTree50[[#This Row],[L2]],CatTree50[[#This Row],[L3]],CatTree50[[#This Row],[L4]]) -> Garden | H24: =_xlfn.XLOOKUP(CatTree50[[#This Row],[Index 5.0]],'Category List'!B:B,'Category List'!C:C,"") | I24: Exclude
B25: Garden | C25: Garden Furniture | F25: =_xlfn.TEXTJOIN("-",TRUE,CatTree50[[#This Row],[L1]],CatTree50[[#This Row],[L2]],CatTree50[[#This Row],[L3]],CatTree50[[#This Row],[L4]]) -> Garden-Garden Furniture | H25: =_xlfn.XLOOKUP(CatTree50[[#This Row],[Index 5.0]],'Category List'!B:B,'Category List'!C:C,"") | I25: Exclude
B26: Garden | C26: Garden Furniture | D26: Accessories for Garden Furniture | F26: =_xlfn.TEXTJOIN("-",TRUE,CatTree50[[#This Row],[L1]],CatTree50[[#This Row],[L2]],CatTree50[[#This Row],[L3]],CatTree50[[#This Row],[L4]]) -> Garden-Garden Furniture-Accessories for Garden Furniture | H26: =_xlfn.XLOOKUP(CatTree50[[#This Row],[Index 5.0]],'Category List'!B:B,'Category List'!C:C,"") | I26: Exclude
B27: Garden | C27: Garden Furniture | D27: Garden Chairs | F27: =_xlfn.TEXTJOIN("-",TRUE,CatTree50[[#This Row],[L1]],CatTree50[[#This Row],[L2]],CatTree50[[#This Row],[L3]],CatTree50[[#This Row],[L4]]) -> Garden-Garden Furniture-Garden Chairs | H27: =_xlfn.XLOOKUP(CatTree50[[#This Row],[Index 5.0]],'Category List'!B:B,'Category List'!C:C,"") | I27: Exclude
B28: Garden | C28: Garden Furniture | D28: Garden Tables | F28: =_xlfn.TEXTJOIN("-",TRUE,CatTree50[[#This Row],[L1]],CatTree50[[#This Row],[L2]],CatTree50[[#This Row],[L3]],CatTree50[[#This Row],[L4]]) -> Garden-Garden Furniture-Garden Tables | H28: =_xlfn.XLOOKUP(CatTree50[[#This Row],[Index 5.0]],'Category List'!B:B,'Category List'!C:C,"") | I28: Exclude
B29: Garden | C29: Garden Furniture | D29: Loungers | F29: =_xlfn.TEXTJOIN("-",TRUE,CatTree50[[#This Row],[L1]],CatTree50[[#This Row],[L2]],CatTree50[[#This Row],[L3]],CatTree50[[#This Row],[L4]]) -> Garden-Garden Furniture-Loungers | H29: =_xlfn.XLOOKUP(CatTree50[[#This Row],[Index 5.0]],'Category List'!B:B,'Category List'!C:C,"") | I29: Exclude
B30: Garden | C30: Garden Furniture | D30: Seating Sets | F30: =_xlfn.TEXTJOIN("-",TRUE,CatTree50[[#This Row],[L1]],CatTree50[[#This Row],[L2]],CatTree50[[#This Row],[L3]],CatTree50[[#This Row],[L4]]) -> Garden-Garden Furniture-Seating Sets | H30: =_xlfn.XLOOKUP(CatTree50[[#This Row],[Index 5.0]],'Category List'!B:B,'Category List'!C:C,"") | I30: Exclude
B31: Garden | C31: Garden Furniture | D31: Sunbeds | F31: =_xlfn.TEXTJOIN("-",TRUE,CatTree50[[#This Row],[L1]],CatTree50[[#This Row],[L2]],CatTree50[[#This Row],[L3]],CatTree50[[#This Row],[L4]]) -> Garden-Garden Furniture-Sunbeds | H31: =_xlfn.XLOOKUP(CatTree50[[#This Row],[Index 5.0]],'Category List'!B:B,'Category List'!C:C,"") | I31: Exclude
B32: Garden | C32: Garden Furniture | D32: Swings | F32: =_xlfn.TEXTJOIN("-",TRUE,CatTree50[[#This Row],[L1]],CatTree50[[#This Row],[L2]],CatTree50[[#This Row],[L3]],CatTree50[[#This Row],[L4]]) -> Garden-Garden Furniture-Swings | H32: =_xlfn.XLOOKUP(CatTree50[[#This Row],[Index 5.0]],'Category List'!B:B,'Category List'!C:C,"") | I32: Exclude
B33: Garden | C33: Garden Structures & Shade | F33: =_xlfn.TEXTJOIN("-",TRUE,CatTree50[[#This Row],[L1]],CatTree50[[#This Row],[L2]],CatTree50[[#This Row],[L3]],CatTree50[[#This Row],[L4]]) -> Garden-Garden Structures & Shade | H33: =_xlfn.XLOOKUP(CatTree50[[#This Row],[Index 5.0]],'Category List'!B:B,'Category List'!C:C,"") | I33: Exclude
B34: Garden | C34: Garden Structures & Shade | D34: Awnings | F34: =_xlfn.TEXTJOIN("-",TRUE,CatTree50[[#This Row],[L1]],CatTree50[[#This Row],[L2]],CatTree50[[#This Row],[L3]],CatTree50[[#This Row],[L4]]) -> Garden-Garden Structures & Shade-Awnings | H34: =_xlfn.XLOOKUP(CatTree50[[#This Row],[Index 5.0]],'Category List'!B:B,'Category List'!C:C,"") | I34: Exclude
B35: Garden | C35: Garden Structures & Shade | D35: Gazebos | F35: =_xlfn.TEXTJOIN("-",TRUE,CatTree50[[#This Row],[L1]],CatTree50[[#This Row],[L2]],CatTree50[[#This Row],[L3]],CatTree50[[#This Row],[L4]]) -> Garden-Garden Structures & Shade-Gazebos | H35: =_xlfn.XLOOKUP(CatTree50[[#This Row],[Index 5.0]],'Category List'!B:B,'Category List'!C:C,"") | I35: Exclude
B36: Garden | C36: Garden Structures & Shade | D36: Privacy Screens | F36: =_xlfn.TEXTJOIN("-",TRUE,CatTree50[[#This Row],[L1]],CatTree50[[#This Row],[L2]],CatTree50[[#This Row],[L3]],CatTree50[[#This Row],[L4]]) -> Garden-Garden Structures & Shade-Privacy Screens | H36: =_xlfn.XLOOKUP(CatTree50[[#This Row],[Index 5.0]],'Category List'!B:B,'Category List'!C:C,"") | I36: Exclude
B37: Garden | C37: Garden Structures & Shade | D37: Umbrellas | F37: =_xlfn.TEXTJOIN("-",TRUE,CatTree50[[#This Row],[L1]],CatTree50[[#This Row],[L2]],CatTree50[[#This Row],[L3]],CatTree50[[#This Row],[L4]]) -> Garden-Garden Structures & Shade-Umbrellas | H37: =_xlfn.XLOOKUP(CatTree50[[#This Row],[Index 5.0]],'Category List'!B:B,'Category List'!C:C,"") | I37: Exclude
B38: Garden | C38: Garden Utilities | F38: =_xlfn.TEXTJOIN("-",TRUE,CatTree50[[#This Row],[L1]],CatTree50[[#This Row],[L2]],CatTree50[[#This Row],[L3]],CatTree50[[#This Row],[L4]]) -> Garden-Garden Utilities | H38: =_xlfn.XLOOKUP(CatTree50[[#This Row],[Index 5.0]],'Category List'!B:B,'Category List'!C:C,"") | I38: Exclude
B39: Garden | C39: Garden Utilities | D39: Breeding Supplies | F39: =_xlfn.TEXTJOIN("-",TRUE,CatTree50[[#This Row],[L1]],CatTree50[[#This Row],[L2]],CatTree50[[#This Row],[L3]],CatTree50[[#This Row],[L4]]) -> Garden-Garden Utilities-Breeding Supplies | H39: =_xlfn.XLOOKUP(CatTree50[[#This Row],[Index 5.0]],'Category List'!B:B,'Category List'!C:C,"") | I39: Exclude
B40: Garden | C40: Garden Utilities | D40: Decorations | F40: =_xlfn.TEXTJOIN("-",TRUE,CatTree50[[#This Row],[L1]],CatTree50[[#This Row],[L2]],CatTree50[[#This Row],[L3]],CatTree50[[#This Row],[L4]]) -> Garden-Garden Utilities-Decorations | H40: =_xlfn.XLOOKUP(CatTree50[[#This Row],[Index 5.0]],'Category List'!B:B,'Category List'!C:C,"") | I40: Exclude
B41: Garden | C41: Garden Utilities | D41: Firewood Stands | F41: =_xlfn.TEXTJOIN("-",TRUE,CatTree50[[#This Row],[L1]],CatTree50[[#This Row],[L2]],CatTree50[[#This Row],[L3]],CatTree50[[#This Row],[L4]]) -> Garden-Garden Utilities-Firewood Stands | G41: Klaudia Weronika Kolodziej | H41: =_xlfn.XLOOKUP(CatTree50[[#This Row],[Index 5.0]],'Category List'!B:B,'Category List'!C:C,"") | I41: Exclude
B42: Garden | C42: Garden Utilities | D42: Fountains | F42: =_xlfn.TEXTJOIN("-",TRUE,CatTree50[[#This Row],[L1]],CatTree50[[#This Row],[L2]],CatTree50[[#This Row],[L3]],CatTree50[[#This Row],[L4]]) -> Garden-Garden Utilities-Fountains | H42: =_xlfn.XLOOKUP(CatTree50[[#This Row],[Index 5.0]],'Category List'!B:B,'Category List'!C:C,"") | I42: Exclude
B43: Garden | C43: Garden Utilities | D43: Garden Showers | F43: =_xlfn.TEXTJOIN("-",TRUE,CatTree50[[#This Row],[L1]],CatTree50[[#This Row],[L2]],CatTree50[[#This Row],[L3]],CatTree50[[#This Row],[L4]]) -> Garden-Garden Utilities-Garden Showers | H43: =_xlfn.XLOOKUP(CatTree50[[#This Row],[Index 5.0]],'Category List'!B:B,'Category List'!C:C,"") | I43: Exclude
B44: Garden | C44: Garden Utilities | D44: Insect Traps | F44: =_xlfn.TEXTJOIN("-",TRUE,CatTree50[[#This Row],[L1]],CatTree50[[#This Row],[L2]],CatTree50[[#This Row],[L3]],CatTree50[[#This Row],[L4]]) -> Garden-Garden Utilities-Insect Traps | H44: =_xlfn.XLOOKUP(CatTree50[[#This Row],[Index 5.0]],'Category List'!B:B,'Category List'!C:C,"") | I44: Exclude
B45: Garden | C45: Garden Utilities | D45: Metal Detectors | F45: =_xlfn.TEXTJOIN("-",TRUE,CatTree50[[#This Row],[L1]],CatTree50[[#This Row],[L2]],CatTree50[[#This Row],[L3]],CatTree50[[#This Row],[L4]]) -> Garden-Garden Utilities-Metal Detectors | H45: =_xlfn.XLOOKUP(CatTree50[[#This Row],[Index 5.0]],'Category List'!B:B,'Category List'!C:C,"") | I45: Exclude
B46: Garden | C46: Gardening & Equipment | F46: =_xlfn.TEXTJOIN("-",TRUE,CatTree50[[#This Row],[L1]],CatTree50[[#This Row],[L2]],CatTree50[[#This Row],[L3]],CatTree50[[#This Row],[L4]]) -> Garden-Gardening & Equipment | H46: =_xlfn.XLOOKUP(CatTree50[[#This Row],[Index 5.0]],'Category List'!B:B,'Category List'!C:C,"") | I46: Exclude
B47: Garden | C47: Gardening & Equipment | D47: Heating Cables | F47: =_xlfn.TEXTJOIN("-",TRUE,CatTree50[[#This Row],[L1]],CatTree50[[#This Row],[L2]],CatTree50[[#This Row],[L3]],CatTree50[[#This Row],[L4]]) -> Garden-Gardening & Equipment-Heating Cables | H47: =_xlfn.XLOOKUP(CatTree50[[#This Row],[Index 5.0]],'Category List'!B:B,'Category List'!C:C,"") | I47: Exclude
B48: Garden | C48: Gardening & Equipment | D48: Metal Detectors | F48: =_xlfn.TEXTJOIN("-",TRUE,CatTree50[[#This Row],[L1]],CatTree50[[#This Row],[L2]],CatTree50[[#This Row],[L3]],CatTree50[[#This Row],[L4]]) -> Garden-Gardening & Equipment-Metal Detectors | H48: =_xlfn.XLOOKUP(CatTree50[[#This Row],[Index 5.0]],'Category List'!B:B,'Category List'!C:C,"") | I48: Exclude
B49: Garden | C49: Gardening & Equipment | D49: Pond Technologies | F49: =_xlfn.TEXTJOIN("-",TRUE,CatTree50[[#This Row],[L1]],CatTree50[[#This Row],[L2]],CatTree50[[#This Row],[L3]],CatTree50[[#This Row],[L4]]) -> Garden-Gardening & Equipment-Pond Technologies | H49: =_xlfn.XLOOKUP(CatTree50[[#This Row],[Index 5.0]],'Category List'!B:B,'Category List'!C:C,"") | I49: Exclude
B50: Garden | C50: Gardening & Equipment | D50: Robotic Lawn Mowers | F50: =_xlfn.TEXTJOIN("-",TRUE,CatTree50[[#This Row],[L1]],CatTree50[[#This Row],[L2]],CatTree50[[#This Row],[L3]],CatTree50[[#This Row],[L4]]) -> Garden-Gardening & Equipment-Robotic Lawn Mowers | H50: =_xlfn.XLOOKUP(CatTree50[[#This Row],[Index 5.0]],'Category List'!B:B,'Category List'!C:C,"") | I50: Exclude
B51: Garden | C51: Gardening & Equipment | D51: Wheelbarrows & Carts | F51: =_xlfn.TEXTJOIN("-",TRUE,CatTree50[[#This Row],[L1]],CatTree50[[#This Row],[L2]],CatTree50[[#This Row],[L3]],CatTree50[[#This Row],[L4]]) -> Garden-Gardening & Equipment-Wheelbarrows & Carts | H51: =_xlfn.XLOOKUP(CatTree50[[#This Row],[Index 5.0]],'Category List'!B:B,'Category List'!C:C,"") | I51: Exclude
B52: Garden | C52: Grills | F52: =_xlfn.TEXTJOIN("-",TRUE,CatTree50[[#This Row],[L1]],CatTree50[[#This Row],[L2]],CatTree50[[#This Row],[L3]],CatTree50[[#This Row],[L4]]) -> Garden-Grills | G52: Klaudia Weronika Kolodziej | H52: =_xlfn.XLOOKUP(CatTree50[[#This Row],[Index 5.0]],'Category List'!B:B,'Category List'!C:C,"") | I52: Exclude
B53: Garden | C53: Grills | D53: Accessories for Grills | F53: =_xlfn.TEXTJOIN("-",TRUE,CatTree50[[#This Row],[L1]],CatTree50[[#This Row],[L2]],CatTree50[[#This Row],[L3]],CatTree50[[#This Row],[L4]]) -> Garden-Grills-Accessories for Grills | G53: Klaudia Weronika Kolodziej | H53: =_xlfn.XLOOKUP(CatTree50[[#This Row],[Index 5.0]],'Category List'!B:B,'Category List'!C:C,"") | I53: Exclude
B54: Garden | C54: Grills | D54: Cast Iron Pots | F54: =_xlfn.TEXTJOIN("-",TRUE,CatTree50[[#This Row],[L1]],CatTree50[[#This Row],[L2]],CatTree50[[#This Row],[L3]],CatTree50[[#This Row],[L4]]) -> Garden-Grills-Cast Iron Pots | G54: Klaudia Weronika Kolodziej | H54: =_xlfn.XLOOKUP(CatTree50[[#This Row],[Index 5.0]],'Category List'!B:B,'Category List'!C:C,"") | I54: Exclude
B55: Garden | C55: Grills | D55: Combined Grills | F55: =_xlfn.TEXTJOIN("-",TRUE,CatTree50[[#This Row],[L1]],CatTree50[[#This Row],[L2]],CatTree50[[#This Row],[L3]],CatTree50[[#This Row],[L4]]) -> Garden-Grills-Combined Grills | G55: Klaudia Weronika Kolodziej | H55: =_xlfn.XLOOKUP(CatTree50[[#This Row],[Index 5.0]],'Category List'!B:B,'Category List'!C:C,"") | I55: Exclude
B56: Garden | C56: oldGarden Tools | E56: oldRobot Mower | F56: =_xlfn.TEXTJOIN("-",TRUE,CatTree50[[#This Row],[L1]],CatTree50[[#This Row],[L2]],CatTree50[[#This Row],[L3]],CatTree50[[#This Row],[L4]]) -> Garden-oldGarden Tools-oldRobot Mower | H56: =_xlfn.XLOOKUP(CatTree50[[#This Row],[Index 5.0]],'Category List'!B:B,'Category List'!C:C,"") | I56: Exclude
B57: Large Appliances | F57: =_xlfn.TEXTJOIN("-",TRUE,CatTree50[[#This Row],[L1]],CatTree50[[#This Row],[L2]],CatTree50[[#This Row],[L3]],CatTree50[[#This Row],[L4]]) -> Large Appliances | H57: =_xlfn.XLOOKUP(CatTree50[[#This Row],[Index 5.0]],'Category List'!B:B,'Category List'!C:C,"") | I57: Exclude
B58: Large Appliances | C58: Appliance Sets | F58: =_xlfn.TEXTJOIN("-",TRUE,CatTree50[[#This Row],[L1]],CatTree50[[#This Row],[L2]],CatTree50[[#This Row],[L3]],CatTree50[[#This Row],[L4]]) -> Large Appliances-Appliance Sets | G58: Berkay Ağirkol | H58: =_xlfn.XLOOKUP(CatTree50[[#This Row],[Index 5.0]],'Category List'!B:B,'Category List'!C:C,"") | I58: Exclude
B59: Large Appliances | C59: Dishwashers | F59: =_xlfn.TEXTJOIN("-",TRUE,CatTree50[[#This Row],[L1]],CatTree50[[#This Row],[L2]],CatTree50[[#This Row],[L3]],CatTree50[[#This Row],[L4]]) -> Large Appliances-Dishwashers | G59: Özge Gönüllü | H59: =_xlfn.XLOOKUP(CatTree50[[#This Row],[Index 5.0]],'Category List'!B:B,'Category List'!C:C,"") | I59: Done
B60: Large Appliances | C60: Dishwashers | D60: Accessories for Dishwashers | F60: =_xlfn.TEXTJOIN("-",TRUE,CatTree50[[#This Row],[L1]],CatTree50[[#This Row],[L2]],CatTree50[[#This Row],[L3]],CatTree50[[#This Row],[L4]]) -> Large Appliances-Dishwashers-Accessories for Dishwashers | G60: Özge Gönüllü | H60: =_xlfn.XLOOKUP(CatTree50[[#This Row],[Index 5.0]],'Category List'!B:B,'Category List'!C:C,"") | I60: Exclude
B61: Large Appliances | C61: Freezers | F61: =_xlfn.TEXTJOIN("-",TRUE,CatTree50[[#This Row],[L1]],CatTree50[[#This Row],[L2]],CatTree50[[#This Row],[L3]],CatTree50[[#This Row],[L4]]) -> Large Appliances-Freezers | G61: Özge Gönüllü | H61: =_xlfn.XLOOKUP(CatTree50[[#This Row],[Index 5.0]],'Category List'!B:B,'Category List'!C:C,"") | I61: Done
B62: Large Appliances | C62: Freezers | D62: Freestanding Freezers | F62: =_xlfn.TEXTJOIN("-",TRUE,CatTree50[[#This Row],[L1]],CatTree50[[#This Row],[L2]],CatTree50[[#This Row],[L3]],CatTree50[[#This Row],[L4]]) -> Large Appliances-Freezers-Freestanding Freezers | G62: Özge Gönüllü | H62: =_xlfn.XLOOKUP(CatTree50[[#This Row],[Index 5.0]],'Category List'!B:B,'Category List'!C:C,"") | I62: Done
B63: Large Appliances | C63: Hobs | F63: =_xlfn.TEXTJOIN("-",TRUE,CatTree50[[#This Row],[L1]],CatTree50[[#This Row],[L2]],CatTree50[[#This Row],[L3]],CatTree50[[#This Row],[L4]]) -> Large Appliances-Hobs | G63: Berkay Ağirkol | H63: =_xlfn.XLOOKUP(CatTree50[[#This Row],[Index 5.0]],'Category List'!B:B,'Category List'!C:C,"") | I63: Exclude
B64: Large Appliances | C64: Hobs | D64: Combination Hobs | F64: =_xlfn.TEXTJOIN("-",TRUE,CatTree50[[#This Row],[L1]],CatTree50[[#This Row],[L2]],CatTree50[[#This Row],[L3]],CatTree50[[#This Row],[L4]]) -> Large Appliances-Hobs-Combination Hobs | G64: Berkay Ağirkol | H64: =_xlfn.XLOOKUP(CatTree50[[#This Row],[Index 5.0]],'Category List'!B:B,'Category List'!C:C,"") | I64: Done
B65: Large Appliances | C65: Hobs | D65: Tabletop Hobs | F65: =_xlfn.TEXTJOIN("-",TRUE,CatTree50[[#This Row],[L1]],CatTree50[[#This Row],[L2]],CatTree50[[#This Row],[L3]],CatTree50[[#This Row],[L4]]) -> Large Appliances-Hobs-Tabletop Hobs | G65: Berkay Ağirkol | H65: =_xlfn.XLOOKUP(CatTree50[[#This Row],[Index 5.0]],'Category List'!B:B,'Category List'!C:C,"") | I65: Done
B66: Large Appliances | C66: Humidors | F66: =_xlfn.TEXTJOIN("-",TRUE,CatTree50[[#This Row],[L1]],CatTree50[[#This Row],[L2]],CatTree50[[#This Row],[L3]],CatTree50[[#This Row],[L4]]) -> Large Appliances-Humidors | G66: Özge Gönüllü | H66: =_xlfn.XLOOKUP(CatTree50[[#This Row],[Index 5.0]],'Category List'!B:B,'Category List'!C:C,"") -> Humidors - Attributes V3.0.xlsx
B67: Large Appliances | C67: Humidors | E67: oldChimney Wall Hoods | F67: =_xlfn.TEXTJOIN("-",TRUE,CatTree50[[#This Row],[L1]],CatTree50[[#This Row],[L2]],CatTree50[[#This Row],[L3]],CatTree50[[#This Row],[L4]]) -> Large Appliances-Humidors-oldChimney Wall Hoods | G67: Özge Gönüllü | H67: =_xlfn.XLOOKUP(CatTree50[[#This Row],[Index 5.0]],'Category List'!B:B,'Category List'!C:C,"") | I67: Exclude
B68: Large Appliances | C68: Microwave Ovens | F68: =_xlfn.TEXTJOIN("-",TRUE,CatTree50[[#This Row],[L1]],CatTree50[[#This Row],[L2]],CatTree50[[#This Row],[L3]],CatTree50[[#This Row],[L4]]) -> Large Appliances-Microwave Ovens | G68: Berkay Ağirkol | H68: =_xlfn.XLOOKUP(CatTree50[[#This Row],[Index 5.0]],'Category List'!B:B,'Category List'!C:C,"") | I68: Exclude
B69: Large Appliances | C69: Microwave Ovens | D69: Built-In Microwave Ovens | F69: =_xlfn.TEXTJOIN("-",TRUE,CatTree50[[#This Row],[L1]],CatTree50[[#This Row],[L2]],CatTree50[[#This Row],[L3]],CatTree50[[#This Row],[L4]]) -> Large Appliances-Microwave Ovens-Built-In Microwave Ovens | G69: Berkay Ağirkol | H69: =_xlfn.XLOOKUP(CatTree50[[#This Row],[Index 5.0]],'Category List'!B:B,'Category List'!C:C,"") | I69: Done
B70: Large Appliances | C70: Microwave Ovens | D70: Freestanding Microwave Ovens | F70: =_xlfn.TEXTJOIN("-",TRUE,CatTree50[[#This Row],[L1]],CatTree50[[#This Row],[L2]],CatTree50[[#This Row],[L3]],CatTree50[[#This Row],[L4]]) -> Large Appliances-Microwave Ovens-Freestanding Microwave Ovens | G70: Berkay Ağirkol | H70: =_xlfn.XLOOKUP(CatTree50[[#This Row],[Index 5.0]],'Category List'!B:B,'Category List'!C:C,"") | I70: Done
B71: Large Appliances | C71: oldCookers & Ovens | E71: oldInstalled Ovens | F71: =_xlfn.TEXTJOIN("-",TRUE,CatTree50[[#This Row],[L1]],CatTree50[[#This Row],[L2]],CatTree50[[#This Row],[L3]],CatTree50[[#This Row],[L4]]) -> Large Appliances-oldCookers & Ovens-oldInstalled Ovens | H71: =_xlfn.XLOOKUP(CatTree50[[#This Row],[Index 5.0]],'Category List'!B:B,'Category List'!C:C,"") | I71: Exclude
B72: Large Appliances | C72: oldFridges & Freezers | E72: oldBeverage Cooler | F72: =_xlfn.TEXTJOIN("-",TRUE,CatTree50[[#This Row],[L1]],CatTree50[[#This Row],[L2]],CatTree50[[#This Row],[L3]],CatTree50[[#This Row],[L4]]) -> Large Appliances-oldFridges & Freezers-oldBeverage Cooler | H72: =_xlfn.XLOOKUP(CatTree50[[#This Row],[Index 5.0]],'Category List'!B:B,'Category List'!C:C,"") | I72: Exclude
B73: Large Appliances | C73: oldFridges & Freezers | E73: oldFreezers | F73: =_xlfn.TEXTJOIN("-",TRUE,CatTree50[[#This Row],[L1]],CatTree50[[#This Row],[L2]],CatTree50[[#This Row],[L3]],CatTree50[[#This Row],[L4]]) -> Large Appliances-oldFridges & Freezers-oldFreezers | H73: =_xlfn.XLOOKUP(CatTree50[[#This Row],[Index 5.0]],'Category List'!B:B,'Category List'!C:C,"") | I73: Exclude
B74: Large Appliances | C74: oldFridges & Freezers | E74: oldFridges | F74: =_xlfn.TEXTJOIN("-",TRUE,CatTree50[[#This Row],[L1]],CatTree50[[#This Row],[L2]],CatTree50[[#This Row],[L3]],CatTree50[[#This Row],[L4]]) -> Large Appliances-oldFridges & Freezers-oldFridges | H74: =_xlfn.XLOOKUP(CatTree50[[#This Row],[Index 5.0]],'Category List'!B:B,'Category List'!C:C,"") | I74: Exclude
B75: Large Appliances | C75: oldFridges & Freezers | E75: oldWine Fridge | F75: =_xlfn.TEXTJOIN("-",TRUE,CatTree50[[#This Row],[L1]],CatTree50[[#This Row],[L2]],CatTree50[[#This Row],[L3]],CatTree50[[#This Row],[L4]]) -> Large Appliances-oldFridges & Freezers-oldWine Fridge | H75: =_xlfn.XLOOKUP(CatTree50[[#This Row],[Index 5.0]],'Category List'!B:B,'Category List'!C:C,"") | I75: Exclude
B76: Large Appliances | C76: Ovens | F76: =_xlfn.TEXTJOIN("-",TRUE,CatTree50[[#This Row],[L1]],CatTree50[[#This Row],[L2]],CatTree50[[#This Row],[L3]],CatTree50[[#This Row],[L4]]) -> Large Appliances-Ovens | G76: Berkay Ağirkol | H76: =_xlfn.XLOOKUP(CatTree50[[#This Row],[Index 5.0]],'Category List'!B:B,'Category List'!C:C,"") | I76: Done
B77: Large Appliances | C77: Ovens | D77: Freestanding Ovens | F77: =_xlfn.TEXTJOIN("-",TRUE,CatTree50[[#This Row],[L1]],CatTree50[[#This Row],[L2]],CatTree50[[#This Row],[L3]],CatTree50[[#This Row],[L4]]) -> Large Appliances-Ovens-Freestanding Ovens | G77: Berkay Ağirkol | H77: =_xlfn.XLOOKUP(CatTree50[[#This Row],[Index 5.0]],'Category List'!B:B,'Category List'!C:C,"") | I77: Done
B78: Large Appliances | C78: Range Hoods | F78: =_xlfn.TEXTJOIN("-",TRUE,CatTree50[[#This Row],[L1]],CatTree50[[#This Row],[L2]],CatTree50[[#This Row],[L3]],CatTree50[[#This Row],[L4]]) -> Large Appliances-Range Hoods | G78: Berkay Ağirkol | H78: =_xlfn.XLOOKUP(CatTree50[[#This Row],[Index 5.0]],'Category List'!B:B,'Category List'!C:C,"") | I78: Exclude
B79: Large Appliances | C79: Range Hoods | D79: Accessories for Range Hoods | F79: =_xlfn.TEXTJOIN("-",TRUE,CatTree50[[#This Row],[L1]],CatTree50[[#This Row],[L2]],CatTree50[[#This Row],[L3]],CatTree50[[#This Row],[L4]]) -> Large Appliances-Range Hoods-Accessories for Range Hoods | G79: Berkay Ağirkol | H79: =_xlfn.XLOOKUP(CatTree50[[#This Row],[Index 5.0]],'Category List'!B:B,'Category List'!C:C,"") | I79: Exclude
B80: Large Appliances | C80: Range Hoods | D80: Ceilling Hoods | F80: =_xlfn.TEXTJOIN("-",TRUE,CatTree50[[#This Row],[L1]],CatTree50[[#This Row],[L2]],CatTree50[[#This Row],[L3]],CatTree50[[#This Row],[L4]]) -> Large Appliances-Range Hoods-Ceilling Hoods | G80: Berkay Ağirkol | H80: =_xlfn.XLOOKUP(CatTree50[[#This Row],[Index 5.0]],'Category List'!B:B,'Category List'!C:C,"") | I80: Done
B81: Audio | F81: =_xlfn.TEXTJOIN("-",TRUE,CatTree50[[#This Row],[L1]],CatTree50[[#This Row],[L2]],CatTree50[[#This Row],[L3]],CatTree50[[#This Row],[L4]]) -> Audio | H81: =_xlfn.XLOOKUP(CatTree50[[#This Row],[Index 5.0]],'Category List'!B:B,'Category List'!C:C,"")
B82: Audio | C82: Av & Lighting | F82: =_xlfn.TEXTJOIN("-",TRUE,CatTree50[[#This Row],[L1]],CatTree50[[#This Row],[L2]],CatTree50[[#This Row],[L3]],CatTree50[[#This Row],[L4]]) -> Audio-Av & Lighting | H82: =_xlfn.XLOOKUP(CatTree50[[#This Row],[Index 5.0]],'Category List'!B:B,'Category List'!C:C,"")
B83: Audio | C83: Av & Lighting | D83: DMX Controllers | F83: =_xlfn.TEXTJOIN("-",TRUE,CatTree50[[#This Row],[L1]],CatTree50[[#This Row],[L2]],CatTree50[[#This Row],[L3]],CatTree50[[#This Row],[L4]]) -> Audio-Av & Lighting-DMX Controllers | H83: =_xlfn.XLOOKUP(CatTree50[[#This Row],[Index 5.0]],'Category List'!B:B,'Category List'!C:C,"")
B84: Audio | C84: Av & Lighting | D84: Projection Technologies | F84: =_xlfn.TEXTJOIN("-",TRUE,CatTree50[[#This Row],[L1]],CatTree50[[#This Row],[L2]],CatTree50[[#This Row],[L3]],CatTree50[[#This Row],[L4]]) -> Audio-Av & Lighting-Projection Technologies | H84: =_xlfn.XLOOKUP(CatTree50[[#This Row],[Index 5.0]],'Category List'!B:B,'Category List'!C:C,"")
B85: Audio | C85: Av & Lighting | D85: Smart Lights | F85: =_xlfn.TEXTJOIN("-",TRUE,CatTree50[[#This Row],[L1]],CatTree50[[#This Row],[L2]],CatTree50[[#This Row],[L3]],CatTree50[[#This Row],[L4]]) -> Audio-Av & Lighting-Smart Lights | H85: =_xlfn.XLOOKUP(CatTree50[[#This Row],[Index 5.0]],'Category List'!B:B,'Category List'!C:C,"")
B86: Audio | C86: Cables & Accessories | F86: =_xlfn.TEXTJOIN("-",TRUE,CatTree50[[#This Row],[L1]],CatTree50[[#This Row],[L2]],CatTree50[[#This Row],[L3]],CatTree50[[#This Row],[L4]]) -> Audio-Cables & Accessories | H86: =_xlfn.XLOOKUP(CatTree50[[#This Row],[Index 5.0]],'Category List'!B:B,'Category List'!C:C,"")
B87: Audio | C87: Cables & Accessories | D87: Cable Passages | F87: =_xlfn.TEXTJOIN("-",TRUE,CatTree50[[#This Row],[L1]],CatTree50[[#This Row],[L2]],CatTree50[[#This Row],[L3]],CatTree50[[#This Row],[L4]]) -> Audio-Cables & Accessories-Cable Passages | H87: =_xlfn.XLOOKUP(CatTree50[[#This Row],[Index 5.0]],'Category List'!B:B,'Category List'!C:C,"")
B88: Audio | C88: Cables & Accessories | D88: Dvi Cables | F88: =_xlfn.TEXTJOIN("-",TRUE,CatTree50[[#This Row],[L1]],CatTree50[[#This Row],[L2]],CatTree50[[#This Row],[L3]],CatTree50[[#This Row],[L4]]) -> Audio-Cables & Accessories-Dvi Cables | H88: =_xlfn.XLOOKUP(CatTree50[[#This Row],[Index 5.0]],'Category List'!B:B,'Category List'!C:C,"")
B89: Audio | C89: Cables & Accessories | D89: Jack Cables | F89: =_xlfn.TEXTJOIN("-",TRUE,CatTree50[[#This Row],[L1]],CatTree50[[#This Row],[L2]],CatTree50[[#This Row],[L3]],CatTree50[[#This Row],[L4]]) -> Audio-Cables & Accessories-Jack Cables | H89: =_xlfn.XLOOKUP(CatTree50[[#This Row],[Index 5.0]],'Category List'!B:B,'Category List'!C:C,"")
B90: Audio | C90: Cables & Accessories | D90: Reductions | F90: =_xlfn.TEXTJOIN("-",TRUE,CatTree50[[#This Row],[L1]],CatTree50[[#This Row],[L2]],CatTree50[[#This Row],[L3]],CatTree50[[#This Row],[L4]]) -> Audio-Cables & Accessories-Reductions | H90: =_xlfn.XLOOKUP(CatTree50[[#This Row],[Index 5.0]],'Category List'!B:B,'Category List'!C:C,"")
B91: Audio | C91: Cables & Accessories | D91: Speakon Cables | F91: =_xlfn.TEXTJOIN("-",TRUE,CatTree50[[#This Row],[L1]],CatTree50[[#This Row],[L2]],CatTree50[[#This Row],[L3]],CatTree50[[#This Row],[L4]]) -> Audio-Cables & Accessories-Speakon Cables | H91: =_xlfn.XLOOKUP(CatTree50[[#This Row],[Index 5.0]],'Category List'!B:B,'Category List'!C:C,"")
B92: Audio | C92: Cables & Accessories | D92: Xlr Cables | F92: =_xlfn.TEXTJOIN("-",TRUE,CatTree50[[#This Row],[L1]],CatTree50[[#This Row],[L2]],CatTree50[[#This Row],[L3]],CatTree50[[#This Row],[L4]]) -> Audio-Cables & Accessories-Xlr Cables | H92: =_xlfn.XLOOKUP(CatTree50[[#This Row],[Index 5.0]],'Category List'!B:B,'Category List'!C:C,"")
B93: Audio | C93: DJ Equipment | F93: =_xlfn.TEXTJOIN("-",TRUE,CatTree50[[#This Row],[L1]],CatTree50[[#This Row],[L2]],CatTree50[[#This Row],[L3]],CatTree50[[#This Row],[L4]]) -> Audio-DJ Equipment | H93: =_xlfn.XLOOKUP(CatTree50[[#This Row],[Index 5.0]],'Category List'!B:B,'Category List'!C:C,"")
B94: Audio | C94: DJ Mixing Consoles | F94: =_xlfn.TEXTJOIN("-",TRUE,CatTree50[[#This Row],[L1]],CatTree50[[#This Row],[L2]],CatTree50[[#This Row],[L3]],CatTree50[[#This Row],[L4]]) -> Audio-DJ Mixing Consoles | H94: =_xlfn.XLOOKUP(CatTree50[[#This Row],[Index 5.0]],'Category List'!B:B,'Category List'!C:C,"")
B95: Audio | C95: Hifi Systems & Components | F95: =_xlfn.TEXTJOIN("-",TRUE,CatTree50[[#This Row],[L1]],CatTree50[[#This Row],[L2]],CatTree50[[#This Row],[L3]],CatTree50[[#This Row],[L4]]) -> Audio-Hifi Systems & Components | H95: =_xlfn.XLOOKUP(CatTree50[[#This Row],[Index 5.0]],'Category List'!B:B,'Category List'!C:C,"")
B96: Audio | C96: Hifi Systems & Components | D96: Hifi Amplifiers | F96: =_xlfn.TEXTJOIN("-",TRUE,CatTree50[[#This Row],[L1]],CatTree50[[#This Row],[L2]],CatTree50[[#This Row],[L3]],CatTree50[[#This Row],[L4]]) -> Audio-Hifi Systems & Components-Hifi Amplifiers | H96: =_xlfn.XLOOKUP(CatTree50[[#This Row],[Index 5.0]],'Category List'!B:B,'Category List'!C:C,"")
B97: Audio | C97: Hifi Systems & Components | D97: Hifi Cd Players | F97: =_xlfn.TEXTJOIN("-",TRUE,CatTree50[[#This Row],[L1]],CatTree50[[#This Row],[L2]],CatTree50[[#This Row],[L3]],CatTree50[[#This Row],[L4]]) -> Audio-Hifi Systems & Components-Hifi Cd Players | H97: =_xlfn.XLOOKUP(CatTree50[[#This Row],[Index 5.0]],'Category List'!B:B,'Category List'!C:C,"")
B98: Audio | C98: Hifi Systems & Components | D98: Hifi Systems | F98: =_xlfn.TEXTJOIN("-",TRUE,CatTree50[[#This Row],[L1]],CatTree50[[#This Row],[L2]],CatTree50[[#This Row],[L3]],CatTree50[[#This Row],[L4]]) -> Audio-Hifi Systems & Components-Hifi Systems | H98: =_xlfn.XLOOKUP(CatTree50[[#This Row],[Index 5.0]],'Category List'!B:B,'Category List'!C:C,"")
B99: Audio | C99: Hifi Systems & Components | D99: Turntables | F99: =_xlfn.TEXTJOIN("-",TRUE,CatTree50[[#This Row],[L1]],CatTree50[[#This Row],[L2]],CatTree50[[#This Row],[L3]],CatTree50[[#This Row],[L4]]) -> Audio-Hifi Systems & Components-Turntables | H99: =_xlfn.XLOOKUP(CatTree50[[#This Row],[Index 5.0]],'Category List'!B:B,'Category List'!C:C,"")
B100: Audio | C100: Hifi Systems & Components | D100: Turntables | E100: USB Turntables | F100: =_xlfn.TEXTJOIN("-",TRUE,CatTree50[[#This Row],[L1]],CatTree50[[#This Row],[L2]],CatTree50[[#This Row],[L3]],CatTree50[[#This Row],[L4]]) -> Audio-Hifi Systems & Components-Turntables-USB Turntables | H100: =_xlfn.XLOOKUP(CatTree50[[#This Row],[Index 5.0]],'Category List'!B:B,'Category List'!C:C,"")
B101: Audio | C101: Hifi Systems & Components | D101: Turntables | E101: Vinyl Turntables | F101: =_xlfn.TEXTJOIN("-",TRUE,CatTree50[[#This Row],[L1]],CatTree50[[#This Row],[L2]],CatTree50[[#This Row],[L3]],CatTree50[[#This Row],[L4]]) -> Audio-Hifi Systems & Components-Turntables-Vinyl Turntables | H101: =_xlfn.XLOOKUP(CatTree50[[#This Row],[Index 5.0]],'Category List'!B:B,'Category List'!C:C,"")
B102: Audio | C102: Home Theaters | F102: =_xlfn.TEXTJOIN("-",TRUE,CatTree50[[#This Row],[L1]],CatTree50[[#This Row],[L2]],CatTree50[[#This Row],[L3]],CatTree50[[#This Row],[L4]]) -> Audio-Home Theaters | H102: =_xlfn.XLOOKUP(CatTree50[[#This Row],[Index 5.0]],'Category List'!B:B,'Category List'!C:C,"")
...

Sheet Briefing
A1: Project ID | B1: Index 3.0 | C1: Column4 | D1: Image 1 | E1: Image 2 | F1: Image 3 | G1: Image 4 | H1: Image 5 | I1: Image 6 | J1: Image 7 | K1: Image 8 | L1: Image 9 | M1: Image 10
A2: MDA25065 | B2: Large Appliances-Cooker Hoods-Angled Wall Hoods | C2: Use as reference: | D2: 1003777
A3: MDA25083 | B3: Large Appliances-Hobs-Hobs - VTC | C3: Use as reference: | D3: 10029239
A4: MDA25083 | B4: Outdoor Living-Pits-Fire Pits | C4: Use as reference: | D4: 10029239
A5: MDA 25079 | C5: Use as reference: | D5: 10032301
A6: MDA 25075 | C6: Use as reference: | D6: 10032902
A7: MDA 25075 | C7: Use as reference: | D7: 10032902
A8: MDA25074 | B8: Large Appliances-Dishwashing-Dishwashers - Built-In/Under | C8: Use as reference: | D8: 10032913
A9: MDA25041 | B9: Large Appliances-Hobs-Hobs - Gas | C9: Use as reference: | D9: 10033132
A10: MDA25041 | C10: Use as reference: | D10: 10033132
A11: PROJECT ID GL25033 | C11: Use as reference: | D11: 10034123
A12: PROJECT ID GL25033 | C12: Use as reference: | D12: 10034123
A13: PROJECT ID GL25033 | B13: Climate-Indoor Heating-Electric Mantel Fireplaces | C13: Use as reference: | D13: 10034123
A14: PROJECT ID GL25033 | C14: Use as reference: | D14: 10034124
A15: PROJECT ID GL25033 | C15: Use as reference: | D15: 10034124
A16: PROJECT ID GL25033 | B16: Climate-Indoor Heating-Electric Mantel Fireplaces | C16: Use as reference: | D16: 10034124
A17: MDA25050 | C17: Use as reference: | D17: 10034604
A18: MDA25050 | B18: Large Appliances-Hobs-Hobs - VTC | C18: Use as reference: | D18: 10034604
A19: MDA25050 | B19: Outdoor Living-Pits-Fire Pits | C19: Use as reference: | D19: 10034604
A20: MDA25021 | B20: Large Appliances-Hobs-Hobs - Induction | C20: Use as reference: | D20: 10034947
A21: MDA25021 | C21: Use as reference: | D21: 10034947
A22: MDA25073 | B22: Large Appliances-Refrigeration-Beverage Coolers | C22: Use as reference: | D22: 10035304
A23: MDA25022 | B23: Large Appliances-Hobs-Hobs - Induction | C23: Use as reference: | D23: 10040202
A24: MDA25022 | C24: Use as reference: | D24: 10040202
A25: MDA25072 | B25: Large Appliances-Refrigeration-Beverage Coolers | C25: Use as reference: | D25: 10041183
A26: SDA25032 | C26: Use as reference: | D26: 10041253
A27: PROJECT ID GL25016 (10048294/5) | B27: Living-Indoor Heating-Radiators | C27: Use as reference: | D27: 10041265 | E27: 10034800 | F27: competitor 1 | G27: competitor 2
A28: MDA25023 | B28: Large Appliances-Hobs-Hobs - Induction | C28: Use as reference: | D28: 10041381
A29: MDA25023 | C29: Use as reference: | D29: 10041381
A30: SDA25014 | B30: Small Appliances-Cold Food Preparation-Ice Cream Makers | C30: Use as reference: | D30: 10045494
A31: MDA25039 | B31: Large Appliances-Hobs-Hobs - Gas | C31: Use as reference: | D31: 10045623
A32: MDA25046 | B32: Large Appliances-Hobs-Hobs w/ Int. Hoods | C32: Use as reference: | D32: 10046231
A33: MDA25046 | B33: Large Appliances-Hobs-Hobs w/ Int. Hoods | C33: Use as reference: | D33: 10046231
A34: MDA 25057 | B34: Large Appliances-Cooker Hoods-Angled Wall Hoods | C34: Use as reference: | D34: 10046377
A35: MDA25061 | B35: Outdoor Living-Pits-Fire Pits | C35: Use as reference: | D35: 10046565
A36: MDA25024 | B36: Large Appliances-Hobs-Hobs - Induction | C36: Use as reference: | D36: 10046565
A37: PROJECT MDA25093 | B37: Large Appliances-Hobs-Hobs - Induction | C37: Use as reference: | D37: 10046565
A38: MDA25093 | B38: Outdoor Living-Pits-Fire Pits | C38: Use as reference: | D38: 10046565
A39: MDA25024 | C39: Use as reference: | D39: 10046565
A40: MDA25044 | B40: Large Appliances-Refrigeration-Beverage Coolers | C40: Use as reference: | D40: 10046633
A41: 0 | B41: Appliances-Cooking & Baking-Ovens-Electric | C41: Use as reference: | D41: 10046685
A42: SDA25014 | B42: Small Appliances-Cold Food Preparation-Ice Cream Makers | C42: Use as reference: | D42: 10046686
A43: SDA25014 | B43: Small Appliances-Cold Food Preparation-Ice Cream Makers | C43: Use as reference: | D43: 10046686
A44: MDA25025 | B44: Large Appliances-Hobs-Hobs - Induction | C44: Use as reference: | D44: 10046695
A45: MDA25025 | C45: Use as reference: | D45: 10046695
A46: 0 | B46: Appliances-Cooking & Baking-Ovens-Electric | C46: Use as reference: | D46: 10046696
A47: MDA25006 | B47: Outdoor Living-Pits-Fire Pits | C47: Use as reference: | D47: 10046696
A48: MDA25058 | B48: Large Appliances-Cooker Hoods-Angled Wall Hoods | C48: Use as reference: | D48: 10046824
A49: MDA25058 | B49: Outdoor Living-Pits-Fire Pits | C49: Use as reference: | D49: 10046824
A50: 0 | B50: Appliances-Cooking & Baking-Ovens-Electric | C50: Use as reference: | D50: 10047354
A51: 0 | B51: Appliances-Cooking & Baking-Ovens-Electric | C51: Use as reference: | D51: 10047354
A52: 0 | B52: Appliances-Cooking & Baking-Ovens-Electric | C52: Use as reference: | D52: 10047354
A53: MDA25065 | B53: Outdoor Living-Pits-Fire Pits | C53: Use as reference: | D53: 10047366
A54: PROJECT MDA25061 | B54: Large Appliances-Cooker Hoods-Angled Wall Hoods | C54: Use as reference: | D54: 10047367
A55: MDA25059 | B55: Large Appliances-Cooker Hoods-Horizontal Wall Hoods | C55: Use as reference: | D55: 10047369
A56: MDA25059 | B56: Large Appliances-Cooker Hoods-Horizontal Wall Hoods | C56: Use as reference: | D56: 10047369
C57: SKUs | D57: 10048654
A58: SDA24046 | B58: Small Appliances-Coffee Machines-Coffee Machines - Drip Filter | C58: Use as reference: | D58: 60003286
A59: SDA24046 | B59: 0 | C59: Use as reference: | D59: 60003286
A60: SDA24045 | B60: Small Appliances-Coffee Machines-Coffee Machines - Drip Filter | C60: Use as reference: | D60: 60003288
A61: SDA24045 | B61: 0 | C61: Use as reference: | D61: 60003288
A62: SDA24045 | B62: 0 | C62: Use as reference: | D62: 60003288
A63: PROJECT ID XXXX | B63: Large Appliances-Hobs-Hobs w/ Int. Hoods | C63: Reference 1
A64: PROJECT ID XXXX | B64: Large Appliances-Hobs-Hobs w/ Int. Hoods | C64: Reference 1
A65: PROJECT ID XXXX | B65: Large Appliances-Refrigeration-Wine Fridges | C65: Reference 1
A66: Generic | B66: Outdoor Living-Pits-Fire Pits | C66: Reference 1
A67: PROJECT ID XXXX | B67: Large Appliances-Refrigeration-Fridges | C67: Reference 1
A68: Generic | B68: Large Appliances-Refrigeration-Fridges | C68: Reference 1
A69: PROJECT ID XXXX | C69: Reference 1
A70: Generic | C70: Reference 1
A71: PROJECT ID XXXX | C71: Reference 1
A72: PROJECT ID XXXX | B72: Large Appliances-Cooker Hoods-Horizontal Wall Hoods | C72: Reference 1
A73: Generic | B73: Large Appliances-Cooker Hoods-Horizontal Wall Hoods | C73: Reference 1
A74: PROJECT ID XXXX | B74: Large Appliances-Refrigeration-Fridge-Freezers (Combi) | C74: Reference 1
A75: Generic | B75: Large Appliances-Refrigeration-Fridge-Freezers (Combi) | C75: Reference 1
A76: PROJECT ID XXXX | B76: Small Appliances-Cold Food Preparation-Ice Cream Makers | C76: Reference 1
A77: SDA25014 | B77: 0 | C77: Reference 1
A78: PROJECT ID XXXX | B78: Large Appliances-Refrigeration-Freezers | C78: Reference 1
A79: Generic | B79: Large Appliances-Refrigeration-Freezers | C79: Reference 1
A80: PROJECT ID XXXX | C80: Reference 1
A81: Generic | C81: Reference 1
A82: PROJECT ID XXXX | C82: Reference 1
A83: PROJECT ID XXXX | B83: Large Appliances-Cooker Hoods-Angled Wall Hoods | C83: Reference 1
A84: Generic | B84: Outdoor Living-Pits-Fire Pits | C84: Reference 1
A85: MDA25058 | B85: Outdoor Living-Pits-Fire Pits | C85: Reference 1
A86: PROJECT ID XXXX | B86: Large Appliances-Cooker Hoods-Downdraft Hoods | C86: Reference 1
A87: PROJECT ID XXXX | B87: Large Appliances-Hobs-Hobs - Gas | C87: Reference 1
A88: PROJECT ID XXXX | C88: Reference 1
A89: Generic | C89: Reference 1
A90: PROJECT ID XXXX | C90: Reference 1
A91: PROJECT ID XXXX | B91: Large Appliances-Refrigeration-Humidors | C91: Reference 1
A92: Generic | B92: Large Appliances-Refrigeration-Humidors | C92: Reference 1
A93: Generic | B93: Outdoor Living-Pits-Fire Pits | C93: Reference 1
A94: PROJECT ID XXXX | B94: Small Appliances-Fryers-Air Fryers | C94: Reference 1
A95: PROJECT ID XXXX | B95: Small Appliances-Fryers-Air Fryers | C95: Reference 1
A96: PROJECT ID XXXX | B96: 0 | C96: Reference 1
A97: Generic | B97: 0 | C97: Reference 1
A98: PROJECT ID XXXX | B98: Large Appliances-Hobs-Hobs - VTC | C98: Reference 1
A99: Generic | B99: Outdoor Living-Pits-Fire Pits | C99: Reference 1
A100: PROJECT ID XXXX | B100: Climate-Air Treatment-Air Cleaner | C100: Reference 1
...

Sheet Category List
B3: Index | C3: SourceFile
B4: Small Appliances-Preserving Pots | C4: Preserving Pots - Attributes V3.0.xlsx
B5: Small Appliances-Pizza Ovens | C5: Pizza Ovens - Attributes V3.0.xlsx
B6: Small Appliances-Pasta Makers | C6: Pasta Makers - Attributes V3.0.xlsx
B7: Small Appliances-Meat Grinders | C7: Meat Grinders - Attributes V3.0.xlsx
B8: Small Appliances-Kitchen Machines-Stand Mixers | C8: Stand Mixers - Attributes V3.0.xlsx
B9: Small Appliances-Kitchen Machines-Mixers | C9: Mixers - Attributes V3.0.xlsx
B10: Small Appliances-Kitchen Machines-Juicers | C10: Juicers - Attributes V3.0.xlsx
B11: Small Appliances-Kitchen Machines-Food Processors | C11: Food Processors - Attributes V3.0.xlsx
B12: Small Appliances-Ice Makers-Ice Crushers | C12: Ice Crushers - Attributes V3.0.xlsx
B13: Small Appliances-Ice Makers-Domestic Ice Makers | C13: Domestic Ice Makers - Attributes V3.0.xlsx
B14: Small Appliances-Ice Makers-Commercial Ice Makers | C14: Commercial Ice Makers - Attributes V3.0.xlsx
... B62: Climate-Air Purifiers | C62: Air Purifiers - Attributes V3.0.xlsx

Sheet Sheet3

Sheet AttributeDictionary
A1: Where to Store | B1: Attribute | C1: Index 3.0 | D1: Attribute ID | E1: SourceFile | F1: SourcePath | G1: Key
B2: Name | C2: Large Appliances-Refrigerators-Portable Refrigerators | D2: Attribute1 | E2: Portable Refrigerators - Attributes V3.0.xlsx | F2: https://chaltecadmin.sharepoint.com/sites/ProductManagement/Shared Documents/02_Strategy/01_Portfolio Strategy/05_Product Passport/01_Large Appliances/ | G2: Attribute1Large Appliances-Refrigerators-Portable Refrigerators
B3: Picture | C3: Large Appliances-Refrigerators-Portable Refrigerators | D3: Attribute2 | E3: Portable Refrigerators - Attributes V3.0.xlsx | F3: https://chaltecadmin.sharepoint.com/sites/ProductManagement/Shared Documents/02_Strategy/01_Portfolio Strategy/05_Product Passport/01_Large Appliances/ | G3: Attribute2Large Appliances-Refrigerators-Portable Refrigerators
B4: e-star | C4: Large Appliances-Refrigerators-Portable Refrigerators | D4: Attribute3 | E4: Portable Refrigerators - Attributes V3.0.xlsx | F4: https://chaltecadmin.sharepoint.com/sites/ProductManagement/Shared Documents/02_Strategy/01_Portfolio Strategy/05_Product Passport/01_Large Appliances/ | G4: Attribute3Large Appliances-Refrigerators-Portable Refrigerators
B5: Family | C5: Large Appliances-Refrigerators-Portable Refrigerators | D5: Attribute4 | E5: Portable Refrigerators - Attributes V3.0.xlsx | F5: https://chaltecadmin.sharepoint.com/sites/ProductManagement/Shared Documents/02_Strategy/01_Portfolio Strategy/05_Product Passport/01_Large Appliances/ | G5: Attribute4Large Appliances-Refrigerators-Portable Refrigerators
B6: EOL | C6: Large Appliances-Refrigerators-Portable Refrigerators | D6: Attribute5 | E6: Portable Refrigerators - Attributes V3.0.xlsx | F6: https://chaltecadmin.sharepoint.com/sites/ProductManagement/Shared Documents/02_Strategy/01_Portfolio Strategy/05_Product Passport/01_Large Appliances/ | G6: Attribute5Large Appliances-Refrigerators-Portable Refrigerators
B7: Supplier | C7: Large Appliances-Refrigerators-Portable Refrigerators | D7: Attribute6 | E7: Portable Refrigerators - Attributes V3.0.xlsx | F7: https://chaltecadmin.sharepoint.com/sites/ProductManagement/Shared Documents/02_Strategy/01_Portfolio Strategy/05_Product Passport/01_Large Appliances/ | G7: Attribute6Large Appliances-Refrigerators-Portable Refrigerators
B8: Data Status | C8: Large Appliances-Refrigerators-Portable Refrigerators | D8: Attribute7 | E8: Portable Refrigerators - Attributes V3.0.xlsx | F8: https://chaltecadmin.sharepoint.com/sites/ProductManagement/Shared Documents/02_Strategy/01_Portfolio Strategy/05_Product Passport/01_Large Appliances/ | G8: Attribute7Large Appliances-Refrigerators-Portable Refrigerators
B9: Upload Status | C9: Large Appliances-Refrigerators-Portable Refrigerators | D9: Attribute8 | E9: Portable Refrigerators - Attributes V3.0.xlsx | F9: https://chaltecadmin.sharepoint.com/sites/ProductManagement/Shared Documents/02_Strategy/01_Portfolio Strategy/05_Product Passport/01_Large Appliances/ | G9: Attribute8Large Appliances-Refrigerators-Portable Refrigerators
B10: Date Last Upload Akeneo | C10: Large Appliances-Refrigerators-Portable Refrigerators | D10: Attribute9 | E10: Portable Refrigerators - Attributes V3.0.xlsx | F10: https://chaltecadmin.sharepoint.com/sites/ProductManagement/Shared Documents/02_Strategy/01_Portfolio Strategy/05_Product Passport/01_Large Appliances/ | G10: Attribute9Large Appliances-Refrigerators-Portable Refrigerators
B11: Category 5.0 & Segmentation | C11: Large Appliances-Refrigerators-Portable Refrigerators | D11: Attribute10 | E11: Portable Refrigerators - Attributes V3.0.xlsx | F11: https://chaltecadmin.sharepoint.com/sites/ProductManagement/Shared Documents/02_Strategy/01_Portfolio Strategy/05_Product Passport/01_Large Appliances/ | G11: Attribute10Large Appliances-Refrigerators-Portable Refrigerators
B12: Index | C12: Large Appliances-Refrigerators-Portable Refrigerators | D12: Attribute11 | E12: Portable Refrigerators - Attributes V3.0.xlsx | F12: https://chaltecadmin.sharepoint.com/sites/ProductManagement/Shared Documents/02_Strategy/01_Portfolio Strategy/05_Product Passport/01_Large Appliances/ | G12: Attribute11Large Appliances-Refrigerators-Portable Refrigerators
A13: SAP | B13: L1 | C13: Large Appliances-Refrigerators-Portable Refrigerators | D13: Attribute12 | E13: Portable Refrigerators - Attributes V3.0.xlsx | F13: https://chaltecadmin.sharepoint.com/sites/ProductManagement/Shared Documents/02_Strategy/01_Portfolio Strategy/05_Product Passport/01_Large Appliances/ | G13: Attribute12Large Appliances-Refrigerators-Portable Refrigerators
A14: SAP | B14: L2 | C14: Large Appliances-Refrigerators-Portable Refrigerators | D14: Attribute13 | E14: Portable Refrigerators - Attributes V3.0.xlsx | F14: https://chaltecadmin.sharepoint.com/sites/ProductManagement/Shared Documents/02_Strategy/01_Portfolio Strategy/05_Product Passport/01_Large Appliances/ | G14: Attribute13Large Appliances-Refrigerators-Portable Refrigerators
A15: SAP | B15: L3 | C15: Large Appliances-Refrigerators-Portable Refrigerators | D15: Attribute14 | E15: Portable Refrigerators - Attributes V3.0.xlsx | F15: https://chaltecadmin.sharepoint.com/sites/ProductManagement/Shared Documents/02_Strategy/01_Portfolio Strategy/05_Product Passport/01_Large Appliances/ | G15: Attribute14Large Appliances-Refrigerators-Portable Refrigerators
A16: SAP | B16: L4 | C16: Large Appliances-Refrigerators-Portable Refrigerators | D16: Attribute15 | E16: Portable Refrigerators - Attributes V3.0.xlsx | F16: https://chaltecadmin.sharepoint.com/sites/ProductManagement/Shared Documents/02_Strategy/01_Portfolio Strategy/05_Product Passport/01_Large Appliances/ | G16: Attribute15Large Appliances-Refrigerators-Portable Refrigerators
A17: Akeneo | B17: Family Name | C17: Large Appliances-Refrigerators-Portable Refrigerators | D17: Attribute16 | E17: Portable Refrigerators - Attributes V3.0.xlsx | F17: https://chaltecadmin.sharepoint.com/sites/ProductManagement/Shared Documents/02_Strategy/01_Portfolio Strategy/05_Product Passport/01_Large Appliances/ | G17: Attribute16Large Appliances-Refrigerators-Portable Refrigerators
A18: Akeneo | B18: Project ID | C18: Large Appliances-Refrigerators-Portable Refrigerators | D18: Attribute17 | E18: Portable Refrigerators - Attributes V3.0.xlsx | F18: https://chaltecadmin.sharepoint.com/sites/ProductManagement/Shared Documents/02_Strategy/01_Portfolio Strategy/05_Product Passport/01_Large Appliances/ | G18: Attribute17Large Appliances-Refrigerators-Portable Refrigerators
A19: Akeneo | B19: Segment 1 | C19: Large Appliances-Refrigerators-Portable Refrigerators | D19: Attribute18 | E19: Portable Refrigerators - Attributes V3.0.xlsx | F19: https://chaltecadmin.sharepoint.com/sites/ProductManagement/Shared Documents/02_Strategy/01_Portfolio Strategy/05_Product Passport/01_Large Appliances/ | G19: Attribute18Large Appliances-Refrigerators-Portable Refrigerators
A20: Akeneo | B20: Segment 2 | C20: Large Appliances-Refrigerators-Portable Refrigerators | D20: Attribute19 | E20: Portable Refrigerators - Attributes V3.0.xlsx | F20: https://chaltecadmin.sharepoint.com/sites/ProductManagement/Shared Documents/02_Strategy/01_Portfolio Strategy/05_Product Passport/01_Large Appliances/ | G20: Attribute19Large Appliances-Refrigerators-Portable Refrigerators
A21: Akeneo | B21: Segment 3 | C21: Large Appliances-Refrigerators-Portable Refrigerators | D21: Attribute20 | E21: Portable Refrigerators - Attributes V3.0.xlsx | F21: https://chaltecadmin.sharepoint.com/sites/ProductManagement/Shared Documents/02_Strategy/01_Portfolio Strategy/05_Product Passport/01_Large Appliances/ | G21: Attribute20Large Appliances-Refrigerators-Portable Refrigerators
A22: Akeneo | B22: Segment 4 | C22: Large Appliances-Refrigerators-Portable Refrigerators | D22: Attribute21 | E22: Portable Refrigerators - Attributes V3.0.xlsx | F22: https://chaltecadmin.sharepoint.com/sites/ProductManagement/Shared Documents/02_Strategy/01_Portfolio Strategy/05_Product Passport/01_Large Appliances/ | G22: Attribute21Large Appliances-Refrigerators-Portable Refrigerators
A23: Akeneo | B23: Segment 5 | C23: Large Appliances-Refrigerators-Portable Refrigerators | D23: Attribute22 | E23: Portable Refrigerators - Attributes V3.0.xlsx | F23: https://chaltecadmin.sharepoint.com/sites/ProductManagement/Shared Documents/02_Strategy/01_Portfolio Strategy/05_Product Passport/01_Large Appliances/ | G23: Attribute22Large Appliances-Refrigerators-Portable Refrigerators
B24: Listing & Data | C24: Large Appliances-Refrigerators-Portable Refrigerators | D24: Attribute23 | E24: Portable Refrigerators - Attributes V3.0.xlsx | F24: https://chaltecadmin.sharepoint.com/sites/ProductManagement/Shared Documents/02_Strategy/01_Portfolio Strategy/05_Product Passport/01_Large Appliances/ | G24: Attribute23Large Appliances-Refrigerators-Portable Refrigerators
A25: SAP | B25: Database Name | C25: Large Appliances-Refrigerators-Portable Refrigerators | D25: Attribute24 | E25: Portable Refrigerators - Attributes V3.0.xlsx | F25: https://chaltecadmin.sharepoint.com/sites/ProductManagement/Shared Documents/02_Strategy/01_Portfolio Strategy/05_Product Passport/01_Large Appliances/ | G25: Attribute24Large Appliances-Refrigerators-Portable Refrigerators
B26: Char Count -> MAX 40 | C26: Large Appliances-Refrigerators-Portable Refrigerators | D26: Attribute25 | E26: Portable Refrigerators - Attributes V3.0.xlsx | F26: https://chaltecadmin.sharepoint.com/sites/ProductManagement/Shared Documents/02_Strategy/01_Portfolio Strategy/05_Product Passport/01_Large Appliances/ | G26: Attribute25Large Appliances-Refrigerators-Portable Refrigerators
B27: Variant with SKU or Family: | C27: Large Appliances-Refrigerators-Portable Refrigerators | D27: Attribute26 | E27: Portable Refrigerators - Attributes V3.0.xlsx | F27: https://chaltecadmin.sharepoint.com/sites/ProductManagement/Shared Documents/02_Strategy/01_Portfolio Strategy/05_Product Passport/01_Large Appliances/ | G27: Attribute26Large Appliances-Refrigerators-Portable Refrigerators
A28: Akeneo | B28: Variation 1 | C28: Large Appliances-Refrigerators-Portable Refrigerators | D28: Attribute27 | E28: Portable Refrigerators - Attributes V3.0.xlsx | F28: https://chaltecadmin.sharepoint.com/sites/ProductManagement/Shared Documents/02_Strategy/01_Portfolio Strategy/05_Product Passport/01_Large Appliances/ | G28: Attribute27Large Appliances-Refrigerators-Portable Refrigerators
A29: Akeneo | B29: Variation 1 - Value | C29: Large Appliances-Refrigerators-Portable Refrigerators | D29: Attribute28 | E29: Portable Refrigerators - Attributes V3.0.xlsx | F29: https://chaltecadmin.sharepoint.com/sites/ProductManagement/Shared Documents/02_Strategy/01_Portfolio Strategy/05_Product Passport/01_Large Appliances/ | G29: Attribute28Large Appliances-Refrigerators-Portable Refrigerators
A30: Akeneo | B30: Variation 2 | C30: Large Appliances-Refrigerators-Portable Refrigerators | D30: Attribute29 | E30: Portable Refrigerators - Attributes V3.0.xlsx | F30: https://chaltecadmin.sharepoint.com/sites/ProductManagement/Shared Documents/02_Strategy/01_Portfolio Strategy/05_Product Passport/01_Large Appliances/ | G30: Attribute29Large Appliances-Refrigerators-Portable Refrigerators
A31: Akeneo | B31: Variation 2 - Value | C31: Large Appliances-Refrigerators-Portable Refrigerators | D31: Attribute30 | E31: Portable Refrigerators - Attributes V3.0.xlsx | F31: https://chaltecadmin.sharepoint.com/sites/ProductManagement/Shared Documents/02_Strategy/01_Portfolio Strategy/05_Product Passport/01_Large Appliances/ | G31: Attribute30Large Appliances-Refrigerators-Portable Refrigerators
A32: Akeneo | B32: Variation 3 | C32: Large Appliances-Refrigerators-Portable Refrigerators | D32: Attribute31 | E32: Portable Refrigerators - Attributes V3.0.xlsx | F32: https://chaltecadmin.sharepoint.com/sites/ProductManagement/Shared Documents/02_Strategy/01_Portfolio Strategy/05_Product Passport/01_Large Appliances/ | G32: Attribute31Large Appliances-Refrigerators-Portable Refrigerators
A33: Akeneo | B33: Variation 3 - Value | C33: Large Appliances-Refrigerators-Portable Refrigerators | D33: Attribute32 | E33: Portable Refrigerators - Attributes V3.0.xlsx | F33: https://chaltecadmin.sharepoint.com/sites/ProductManagement/Shared Documents/02_Strategy/01_Portfolio Strategy/05_Product Passport/01_Large Appliances/ | G33: Attribute32Large Appliances-Refrigerators-Portable Refrigerators
B34: 1 . Category Specific Attributes | C34: Large Appliances-Refrigerators-Portable Refrigerators | D34: Attribute33 | E34: Portable Refrigerators - Attributes V3.0.xlsx | F34: https://chaltecadmin.sharepoint.com/sites/ProductManagement/Shared Documents/02_Strategy/01_Portfolio Strategy/05_Product Passport/01_Large Appliances/ | G34: Attribute33Large Appliances-Refrigerators-Portable Refrigerators
A35: SAP | B35: Supplier Part Number | C35: Large Appliances-Refrigerators-Portable Refrigerators | D35: Attribute34 | E35: Portable Refrigerators - Attributes V3.0.xlsx | F35: https://chaltecadmin.sharepoint.com/sites/ProductManagement/Shared Documents/02_Strategy/01_Portfolio Strategy/05_Product Passport/01_Large Appliances/ | G35: Attribute34Large Appliances-Refrigerators-Portable Refrigerators
A36: Akeneo | B36: Nominal capacity [L] | C36: Large Appliances-Refrigerators-Portable Refrigerators | D36: Attribute35 | E36: Portable Refrigerators - Attributes V3.0.xlsx | F36: https://chaltecadmin.sharepoint.com/sites/ProductManagement/Shared Documents/02_Strategy/01_Portfolio Strategy/05_Product Passport/01_Large Appliances/ | G36: Attribute35Large Appliances-Refrigerators-Portable Refrigerators
A37: Akeneo | B37: Compartment [Single, Dual] | C37: Large Appliances-Refrigerators-Portable Refrigerators | D37: Attribute36 | E37: Portable Refrigerators - Attributes V3.0.xlsx | F37: https://chaltecadmin.sharepoint.com/sites/ProductManagement/Shared Documents/02_Strategy/01_Portfolio Strategy/05_Product Passport/01_Large Appliances/ | G37: Attribute36Large Appliances-Refrigerators-Portable Refrigerators
A38: Akeneo | B38: Dual Zone Control [Y/N] | C38: Large Appliances-Refrigerators-Portable Refrigerators | D38: Attribute37 | E38: Portable Refrigerators - Attributes V3.0.xlsx | F38: https://chaltecadmin.sharepoint.com/sites/ProductManagement/Shared Documents/02_Strategy/01_Portfolio Strategy/05_Product Passport/01_Large Appliances/ | G38: Attribute37Large Appliances-Refrigerators-Portable Refrigerators
B39: Type of cooling system | C39: Large Appliances-Refrigerators-Portable Refrigerators | D39: Attribute38 | E39: Portable Refrigerators - Attributes V3.0.xlsx | F39: https://chaltecadmin.sharepoint.com/sites/ProductManagement/Shared Documents/02_Strategy/01_Portfolio Strategy/05_Product Passport/01_Large Appliances/ | G39: Attribute38Large Appliances-Refrigerators-Portable Refrigerators
B40: Refrigerant Type | C40: Large Appliances-Refrigerators-Portable Refrigerators | D40: Attribute39 | E40: Portable Refrigerators - Attributes V3.0.xlsx | F40: https://chaltecadmin.sharepoint.com/sites/ProductManagement/Shared Documents/02_Strategy/01_Portfolio Strategy/05_Product Passport/01_Large Appliances/ | G40: Attribute39Large Appliances-Refrigerators-Portable Refrigerators
B41: Refrigerant weight [g] | C41: Large Appliances-Refrigerators-Portable Refrigerators | D41: Attribute40 | E41: Portable Refrigerators - Attributes V3.0.xlsx | F41: https://chaltecadmin.sharepoint.com/sites/ProductManagement/Shared Documents/02_Strategy/01_Portfolio Strategy/05_Product Passport/01_Large Appliances/ | G41: Attribute40Large Appliances-Refrigerators-Portable Refrigerators
B42: Climate Class | C42: Large Appliances-Refrigerators-Portable Refrigerators | D42: Attribute41 | E42: Portable Refrigerators - Attributes V3.0.xlsx | F42: https://chaltecadmin.sharepoint.com/sites/ProductManagement/Shared Documents/02_Strategy/01_Portfolio Strategy/05_Product Passport/01_Large Appliances/ | G42: Attribute41Large Appliances-Refrigerators-Portable Refrigerators
B43: Defrost Type [Manual, Auto, Drain] | C43: Large Appliances-Refrigerators-Portable Refrigerators | D43: Attribute42 | E43: Portable Refrigerators - Attributes V3.0.xlsx | F43: https://chaltecadmin.sharepoint.com/sites/ProductManagement/Shared Documents/02_Strategy/01_Portfolio Strategy/05_Product Passport/01_Large Appliances/ | G43: Attribute42Large Appliances-Refrigerators-Portable Refrigerators
B44: Heating Feature [Yes/No] | C44: Large Appliances-Refrigerators-Portable Refrigerators | D44: Attribute43 | E44: Portable Refrigerators - Attributes V3.0.xlsx | F44: https://chaltecadmin.sharepoint.com/sites/ProductManagement/Shared Documents/02_Strategy/01_Portfolio Strategy/05_Product Passport/01_Large Appliances/ | G44: Attribute43Large Appliances-Refrigerators-Portable Refrigerators
B45: Cooling Feature [Yes/No] | C45: Large Appliances-Refrigerators-Portable Refrigerators | D45: Attribute44 | E45: Portable Refrigerators - Attributes V3.0.xlsx | F45: https://chaltecadmin.sharepoint.com/sites/ProductManagement/Shared Documents/02_Strategy/01_Portfolio Strategy/05_Product Passport/01_Large Appliances/ | G45: Attribute44Large Appliances-Refrigerators-Portable Refrigerators
B46: Min Cooling temperature [°C] | C46: Large Appliances-Refrigerators-Portable Refrigerators | D46: Attribute45 | E46: Portable Refrigerators - Attributes V3.0.xlsx | F46: https://chaltecadmin.sharepoint.com/sites/ProductManagement/Shared Documents/02_Strategy/01_Portfolio Strategy/05_Product Passport/01_Large Appliances/ | G46: Attribute45Large Appliances-Refrigerators-Portable Refrigerators
B47: Max Heating temperature [°C] | C47: Large Appliances-Refrigerators-Portable Refrigerators | D47: Attribute46 | E47: Portable Refrigerators - Attributes V3.0.xlsx | F47: https://chaltecadmin.sharepoint.com/sites/ProductManagement/Shared Documents/02_Strategy/01_Portfolio Strategy/05_Product Passport/01_Large Appliances/ | G47: Attribute46Large Appliances-Refrigerators-Portable Refrigerators
B48: Temperature Range [°C] | C48: Large Appliances-Refrigerators-Portable Refrigerators | D48: Attribute47 | E48: Portable Refrigerators - Attributes V3.0.xlsx | F48: https://chaltecadmin.sharepoint.com/sites/ProductManagement/Shared Documents/02_Strategy/01_Portfolio Strategy/05_Product Passport/01_Large Appliances/ | G48: Attribute47Large Appliances-Refrigerators-Portable Refrigerators
B49: Cooling Time [°C/min] | C49: Large Appliances-Refrigerators-Portable Refrigerators | D49: Attribute48 | E49: Portable Refrigerators - Attributes V3.0.xlsx | F49: https://chaltecadmin.sharepoint.com/sites/ProductManagement/Shared Documents/02_Strategy/01_Portfolio Strategy/05_Product Passport/01_Large Appliances/ | G49: Attribute48Large Appliances-Refrigerators-Portable Refrigerators
B50: Available Cables [Power Cable, Cigarette etc] | C50: Large Appliances-Refrigerators-Portable Refrigerators | D50: Attribute49 | E50: Portable Refrigerators - Attributes V3.0.xlsx | F50: https://chaltecadmin.sharepoint.com/sites/ProductManagement/Shared Documents/02_Strategy/01_Portfolio Strategy/05_Product Passport/01_Large Appliances/ | G50: Attribute49Large Appliances-Refrigerators-Portable Refrigerators
... B58: [If applicable] Inverter Type | C58: Large Appliances-Refrigerators-Portable Refrigerators | D58: Attribute57 | E58: Portable Refrigerators - Attributes V3.0.xlsx | F58: https://chaltecadmin.sharepoint.com/sites/ProductManagement/Shared Documents/02_Strategy/01_Portfolio Strategy/05_Product Passport/01_Large Appliances/ | G58: Attribute57Large Appliances-Refrigerators-Portable Refrigerators
A59: Akeneo | B59: Housing Material | C59: Large Appliances-Refrigerators-Portable Refrigerators | D59: Attribute58 | E59: Portable Refrigerators - Attributes V3.0.xlsx | F59: https://chaltecadmin.sharepoint.com/sites/ProductManagement/Shared Documents/02_Strategy/01_Portfolio Strategy/05_Product Passport/01_Large Appliances/ | G59: Attribute58Large Appliances-Refrigerators-Portable Refrigerators
A60: Akeneo | B60: Insulation Material | C60: Large Appliances-Refrigerators-Portable Refrigerators | D60: Attribute59 | E60: Portable Refrigerators - Attributes V3.0.xlsx | F60: https://chaltecadmin.sharepoint.com/sites/ProductManagement/Shared Documents/02_Strategy/01_Portfolio Strategy/05_Product Passport/01_Large Appliances/ | G60: Attribute59Large Appliances-Refrigerators-Portable Refrigerators
A61: Akeneo | B61: Lid Type [Hinged, Split, Removable] | C61: Large Appliances-Refrigerators-Portable Refrigerators | D61: Attribute60 | E61: Portable Refrigerators - Attributes V3.0.xlsx | F61: https://chaltecadmin.sharepoint.com/sites/ProductManagement/Shared Documents/02_Strategy/01_Portfolio Strategy/05_Product Passport/01_Large Appliances/ | G61: Attribute60Large Appliances-Refrigerators-Portable Refrigerators
A62: Akeneo | B62: Lid Opening Direction [Top, Side, Reversible] | C62: Large Appliances-Refrigerators-Portable Refrigerators | D62: Attribute61 | E62: Portable Refrigerators - Attributes V3.0.xlsx | F62: https://chaltecadmin.sharepoint.com/sites/ProductManagement/Shared Documents/02_Strategy/01_Portfolio Strategy/05_Product Passport/01_Large Appliances/ | G62: Attribute61Large Appliances-Refrigerators-Portable Refrigerators
A63: Akeneo | B63: Lid Material | C63: Large Appliances-Refrigerators-Portable Refrigerators | D63: Attribute62 | E63: Portable Refrigerators - Attributes V3.0.xlsx | F63: https://chaltecadmin.sharepoint.com/sites/ProductManagement/Shared Documents/02_Strategy/01_Portfolio Strategy/05_Product Passport/01_Large Appliances/ | G63: Attribute62Large Appliances-Refrigerators-Portable Refrigerators
A64: Akeneo | B64: Carry Handle [Y/N] | C64: Large Appliances-Refrigerators-Portable Refrigerators | D64: Attribute63 | E64: Portable Refrigerators - Attributes V3.0.xlsx | F64: https://chaltecadmin.sharepoint.com/sites/ProductManagement/Shared Documents/02_Strategy/01_Portfolio Strategy/05_Product Passport/01_Large Appliances/ | G64: Attribute63Large Appliances-Refrigerators-Portable Refrigerators
A65: Akeneo | B65: Telescopic Handle [Y/N] | C65: Large Appliances-Refrigerators-Portable Refrigerators | D65: Attribute64 | E65: Portable Refrigerators - Attributes V3.0.xlsx | F65: https://chaltecadmin.sharepoint.com/sites/ProductManagement/Shared Documents/02_Strategy/01_Portfolio Strategy/05_Product Passport/01_Large Appliances/ | G65: Attribute64Large Appliances-Refrigerators-Portable Refrigerators
A66: Akeneo | B66: Handle Material | C66: Large Appliances-Refrigerators-Portable Refrigerators | D66: Attribute65 | E66: Portable Refrigerators - Attributes V3.0.xlsx | F66: https://chaltecadmin.sharepoint.com/sites/ProductManagement/Shared Documents/02_Strategy/01_Portfolio Strategy/05_Product Passport/01_Large Appliances/ | G66: Attribute65Large Appliances-Refrigerators-Portable Refrigerators
A67: Akeneo | B67: Wheels [Y/N] | C67: Large Appliances-Refrigerators-Portable Refrigerators | D67: Attribute66 | E67: Portable Refrigerators - Attributes V3.0.xlsx | F67: https://chaltecadmin.sharepoint.com/sites/ProductManagement/Shared Documents/02_Strategy/01_Portfolio Strategy/05_Product Passport/01_Large Appliances/ | G67: Attribute66Large Appliances-Refrigerators-Portable Refrigerators
A68: Akeneo | B68: Adjustable divider insert [Y/N] | C68: Large Appliances-Refrigerators-Portable Refrigerators | D68: Attribute67 | E68: Portable Refrigerators - Attributes V3.0.xlsx | F68: https://chaltecadmin.sharepoint.com/sites/ProductManagement/Shared Documents/02_Strategy/01_Portfolio Strategy/05_Product Passport/01_Large Appliances/ | G68: Attribute67Large Appliances-Refrigerators-Portable Refrigerators
A69: Akeneo | B69: Removable basket [Y/N] | C69: Large Appliances-Refrigerators-Portable Refrigerators | D69: Attribute68 | E69: Portable Refrigerators - Attributes V3.0.xlsx | F69: https://chaltecadmin.sharepoint.com/sites/ProductManagement/Shared Documents/02_Strategy/01_Portfolio Strategy/05_Product Passport/01_Large Appliances/ | G69: Attribute68Large Appliances-Refrigerators-Portable Refrigerators
A70: Akeneo | B70: Insulated Cover/Bag [Y/N] | C70: Large Appliances-Refrigerators-Portable Refrigerators | D70: Attribute69 | E70: Portable Refrigerators - Attributes V3.0.xlsx | F70: https://chaltecadmin.sharepoint.com/sites/ProductManagement/Shared Documents/02_Strategy/01_Portfolio Strategy/05_Product Passport/01_Large Appliances/ | G70: Attribute69Large Appliances-Refrigerators-Portable Refrigerators
... A86: Akeneo | B86: Secondary Color | C86: Large Appliances-Refrigerators-Portable Refrigerators | D86: Attribute85 | E86: Portable Refrigerators - Attributes V3.0.xlsx | F86: https://chaltecadmin.sharepoint.com/sites/ProductManagement/Shared Documents/02_Strategy/01_Portfolio Strategy/05_Product Passport/01_Large Appliances/ | G86: Attribute85Large Appliances-Refrigerators-Portable Refrigerators
B87: Abreviation Color | C87: Large Appliances-Refrigerators-Portable Refrigerators | D87: Attribute86 | E87: Portable Refrigerators - Attributes V3.0.xlsx | F87: https://chaltecadmin.sharepoint.com/sites/ProductManagement/Shared Documents/02_Strategy/01_Portfolio Strategy/05_Product Passport/01_Large Appliances/ | G87: Attribute86Large Appliances-Refrigerators-Portable Refrigerators
A88: Akeneo | B88: IoT/Smart | C88: Large Appliances-Refrigerators-Portable Refrigerators | D88: Attribute87 | E88: Portable Refrigerators - Attributes V3.0.xlsx | F88: https://chaltecadmin.sharepoint.com/sites/ProductManagement/Shared Documents/02_Strategy/01_Portfolio Strategy/05_Product Passport/01_Large Appliances/ | G88: Attribute87Large Appliances-Refrigerators-Portable Refrigerators
B89: Additional Features | C89: Large Appliances-Refrigerators-Portable Refrigerators | D89: Attribute88 | E89: Portable Refrigerators - Attributes V3.0.xlsx | F89: https://chaltecadmin.sharepoint.com/sites/ProductManagement/Shared Documents/02_Strategy/01_Portfolio Strategy/05_Product Passport/01_Large Appliances/ | G89: Attribute88Large Appliances-Refrigerators-Portable Refrigerators
A90: Akeneo | B90: Special Attribute 1 | C90: Large Appliances-Refrigerators-Portable Refrigerators | D90: Attribute89 | E90: Portable Refrigerators - Attributes V3.0.xlsx | F90: https://chaltecadmin.sharepoint.com/sites/ProductManagement/Shared Documents/02_Strategy/01_Portfolio Strategy/05_Product Passport/01_Large Appliances/ | G90: Attribute89Large Appliances-Refrigerators-Portable Refrigerators
A91: Akeneo | B91: Special Attribute 2 | C91: Large Appliances-Refrigerators-Portable Refrigerators | D91: Attribute90 | E91: Portable Refrigerators - Attributes V3.0.xlsx | F91: https://chaltecadmin.sharepoint.com/sites/ProductManagement/Shared Documents/02_Strategy/01_Portfolio Strategy/05_Product Passport/01_Large Appliances/ | G91: Attribute90Large Appliances-Refrigerators-Portable Refrigerators
A92: Akeneo | B92: Special Attribute 3 | C92: Large Appliances-Refrigerators-Portable Refrigerators | D92: Attribute91 | E92: Portable Refrigerators - Attributes V3.0.xlsx | F92: https://chaltecadmin.sharepoint.com/sites/ProductManagement/Shared Documents/02_Strategy/01_Portfolio Strategy/05_Product Passport/01_Large Appliances/ | G92: Attribute91Large Appliances-Refrigerators-Portable Refrigerators
A93: Akeneo | B93: Special Attribute 4 | C93: Large Appliances-Refrigerators-Portable Refrigerators | D93: Attribute92 | E93: Portable Refrigerators - Attributes V3.0.xlsx | F93: https://chaltecadmin.sharepoint.com/sites/ProductManagement/Shared Documents/02_Strategy/01_Portfolio Strategy/05_Product Passport/01_Large Appliances/ | G93: Attribute92Large Appliances-Refrigerators-Portable Refrigerators
A94: Akeneo | B94: Special Attribute 5 | C94: Large Appliances-Refrigerators-Portable Refrigerators | D94: Attribute93 | E94: Portable Refrigerators - Attributes V3.0.xlsx | F94: https://chaltecadmin.sharepoint.com/sites/ProductManagement/Shared Documents/02_Strategy/01_Portfolio Strategy/05_Product Passport/01_Large Appliances/ | G94: Attribute93Large Appliances-Refrigerators-Portable Refrigerators
B95: 2. Standard Electric Specs | C95: Large Appliances-Refrigerators-Portable Refrigerators | D95: Attribute94 | E95: Portable Refrigerators - Attributes V3.0.xlsx | F95: https://chaltecadmin.sharepoint.com/sites/ProductManagement/Shared Documents/02_Strategy/01_Portfolio Strategy/05_Product Passport/01_Large Appliances/ | G95: Attribute94Large Appliances-Refrigerators-Portable Refrigerators
A96: Akeneo | B96: Energy efficiency class | C96: Large Appliances-Refrigerators-Portable Refrigerators | D96: Attribute95 | E96: Portable Refrigerators - Attributes V3.0.xlsx | F96: https://chaltecadmin.sharepoint.com/sites/ProductManagement/Shared Documents/02_Strategy/01_Portfolio Strategy/05_Product Passport/01_Large Appliances/ | G96: Attribute95Large Appliances-Refrigerators-Portable Refrigerators
A97: Akeneo | B97: Annual energy consumption [kWh/year] | C97: Large Appliances-Refrigerators-Portable Refrigerators | D97: Attribute96 | E97: Portable Refrigerators - Attributes V3.0.xlsx | F97: https://chaltecadmin.sharepoint.com/sites/ProductManagement/Shared Documents/02_Strategy/01_Portfolio Strategy/05_Product Passport/01_Large Appliances/ | G97: Attribute96Large Appliances-Refrigerators-Portable Refrigerators
A98: Akeneo | B98: Voltage Range [V / Hz] | C98: Large Appliances-Refrigerators-Portable Refrigerators | D98: Attribute97 | E98: Portable Refrigerators - Attributes V3.0.xlsx | F98: https://chaltecadmin.sharepoint.com/sites/ProductManagement/Shared Documents/02_Strategy/01_Portfolio Strategy/05_Product Passport/01_Large Appliances/ | G98: Attribute97Large Appliances-Refrigerators-Portable Refrigerators
A99: Akeneo | B99: Type of plug | C99: Large Appliances-Refrigerators-Portable Refrigerators | D99: Attribute98 | E99: Portable Refrigerators - Attributes V3.0.xlsx | F99: https://chaltecadmin.sharepoint.com/sites/ProductManagement/Shared Documents/02_Strategy/01_Portfolio Strategy/05_Product Passport/01_Large Appliances/ | G99: Attribute98Large Appliances-Refrigerators-Portable Refrigerators
A100: Akeneo | B100: Power cord length [m] | C100: Large Appliances-Refrigerators-Portable Refrigerators | D100: Attribute99 | E100: Portable Refrigerators - Attributes V3.0.xlsx | F100: https://chaltecadmin.sharepoint.com/sites/ProductManagement/Shared Documents/02_Strategy/01_Portfolio Strategy/05_Product Passport/01_Large Appliances/ | G100: Attribute99Large Appliances-Refrigerators-Portable Refrigerators
A101: Akeneo | B101: IEC protection class [Schutzklasse] | C101: Large Appliances-Refrigerators-Portable Refrigerators | D101: Attribute100 | E101: Portable Refrigerators - Attributes V3.0.xlsx | F101: https://chaltecadmin.sharepoint.com/sites/ProductManagement/Shared Documents/02_Strategy/01_Portfolio Strategy/05_Product Passport/01_Large Appliances/ | G101: Attribute100Large Appliances-Refrigerators-Portable Refrigerators
A102: Akeneo | B102: Power [W] | C102: Large Appliances-Refrigerators-Portable Refrigerators | D102: Attribute101 | E102: Portable Refrigerators - Attributes V3.0.xlsx | F102: https://chaltecadmin.sharepoint.com/sites/ProductManagement/Shared Documents/02_Strategy/01_Portfolio Strategy/05_Product Passport/01_Large Appliances/ | G102: Attribute101Large Appliances-Refrigerators-Portable Refrigerators
A103: Akeneo | B103: Noise Emission [dB] | C103: Large Appliances-Refrigerators-Portable Refrigerators | D103: Attribute102 | E103: Portable Refrigerators - Attributes V3.0.xlsx | F103: https://chaltecadmin.sharepoint.com/sites/ProductManagement/Shared Documents/02_Strategy/01_Portfolio Strategy/05_Product Passport/01_Large Appliances/ | G103: Attribute102Large Appliances-Refrigerators-Portable Refrigerators
B104: Noise Level Min-Max [db] | C104: Large Appliances-Refrigerators-Portable Refrigerators | D104: Attribute103 | E104: Portable Refrigerators - Attributes V3.0.xlsx | F104: https://chaltecadmin.sharepoint.com/sites/ProductManagement/Shared Documents/02_Strategy/01_Portfolio Strategy/05_Product Passport/01_Large Appliances/ | G104: Attribute103Large Appliances-Refrigerators-Portable Refrigerators
B105: 3. Product Dimensions | C105: Large Appliances-Refrigerators-Portable Refrigerators | D105: Attribute104 | E105: Portable Refrigerators - Attributes V3.0.xlsx | F105: https://chaltecadmin.sharepoint.com/sites/ProductManagement/Shared Documents/02_Strategy/01_Portfolio Strategy/05_Product Passport/01_Large Appliances/ | G105: Attribute104Large Appliances-Refrigerators-Portable Refrigerators
A106: Akeneo | B106: Product Height [cm] | C106: Large Appliances-Refrigerators-Portable Refrigerators | D106: Attribute105 | E106: Portable Refrigerators - Attributes V3.0.xlsx | F106: https://chaltecadmin.sharepoint.com/sites/ProductManagement/Shared Documents/02_Strategy/01_Portfolio Strategy/05_Product Passport/01_Large Appliances/ | G106: Attribute105Large Appliances-Refrigerators-Portable Refrigerators
A107: Akeneo | B107: Product Width [cm] | C107: Large Appliances-Refrigerators-Portable Refrigerators | D107: Attribute106 | E107: Portable Refrigerators - Attributes V3.0.xlsx | F107: https://chaltecadmin.sharepoint.com/sites/ProductManagement/Shared Documents/02_Strategy/01_Portfolio Strategy/05_Product Passport/01_Large Appliances/ | G107: Attribute106Large Appliances-Refrigerators-Portable Refrigerators
A108: Akeneo | B108: Product Depth [cm] | C108: Large Appliances-Refrigerators-Portable Refrigerators | D108: Attribute107 | E108: Portable Refrigerators - Attributes V3.0.xlsx | F108: https://chaltecadmin.sharepoint.com/sites/ProductManagement/Shared Documents/02_Strategy/01_Portfolio Strategy/05_Product Passport/01_Large Appliances/ | G108: Attribute107Large Appliances-Refrigerators-Portable Refrigerators
A109: Akeneo | B109: Product weight [kg] | C109: Large Appliances-Refrigerators-Portable Refrigerators | D109: Attribute108 | E109: Portable Refrigerators - Attributes V3.0.xlsx | F109: https://chaltecadmin.sharepoint.com/sites/ProductManagement/Shared Documents/02_Strategy/01_Portfolio Strategy/05_Product Passport/01_Large Appliances/ | G109: Attribute108Large Appliances-Refrigerators-Portable Refrigerators
B110: Internal compartment 1 Height [cm] | C110: Large Appliances-Refrigerators-Portable Refrigerators | D110: Attribute109 | E110: Portable Refrigerators - Attributes V3.0.xlsx | F110: https://chaltecadmin.sharepoint.com/sites/ProductManagement/Shared Documents/02_Strategy/01_Portfolio Strategy/05_Product Passport/01_Large Appliances/ | G110: Attribute109Large Appliances-Refrigerators-Portable Refrigerators
B111: Internal compartment 1 Width [cm] | C111: Large Appliances-Refrigerators-Portable Refrigerators | D111: Attribute110 | E111: Portable Refrigerators - Attributes V3.0.xlsx | F111: https://chaltecadmin.sharepoint.com/sites/ProductManagement/Shared Documents/02_Strategy/01_Portfolio Strategy/05_Product Passport/01_Large Appliances/ | G111: Attribute110Large Appliances-Refrigerators-Portable Refrigerators
B112: Internal compartment 1 Depth [cm] | C112: Large Appliances-Refrigerators-Portable Refrigerators | D112: Attribute111 | E112: Portable Refrigerators - Attributes V3.0.xlsx | F112: https://chaltecadmin.sharepoint.com/sites/ProductManagement/Shared Documents/02_Strategy/01_Portfolio Strategy/05_Product Passport/01_Large Appliances/ | G112: Attribute111Large Appliances-Refrigerators-Portable Refrigerators
B113: Internal compartment 2 Height [cm] | C113: Large Appliances-Refrigerators-Portable Refrigerators | D113: Attribute112 | E113: Portable Refrigerators - Attributes V3.0.xlsx | F113: https://chaltecadmin.sharepoint.com/sites/ProductManagement/Shared Documents/02_Strategy/01_Portfolio Strategy/05_Product Passport/01_Large Appliances/ | G113: Attribute112Large Appliances-Refrigerators-Portable Refrigerators
B114: Internal compartment 2 Width [cm] | C114: Large Appliances-Refrigerators-Portable Refrigerators | D114: Attribute113 | E114: Portable Refrigerators - Attributes V3.0.xlsx | F114: https://chaltecadmin.sharepoint.com/sites/ProductManagement/Shared Documents/02_Strategy/01_Portfolio Strategy/05_Product Passport/01_Large Appliances/ | G114: Attribute113Large Appliances-Refrigerators-Portable Refrigerators
B115: Internal compartment 2 Depth [cm] | C115: Large Appliances-Refrigerators-Portable Refrigerators | D115: Attribute114 | E115: Portable Refrigerators - Attributes V3.0.xlsx | F115: https://chaltecadmin.sharepoint.com/sites/ProductManagement/Shared Documents/02_Strategy/01_Portfolio Strategy/05_Product Passport/01_Large Appliances/ | G115: Attribute114Large Appliances-Refrigerators-Portable Refrigerators
A116: Akeneo | B116: Product Dimensions | C116: Large Appliances-Refrigerators-Portable Refrigerators | D116: Attribute115 | E116: Portable Refrigerators - Attributes V3.0.xlsx | F116: https://chaltecadmin.sharepoint.com/sites/ProductManagement/Shared Documents/02_Strategy/01_Portfolio Strategy/05_Product Passport/01_Large Appliances/ | G116: Attribute115Large Appliances-Refrigerators-Portable Refrigerators
B117: 4. Battery Information - Mandatory for all items with batteries according to EU regulations | C117: Large Appliances-Refrigerators-Portable Refrigerators | D117: Attribute116 | E117: Portable Refrigerators - Attributes V3.0.xlsx | F117: https://chaltecadmin.sharepoint.com/sites/ProductManagement/Shared Documents/02_Strategy/01_Portfolio Strategy/05_Product Passport/01_Large Appliances/ | G117: Attribute116Large Appliances-Refrigerators-Portable Refrigerators
A118: Akeneo | B118: Number of batteries in accessories [qty] | C118: Large Appliances-Refrigerators-Portable Refrigerators | D118: Attribute117 | E118: Portable Refrigerators - Attributes V3.0.xlsx | F118: https://chaltecadmin.sharepoint.com/sites/ProductManagement/Shared Documents/02_Strategy/01_Portfolio Strategy/05_Product Passport/01_Large Appliances/ | G118: Attribute117Large Appliances-Refrigerators-Portable Refrigerators
A119: Akeneo | B119: Type of batteries in accessories [type] | C119: Large Appliances-Refrigerators-Portable Refrigerators | D119: Attribute118 | E119: Portable Refrigerators - Attributes V3.0.xlsx | F119: https://chaltecadmin.sharepoint.com/sites/ProductManagement/Shared Documents/02_Strategy/01_Portfolio Strategy/05_Product Passport/01_Large Appliances/ | G119: Attribute118Large Appliances-Refrigerators-Portable Refrigerators
A120: Akeneo | B120: Weight of one battery in accessories [g] | C120: Large Appliances-Refrigerators-Portable Refrigerators | D120: Attribute119 | E120: Portable Refrigerators - Attributes V3.0.xlsx | F120: https://chaltecadmin.sharepoint.com/sites/ProductManagement/Shared Documents/02_Strategy/01_Portfolio Strategy/05_Product Passport/01_Large Appliances/ | G120: Attribute119Large Appliances-Refrigerators-Portable Refrigerators
A121: Akeneo | B121: Number of batteries main unit [qty] | C121: Large Appliances-Refrigerators-Portable Refrigerators | D121: Attribute120 | E121: Portable Refrigerators - Attributes V3.0.xlsx | F121: https://chaltecadmin.sharepoint.com/sites/ProductManagement/Shared Documents/02_Strategy/01_Portfolio Strategy/05_Product Passport/01_Large Appliances/ | G121: Attribute120Large Appliances-Refrigerators-Portable Refrigerators
A122: Akeneo | B122: Type of batteries main unit [type] | C122: Large Appliances-Refrigerators-Portable Refrigerators | D122: Attribute121 | E122: Portable Refrigerators - Attributes V3.0.xlsx | F122: https://chaltecadmin.sharepoint.com/sites/ProductManagement/Shared Documents/02_Strategy/01_Portfolio Strategy/05_Product Passport/01_Large Appliances/ | G122: Attribute121Large Appliances-Refrigerators-Portable Refrigerators
...

Sheet SKUAttributes
A1: SKU | B1: Name | C1: Picture | D1: e-star | E1: Family | F1: EOL | G1: Supplier | H1: Data Status | I1: Upload Status | J1: Date Last Upload Akeneo | K1: Category 5.0 & Segmentation | L1: Index | M1: L1 | N1: L2 | O1: L3 | P1: L4 | Q1: Family Name | R1: Project ID | S1: Segment 1 | T1: Segment 2 | U1: Segment 3 | V1: Segment 4 | W1: Segment 5 | X1: Listing & Data | Y1: Database Name | Z1: Char Count -> MAX 40 | AA1: Variant with SKU or Family: | AB1: Variation 1 | AC1: Variation 1 - Value | AD1: Variation 2 | AE1: Variation 2 - Value | AF1: Variation 3 | AG1: Variation 3 - Value | AH1: 1 . Category Specific Attributes | AI1: Supplier Part Number | AJ1: Nominal capacity [L] | AK1: Compartment [Single, Dual] | AL1: Dual Zone Control [Y/N] | AM1: Type of cooling system | AN1: Refrigerant Type | AO1: Refrigerant weight [g] | AP1: Climate Class | AQ1: Defrost Type [Manual, Auto, Drain] | AR1: Heating Feature [Yes/No] | AS1: Cooling Feature [Yes/No] | AT1: Min Cooling temperature [°C] | AU1: Max Heating temperature [°C] | AV1: Temperature Range [°C] | AW1: Cooling Time [°C/min] | AX1: Available Cables [Power Cable, Cigarette etc] | AY1: Length of AC cable [cm] | AZ1: Length of DC cable [cm] | BA1: Battery Life [h] | BB1: Battery protection [Y/N] | BC1: Solar Compatibility [Y/N] | BD1: Built-in Battery [Y/N] | BE1: (If yes) Capacity in Wh | BF1: [If applicable] Inverter Type | BG1: Housing Material | BH1: Insulation Material | BI1: Lid Type [Hinged, Split, Removable] | BJ1: Lid Opening Direction [Top, Side, Reversible] | BK1: Lid Material | BL1: Carry Handle [Y/N] | BM1: Telescopic Handle [Y/N] | BN1: Handle Material | BO1: Wheels [Y/N] | BP1: Adjustable divider insert [Y/N] | BQ1: Removable basket [Y/N] | BR1: Insulated Cover/Bag [Y/N] | BS1: Temperature display [N/A, LED, LCD] | BT1: Temperature control [Manual, Digital] | BU1: Integrated LED interior lighting [Y/N] | BV1: USB Port Charging Port [Y/N] | BW1: Safety Lock [Y/N] | BX1: Anti-Shake/Vibration Proof [Y/N] | BY1: Water Resistance Rating [IP] | BZ1: Overheat Protection [Y/N] | CA1: Battery Indicator | CB1: Eco Mode [Y/N] | CC1: Food Safe [Y/N] | CD1: Drainage plug [Y/N] | CE1: Quick Freeze Mode [Y/N] | CF1: Capacity in cans | CG1: Main Color | CH1: Secondary Color | CI1: Abreviation Color | CJ1: IoT/Smart | CK1: Additional Features | CL1: Special Attribute 1 | CM1: Special Attribute 2 | CN1: Special Attribute 3 | CO1: Special Attribute 4 | CP1: Special Attribute 5 | CQ1: 2. Standard Electric Specs | CR1: Energy efficiency class | CS1: Annual energy consumption [kWh/year] | CT1: Voltage Range [V / Hz] | CU1: Type of plug | CV1: Power cord length [m] | CW1: IEC protection class [Schutzklasse] | CX1: Power [W] | CY1: Noise Emission [dB] | CZ1: Noise Level Min-Max [db] | DA1: 3. Product Dimensions | DB1: Product Height [cm] | DC1: Product Width [cm] | DD1: Product Depth [cm] | DE1: Product weight [kg] | DF1: Internal compartment 1 Height [cm] | DG1: Internal compartment 1 Width [cm] | DH1: Internal compartment 1 Depth [cm] | DI1: Internal compartment 2 Height [cm] | DJ1: Internal compartment 2 Width [cm] | DK1: Internal compartment 2 Depth [cm] | DL1: Product Dimensions | DM1: 4. Battery Information - Mandatory for all items with batteries according to EU regulations | DN1: Number of batteries in accessories [qty] | DO1: Type of batteries in accessories [type] | DP1: Weight of one battery in accessories [g] | DQ1: Number of batteries main unit [qty] | DR1: Type of batteries main unit [type] | DS1: Weight of one battery main unit [g] | DT1: 5. Packaging & What is included | DU1: ISTA Level | DV1: How Many Boxes? [qty] | DW1: Box 1 - Content [what's inside?] | DX1: Box 2 - Content [what's inside?] | DY1: Box 3 - Content [what's inside?] | DZ1: 6. Acessories | EA1: Accessory 1 - Description | EB1: Accessory 1 - SKU | EC1: Accessory 2 - Description | ED1: Accessory 2 - SKU | EE1: Accessory 3 - Description | EF1: Accessory 3 - SKU | EG1: Accessory 4 - Description | EH1: Accessory 4 - SKU | EI1: Accessory 5 - Description | EJ1: Accessory 5 - SKU | EK1: 10.Amazon Title USPs | EL1: Amazon Title USP1 | EM1: Amazon Title USP2 | EN1: Amazon Title USP3 | EO1: Amazon Title USP4 | EP1: Amazon Title USP5 | EQ1: 11. Copywrite | ER1: Product Description | ES1: Bullet Point 1 | ET1: Bullet Point 2 | EU1: Bullet Point 3 | EV1: Bullet Point 4 | EW1: Bullet Point 5 | EX1: 99.Data Validations - DO NOT CHANGE | EY1: Akeneo Export? | EZ1: SAP Export? | FA1: SourceFile | FB1: SourcePath | FC1: Type Project (New, Replacement, Upgrade, Expansion) | FD1: Replacement of SKU No | FE1: SEOKeyword1 | FF1: SEOKeyword2 | FG1: SEOKeyword3 | FH1: SEOKeyword4 | FI1: Supplier Model Number | FJ1: Heating Type(Induction/Radiant etc) | FK1: Width cluster (cm) | FL1: Total Power with Booster (W) | FM1: Total Power (W) | FN1: Number of Heating elements | FO1: Flexzone (Y/N) | FP1: Autarkic (Y/N).1 | FQ1: Auto off function | FR1: Boost Zones(which cooking zones) | FS1: Zone 1 Power (W) | FT1: Zone 1 Power - Boost (W) | FU1: Zone 1 Size (cm) | FV1: Zone 2 Power (W) | FW1: Zone 2 Power - Boost (W) | FX1: Zone 2 Size (cm) | FY1: Zone 3 Power (W) | FZ1: Zone 3 Power - Boost (W) | GA1: Zone 3 Size (cm) | GB1: Zone 4 Power (W) | GC1: Zone 4 Power - Boost (W) | GD1: Zone 4 Size (cm) | GE1: Zone 5 Power (W) | GF1: Zone 5 Power - Boost (W) | GG1: Zone 5 Size (cm) | GH1: Zone 6 Power (W) | GI1: Zone 6 Power - Boost (W) | GJ1: Zone 6 Size (cm) | GK1: Flex Zone 1 Power - Boost (W) | GL1: Flex Zone 1 Power (W) | GM1: Flex Zone 2 Power - Boost (W) | GN1: Flex Zone 2 Power (W) | GO1: Flex Zone 3 Power - Boost (W) | GP1: Flex Zone 3 Power (W) | GQ1: Flex Zone Total Power (W) | GR1: Flex Zone with Booster (W) | GS1: Frame material | GT1: Residual heat indicator (Y/N) | GU1: Safety Child lock (Y/N) | GV1: Stop and Go feature (Y/N) | GW1: Temperature control (Y/N) | GX1: Timer (Y/N) | GY1: Top surface material | GZ1: Qty Individual Sliders(How many heating control sections) | HA1: Display Color(Red/White/Blue) | HB1: Type of Control(Touch/Button/Knobs) | HC1: Cut-Out Size (cm)(DxW) | HD1: Flex Configuration | HE1: Keep Warm Function(Yes/No) | HF1: SEO Keyword1 (Width cm) | HG1: SEO Keyword2 (Max Airflow Capacity m3/h) | HH1: SEO Keyword3 (Color) | HI1: SEO Keyword4 (EEC) | HJ1: Size(40, 60, 90, 120 etc.) | HK1: Air capacity/airflow (m³/h) Booster | HL1: Air capacity/airflow (m³/h) max | HM1: Air capacity/airflow (m³/h) min | HN1: Grease Filtering Efficiency (A-G) | HO1: Air Flow Efficiency (A-G) | HP1: Lighting Efficiency (A-G) | HQ1: Fan speed levels/ Power settings(1-10) | HR1: Number of Carbon Filters Included | HS1: Carbon Filter Dimensions (D x H) cm | HT1: Carbon Filter (Weight)g | HU1: Carbon Filter SKU Code | HV1: Aluminium Filter Dimensions (D x H) cm | HW1: Aluminium Filter (Weight) g | HX1: Aluminium Filter SKU Code | HY1: Grease Filter dishwasher safe (Y/N)? | HZ1: Duct outlet (mm) | IA1: Height chimney(max) | IB1: Height chimney(min) | IC1: Noise emission(dB) at Boost level | ID1: Noise emission(dB) at MAX power level | IE1: Noise emission(dB) at MIN power level | IF1: Number of built-in work lights | IG1: Number of layers filter system 1 | IH1: RGB (Yes/No)? | II1: No. of Available RGB Colors | IJ1: Type of built-in work lights (LED/Bulb) | IK1: Light (LED) power (W) | IL1: Type of Control (Touch / Button / Push / Switch / ..) | IM1: Type of Motor (AC/DC) | IN1: Motor Power | IO1: Exhaust Hose Included? (Yes/No) | IP1: Air Cleaning/Purification System? (Yes/No) | IQ1: Odor or Steam Sensor(Yes/No) | IR1: Material of Chimney(Stainless Steel/Coated Steel etc) | IS1: Auto Shut Off Function/Timer? Yes/No | IT1: Carbon Filter Included? (Yes/No) | IU1: SEO Keyword1 (kg Ice) | IV1: SEO Keyword2 (Liter) | IW1: Product Type (Countertop, Undercounter, Built-In, Commercial) | IX1: Daily Ice Production Capacity (kg/d) | IY1: Ice Basket Capacity (kg) | IZ1: Net Water Tank Capacity (L) | JA1: Water Tank Capacity for cold water (L) | JB1: Water Tank Capacity for hot water (L) | JC1: Ice Shape (Bullet, Nugget, Cube etc) | JD1: Ice Cube Size Options (Small, Medium, Large) | JE1: Short Cycle (cubes/min) | JF1: Cold Water Dispenser (Y, N) | JG1: Hot Water Dispenser (Y, N) | JH1: Crushed Ice (Y,N) | JI1: Control Panel Type (Digital, Push Button, Touchscreen) | JJ1: Display Type (LCD, LED etc) | JK1: Ice Basket Full Indicator (Y, N) | JL1: Water Tank Empty Indicator (Y, N) | JM1: Auto Clean Function (Y,N) | JN1: Timer Function (Y, N) | JO1: Auto Shut-Off Function (Y, N) | JP1: Child Lock (Y, N) | JQ1: Removable Ice Basket (Y, N) | JR1: Viewing Window (Y, N) | JS1: Interior Lighting (Y, N) | JT1: Carry Handle (Y, N) | JU1: Ice Scoop Included (Y, N) | JV1: Manual Water Fill (Y, N) | JW1: Plumbed Water Fill (Y,N) | JX1: Water Hose / Drain Hose Included (Y,N) | JY1: Housing Material (Plastic, Stainless Steel, ABS etc) | JZ1: Finish (Stainless Steel, Matte etc) | KA1: SEO Keyword1 (Width) | KB1: SEO Keyword2 (no burners) | KC1: SEO Keyword4 | KD1: Installation Type (Built in / Standalone / Flush) | KE1: Number of Burners | KF1: Cooking zone 1 Size (cm) | KG1: Cooking zone 1 Power (W) | KH1: Cooking zone 2 Size (cm) | KI1: Cooking zone 2 Power (W) | KJ1: Cooking zone 3 Size (cm) | KK1: Cooking zone 3 Power (W) | KL1: Cooking zone 4 Size (cm) | KM1: Cooking zone 4 Power (W) | KN1: Cooking zone 5 Size (cm) | KO1: Cooking zone 5 Power (W) | KP1: Cooking zone 6 Size (cm) | KQ1: Cooking zone 6 Power (W) | KR1: Total Power(W) | KS1: Type of control | KT1: Frame/Burner material | KU1: Gas connection | KV1: Gas Connection convertible? | KW1: Auto Ignition(Y/N) | KX1: Flame failure device/safety(Auto Shut off) | KY1: Cut-Out Width | KZ1: Cut-Out Depth | LA1: Position of Controls | LB1: Autarkic (y/n) | LC1: Operation Indicator Light (y/n) | LD1: Compatible Type of Gas | LE1: Width Cluster | LF1: Hose&Regulator Set Included?(Y/N) | LG1: Suitable Cabinet Size(40, 60, 90, 120 etc.) | LH1: Motor Power(W) | LI1: Height of the Housing inside cabinet | LJ1: Width of the Housing inside cabinet | LK1: Lighting Power(W) | LL1: RGB (Y/N)? | LM1: Motor usable with carbon filter?(Yes/No) | LN1: Carbon Filter Included?(Yes/No) | LO1: Exhaust Hause Included? (Yes/No) | LP1: Number of Carbon Filters Necessary for the motor? | LQ1: Auto Shut Off Function/Timer?( Yes/No) | LR1: Gas Strut for the Lid? (Yes/No) | LS1: Timer(Yes/No) | LT1: SEO Keyword2 (Bottles) | LU1: SEO Keyword4 (Cooling Zones) | LV1: Installation Type [Freestanding/Built in/Built Under] | LW1: Nominal capacity [Bottles] | LX1: Number of Cooling Zone | LY1: Naming for No of Cooling Zone | LZ1: Type of cooling cooling system [Compressor/Thermo] | MA1: Refrigerant type.1 | MB1: Fan System (internal circulation fan, forced air) | MC1: Capacity Zone 1 (bottles) | MD1: Capacity Zone 2 (bottles) | ME1: Capacity Zone 3 (bottles) | MF1: Max Bottle height Zone 1 (cm) | MG1: Max Bottle height Zone 2 (cm) | MH1: Max Bottle height Zone 3 (cm) | MI1: Temperature Zone 1 range(°C Min-Max) | MJ1: Temperature Zone 2 range(°C Min-Max) | MK1: Temperature Zone 3 range(°C Min-Max) | ML1: Independent Controls per Zone [Y/N] | MM1: Temperature control [Mechanic, Electronic] | MN1: Control Panel Type [Digital, Push Button, Touchscreen] | MO1: Number of shelfs | MP1: Shelf Material (wood, beech wood, wire, metal, chrome) | MQ1: Shelf Type (sliding, fixed, telescopic, removable) | MR1: Shelf Color | MS1: Adjustable Shelves Height [Y/N] | MT1: Door opening direction [Right/Left/Top] | MU1: Door hinge changeable [Y/N] | MV1: Door Type | MW1: Height adjustable feet [Y/N] | MX1: Interior lighting Type (LED, RGB) | MY1: Interior lighting color options | MZ1: Humidity Control (yes/no, adjustable %, passive, active) | NA1: Door Open Alarm [Y/N] | NB1: Safety lock [Y/N].1 | NC1: Glass / Storage Rack [Y/N] | ND1: Carbon Filter [Y/N] | NE1: Handle Type [Integrated, Bar, Recessed, Push Open System] | NF1: Body Material (steel, aluminum) | NG1: SEO Keyword2 (air flow) | NH1: Motor Power (Watt) | NI1: SEO Keyword4 (Zones) | NJ1: SEO Keyword1 (width)16 | NK1: SEO Keyword2 (burners) | NL1: SEO Keyword3 (color)17 | NM1: SEO Keyword4 (power) | NN1: SEO Keyword2 (Air Flow)18 | NO1: Grease Filter dishwasher safe (Yes/No)? | NP1: Height chimney(max)(mm) | NQ1: Height chimney(min)(mm) | NR1: Light (LED) power | NS1: SEO Keyword2 (No Burners)19 | NT1: Type of Flex Zone(Dual, Triple, Oval) | NU1: Power Levels Settings/steps | NV1: Type of Control(Touch/Button/Knob) | NW1: Temperature control | NX1: Timer | NY1: Auto Saftey switch off | NZ1: Residual heat | OA1: Residual heat indicator(H) | OB1: Rapid heating | OC1: Pot detection | OD1: Visual indication | OE1: Safety lock(Child Lock) | OF1: Overheating protection | OG1: Ignition | OH1: Flame failure device | OI1: Own Temperature Control for each stove | OJ1: Dimensions (cm) | OK1: Net Weight(kgs) | OL1: Width Niche | OM1: Depth | ON1: Height | OO1: Finish | OP1: Country of Manufacturing | OQ1: Product Type | OR1: Features & Functions | OS1: Flexzone (y/n).1 | OT1: No. of Phases | OU1: Cooking Zones Frame | OV1: Cable and Plug included (y/n) | OW1: Slim Cluster | OX1: HOOD SPECIFICATIONS | OY1: Exhaust system (Exhaust / Carbon Filter / Exhaust + Carbon Filter) | OZ1: Filter system 1 (Aluminium / Carbon) | PA1: Filter system 2 (Aluminium / Carbon) | PB1: Auto Sync with Hob Speed (Y/N)? | PC1: HOB SPECIFICATIONS | PD1: Nominal Size | PE1: Quantiy of Cooking Zones [qty] | PF1: Total Induction Power (W) | PG1: Total induction Power - Boost (W) | PH1: Induction Zone: Left Front (W) | PI1: Induction Zone: Left Front - BOOST (W) | PJ1: Induction Zone : Left Front (Size)(W*H) | PK1: Induction Zone: Right Front (W) | PL1: Induction Zone: Right Front - BOOST (W) | PM1: Induction Zone : Right Front (Size) | PN1: Induction Zone: Left Rear (W) | PO1: Induction Zone: Left Rear - BOOST (W) | PP1: Induction Zone : Left Rear (Size) | PQ1: Induction Zone: Right Rear (W) | PR1: Induction Zone: Right Rear - BOOST (W) | PS1: Induction Zone: Right Rear (Size) | PT1: Induction Zone: Center (W) | PU1: Induction Zone: Center - BOOST (W) | PV1: Induction Zone: Center (Size) | PW1: Flex Mode Zones (qty) | PX1: Timer (Y/N)? | PY1: Stop & Go feature (ThermoRecall) (Y/N)? | PZ1: Residual Heat Indicator (Eco Energy func.) (Y/N)? | QA1: Auto Switch-off function (Y/N)? | QB1: Keep Warm (Y/N)? | QC1: Low Power Continuous Heating (Y/N)? | QD1: Child Lock (Y/N)? | QE1: Timer Minute Range (Minutes) | QF1: Fluid Dynamic Efficiency | QG1: Fluid Dynamic Efficiency class | QH1: Grease Filtering Efficiency | QI1: Grease Filtering Efficiency class | QJ1: Air flow (min speed normal use) | QK1: Air flow (max speed normal use | QL1: Air flow (intensive or boost use) | QM1: Airborne acoustical A-weighted sound power emissions (min speed normal use) | QN1: Airborne acoustical A-weighted sound power emissions (max speed normal use) | QO1: Airborne acoustical A-weighted sound power emissions (intensive or boost use) | QP1: Power consumption in standby mode (W) | QQ1: Thickness of th plate | QR1: Pot Detection (Yes/No) | QS1: Flex Zone Left Power (W) | QT1: Flex Zone Left Power Booster (W) | QU1: Flex Zone Right Power (W) | QV1: Flex Zone Right Power Booster (W) | QW1: Flex Zone Total Power(W) | QX1: Flex Zone with Booster(W) | QY1: Frame Material.1 | QZ1: Top Surface Material.1 | RA1: Size cluster (40, 60, 90, 120 etc.) | RB1: Fan Speed levels/ Power settings (1-10) | RC1: Carbon Filter Dimensions (D x W) cm | RD1: Aluminium Filter Dimensions (D x W) cm | RE1: Aluminum Filter SKU Code | RF1: Grease Filter dishwasher safe (Yes/No) | RG1: Height chimney (max) | RH1: Height chimney (min) | RI1: Cut out Dimension (W x D) mm | RJ1: RGB (Yes/No) | RK1: Number of Available RGB Colors | RL1: Type of Control (Touch / Button / Push / Switch / etc.) | RM1: Exhaust Hose Included (Yes/No) | RN1: Exhaust Hose Qty | RO1: Exhaust Hose Length (m) | RP1: Air Cleaning/Purification System (Yes/No) | RQ1: Odor or Steam Sensor (Yes/No) | RR1: Auto Shut Off Function/Timer (Yes/No) | RS1: Carbon Filter Included (Yes/No) | RT1: Finish/material (Visible Panel) | RU1: Exhaust Hose Orientation (Down/Rear/Side) | RV1: Mounting Style (Flush-mounted / Surface Mounted with frame) | RW1: Remote Control (Yes/No) | RX1: Power Consumption in Standby Mode (W) | RY1: SEO Keyword1 (Amount of cigars) | RZ1: SEO Keyword2 (volume) | SA1: SEO Keyword3 | SB1: Product Type [Cigar Storage/Wine and Cigar combo] | SC1: Cigar Capacity [by count] | SD1: Wine bottle capacity [by count] | SE1: Temperature Zone 1 range [°C Min-Max] | SF1: Temperature Zone 2 range [°C Min-Max] | SG1: Ideal Ambient Temperature | SH1: Humidity Level Range [% ] | SI1: Humidification System Type [fan system, digital humidifier, humidifier spone etc] | SJ1: Humidity Regulation Method [manual, automatic, smart control] | SK1: Hygrometer Type [Analog/ Digital] | SL1: Number of Shelfs.1 | SM1: Shelf Material | SN1: Number of Drawers | SO1: Drawer Material | SP1: Display Window Type [Glass/Acrylic etc] | SQ1: Display Type [LCD, LED etc] | SR1: Interior lighting [LED/Adjustable/None] | SS1: Door hinge position [Right/Left] | ST1: Water Type Recommended [Distilled/Demineralized] | SU1: Water bowl provided [Y/N] | SV1: Exterior Material | SW1: Interior Lining Material | SX1: SEO Keyword1(Width) | SY1: SEO Keyword2(no programms) | SZ1: Type | TA1: Can be Built-In? (Yes/No) | TB1: Portable | TC1: Place Setting | TD1: Water consumption standard program(L) | TE1: Depth with the door open(cm) | TF1: Inlet hose length(cm) | TG1: Drain hose length(cm) | TH1: Water connection | TI1: Water Tank | TJ1: Max. Plate diameter (cm) | TK1: Number of cleaning Programms | TL1: Programme 1 | TM1: Programme 2 | TN1: Programme 3 | TO1: Programme 4 | TP1: Programme 5 | TQ1: Programme 6 | TR1: Programme 7 | TS1: Programme 8 | TT1: Programme9 | TU1: Time display | TV1: Programm display | TW1: Aquastop (Water leakage protection) | TX1: Child safety lock | TY1: Built in Cabinet dimensions (WxHxD) cm | TZ1: SEO Keyword2 (no programs) | UA1: SEOKeyword1 - Liters | UB1: SEOKeyword2 - Height | UC1: Installation Type [Freestanding/Built in] | UD1: No. of Bottles | UE1: Min temperature [°C] | UF1: Max temperature [°C] | UG1: Defrost Type | UH1: Door Material | UI1: Interior lighting [Y/N] | UJ1: Temperature alarm [Y/N] | UK1: Handle Type | UL1: SEO Keyword1 (Height) | UM1: SEO Keyword2 (Liters) | UN1: Installation Type [Freestanding/Built In/Built Under].1 | UO1: Product Type [Upright/ Chest] | UP1: Type of cooling system [Compressor/Thermo] | UQ1: Compressor Type | UR1: Star Classification | US1: Defrost Type [NoFrost, Manual, Auto, Drain] | UT1: Ideal ambient temperature [°C] | UU1: Temperature control [Manual, Digital] | UV1: Temperature Control Panel [Internal, External] | UW1: Cube tray included [Y/N] | UX1: Compartement Type [Shelf/Drawer/Basket] | UY1: (If Shelves) Number of shelfs | UZ1: (If Shelves) Material of shelfs [Wire, Glass, Pastic etc] | VA1: (If Shelves) Adjustable Shelves Height [Y/N] | VB1: (If Drawers) Number of Drawers | VC1: (If Drawers) Material of drawers [Wire, Glass, Pastic etc] | VD1: (If Baskets) Number of Baskets | VE1: (If Baskets) Material of baskets [Wire, Glass, Pastic etc] | VF1: (If Baskets) Removable Baskets [Y/N] | VG1: Cooling Chamber material | VH1: Door hinge position [Right/Left/Top] | VI1: Handle Type [Integrated, Bar, Recessed] | VJ1: Interior Lighting [Y/N].1 | VK1: Child Safety [Y/N] | VL1: On/Off switch [Y/N] | VM1: Temperature Alarm [Y/N].1 | VN1: Super/Quick FreezeFunction [Y/N] | VO1: Adjustable freezer temperature [Y/N] | VP1: Eco Mode [Y/N] | VQ1: Flexible Fridge and Freezer Function [Y/N] | VR1: Drain valve [Y/N] | VS1: SEO Keyword2 (Airflow) | VT1: Exhaust system (Exhaust / Recirculation/Exhaust+Recirculation) | VU1: Installation Type [Freestanding, Built in] | VV1: Type of cooling system [Compressor, Thermo] | VW1: Fridge compartment [Y/N] | VX1: Freezer compartment [Y/N] | VY1: Chiller compartment (IceBox) [Y/N] | VZ1: Total Net capacity [L] | WA1: Refrigerator Net capacity [L] | WB1: Freezer Net capacity [L] | WC1: Cooling Technology [Defrost, No Frost] | WD1: Defrost Type [Automatic, Semi-Automatic, Manual] | WE1: Cooling Capacity [°C] | WF1: Temperature control type [Mechanic, Electronic] | WG1: Shelf type [Plastic, Glass, Aliminum] | WH1: Door hinge position [Right, Left] | WI1: Door reversible [Y/N] | WJ1: Interior LED light [Y/N] | WK1: Handle Type [Integrated, Bar, Recessed, Grip] | WL1: SEO Keyword2(no burners) | WM1: SEO Keyword3(Color) | WN1: SEO Keyword2 (No Programms) | WO1: Product Type (Top-Freezer, Bottom-Freezer) | WP1: Compressor Type [Standard, Digital Inverter, Linear Compressor] | WQ1: Climate Class [SN, N, ST, T] | WR1: Cooling Capacity Fridge [°C] | WS1: Cooling Capacity Freezer [°C] | WT1: Number of Drawers [0,1,..] | WU1: Freezer Compartment [1,2,..] | WV1: Door Type [Flat, Curved, French, Split] | WW1: Fingerprint-Resistant Coating [Y/N] | WX1: Fire Retardant Back [Y/N] | WY1: Child Lock [Y/N] | WZ1: Humidity Control for fruits/vegetables [Y/N] | XA1: Standard Size (45, 60, 90) | XB1: Top Heater Power (W) | XC1: Top Inner Heater Power (W) | XD1: Bottom Heater Power (W) | XE1: Ring Heater Power (W) | XF1: Cavity Size (l) | XG1: Number of Functions | XH1: Control Type | XI1: Pyrolyse (Y/N) | XJ1: Hook In Rack System (Y/N) | XK1: Inner Lamp Type | XL1: Number of Glass Layers on Door | XM1: Number of Shelf Level | XN1: Number of Telescopic Rails | XO1: Temperature Range(°C) | XP1: Timer Range(min) | XQ1: Child Lock(y/n) | XR1: Cut Out Size | XS1: Temperature Probe (Y/N) | XT1: Grid Tray | XU1: Normal Tray | XV1: Deep Tray | XW1: Air Fry Basket | XX1: SEO Keyword1 (Liter) | XY1: SEO Keyword2 (Height) | XZ1: Amazon Data | YA1: ASIN | YB1: SEO Keyword2 (No Plates) | YC1: Housing material.1 | YD1: Grill area size (cm) | YE1: Burner Material | YF1: Burner Output (W) | YG1: Total output (W) | YH1: Ignition type | YI1: Heat level details | YJ1: Grates included (Yes/No) | YK1: Grate material | YL1: Control type.1 | YM1: Gas type | YN1: Gas cylinder type | YO1: Gas Bottle Storage (Yes/No) | YP1: Gas Bottle Storage Size (kg) | YQ1: Gas pressure | YR1: Cooking chamber material | YS1: Warming rack (Yes/No) | YT1: Sear Zone (Yes/No) | YU1: Side burner (Yes/No) | YV1: Even heat distribution (Yes/No) | YW1: Power outlet required (Yes/No) | YX1: Wheels (Yes/No) | YY1: Thermometer (Yes/No) | YZ1: Grease tray included (Yes/No) | ZA1: Grill height with lid open (cm) | ZB1: Automatic Switch Off (Yes/No) | ZC1: Overheating Protection (Yes/No) | ZD1: Rain Cover Included (Yes/No) | ZE1: Tilting Protection (Yes/No) | ZF1: Accessories | ZG1: Shape | ZH1: Fire pit size(cm) | ZI1: Grill grate size(cm) | ZJ1: Fire Grate Size (cm) | ZK1: Fire pit thickness(mm) | ZL1: Plancha Material | ZM1: Cooking Grate Material | ZN1: Body / Frame Material | ZO1: Coating / Finish | ZP1: Ash Tray (Y/N) | ZQ1: Poker (Y/N) | ZR1: Rain Cover (Y/N) | ZS1: Cooking grate (Y/N) | ZT1: Fire grate (Y/N) | ZU1: Spark protection (Y/N) | ZV1: Grill Grate (Y/N) | ZW1: Storage (Y/N) | ZX1: Adaptable Table (Y/N) | ZY1: Wheels | ZZ1: Fuel | AAA1: Max Power | AAB1: Grill Surface [cm] | AAC1: Grill grate material | AAD1: Grill grate number | AAE1: Side tables [Y/N] | AAF1: Side table dimensions [cm] | AAG1: Integrated thermometer [Y/N] | AAH1: Height Adjust Sytem for heat control [Y/N] | AAI1: Fire bowl thickness [mm] | AAJ1: Cool Touch Handle on Lid [Y/N) | AAK1: Floor rollers [Y/N) | AAL1: Storage [Y/N) | AAM1: Thermostat [Y/N) | AAN1: Temperature range (°C) | AAO1: Power supply | AAP1: SEO Keyword1 (size) | AAQ1: SEO Keyword2 | AAR1: Overall Dimension (WxHxD) (cm) | AAS1: Clearance Height (cm) | AAT1: Internal Space Dimension (WxHxD) (cm) | AAU1: Roof Material | AAV1: Roof Material Washable? (Y/N) | AAW1: Roof Fabric density (gsm) | AAX1: Roof Max Load (kg) - for hardtop only | AAY1: Roof Max Snow load (cm) | AAZ1: Roof Removable (Y/N) | ABA1: Roof Type (hardtop / soft-top / louvered) | ABB1: No. of louvers | ABC1: Louver dimensions | ABD1: Roof Open/close Mechanism (e.g sliding) | ABE1: Water Drainage on the Roof (Y/N) | ABF1: UV Protection (Y/N) | ABG1: Waterproof (Y/N) | ABH1: Side wall Included (Y/N) | ABI1: Side Wall Material | ABJ1: Side Walls Fabric Density (gsm) | ABK1: Side wall mechanism | ABL1: Ground Mounting Tool Included | ABM1: Surface Coating Type (powder-coated, anodized, galvanized) | ABN1: Mosquito Net Included (Y/N) | ABO1: Roof Hook (Y/N) | ABP1: Light (Y/N) | ABQ1: Light Source Type (LED, etc) | ABR1: Light Replaceable (Y/N) | ABS1: Light Color Change (Y/N) | ABT1: Dimmable (Y/N) | ABU1: Remote Control (Y/N) | ABV1: Installation Time (min) | ABW1: Minimum Number of people Required for the assembly | ABX1: Solar Panel (Y/N) | ABY1: Form Style or Shape (circular/square/rectangular) | ABZ1: Mounting Necessary (Y/N) | ACA1: Adjustable height (Y/N | ACB1: No. of Columns | ACC1: Main Beams Section Dimension | ACD1: Secondary Beam Section Dimension | ACE1: Total no. of pieces | ACF1: Total weight of aluminum pieces | ACG1: Total weight of steel pieces | ACH1: Total Fabric Weight | ACI1: Total PC Board Weight | ACJ1: Country of Origin (metal components) | ACK1: No. of Sidewalls | ACL1: Area Covered (m2) | ACM1: Sidewalls Foldable (Y/N) | ACN1: Sidewalls detachable (Y/N) | ACO1: Windows in Sidewalls (Y/N) | ACP1: Capacity / Volume [liters] | ACQ1: Frame Finish | ACR1: Thickness (mm) | ACS1: With Lid [Y/N] Or Zipper [Y/N]? | ACT1: With Green House [Y/N]? | ACU1: Screws Material [SS/Galvanized] | ACV1: Levels | ACW1: Number of trays | ACX1: Tray dimensions (W x H x D) (cm) | ACY1: Material of trays | ACZ1: Dishwasher safe trays (Yes/No) | ADA1: Usable drying area (m²) | ADB1: Spacing between trays (cm) | ADC1: Material housing | ADD1: Adjustable Temperature range (°C) | ADE1: Control (digital vs manual) | ADF1: Interface (Knobs, Buttons, Touch,) | ADG1: Type of display (LCD, LED, TFT) | ADH1: Timer range (24-48h) | ADI1: Number of preset programmes | ADJ1: Type of preset programmes (fruit, meat, herbs, etc.) | ADK1: Fan position (rear/side vs top) | ADL1: Inner light | ADM1: Auto Shut-off (Yes/No) | ADN1: Overload Protection(Yes/No) | ADO1: Viewing window (Yes/No) | ADP1: Commercial vs household use | ADQ1: Capacity (l) | ADR1: Adjustable temperature | ADS1: Adjustable timer | ADT1: Timer range (min) | ADU1: Auto shut off | ADV1: Overheat protection | ADW1: Dishwasher safe accessories | ADX1: Heat resistant parts | ADY1: Control | ADZ1: Control Feature | AEA1: Tap Material | AEB1: Jar Rack / Insert Grid | AEC1: Accessories provided | AED1: Keep warm | AEE1: Water level indicator | AEF1: Cord storage | AEG1: Non-sleep feet | AEH1: On/off button | AEI1: functional capcity(that it can be applied for more purpose) | AEJ1: SEO Keyword1 (Power) | AEK1: SEO Keyword2 (Pressure) | AEL1: SEO Keyword 3 (Color) | AEM1: Extraction method | AEN1: Boiler [single - dual] | AEO1: Material | AEP1: Integrated Grinder [Y/N] | AEQ1: Grind levels | AER1: Hopper (Grinder) capacity [gr] | AES1: Grind adjustable coffee quantity [Y/N] | AET1: Steam Milk [Y/N] | AEU1: Integrated Milk Tank [Y/N] | AEV1: Integrated digital display [Y/N] | AEW1: Adjustable water temperature [Y/N] | AEX1: Pressure [bar] | AEY1: Pump brand & type | AEZ1: Integrated Pressure gauge | AFA1: Height adjustment Cup [Y/N] | AFB1: Cup warming tray [Y/N] | AFC1: Hot water tap | AFD1: Water tank capacity [L] | AFE1: Strainer Insert | AFF1: Measuring spoon [Y/N] | AFG1: Tamper included [Y/N] | AFH1: Permanent filter [Y/N] | AFI1: Machine type | AFJ1: [If filter] number of cups | AFK1: Temperature Max [C] | AFL1: Temperature Min [C] | AFM1: Timer setting max [Min] | AFN1: Timer function - timed start | AFO1: Switchable rotation [Y/N] | AFP1: Universal program [Y/N] | AFQ1: Grill skewer program [Y/N] | AFR1: Handle cage program [Y/N] | AFS1: Baking program [Y/N] | AFT1: Pizza program | AFU1: Steak program | AFV1: Shashlik program | AFW1: Removable metal inlay | AFX1: Non Stick coating | AFY1: Manual temperature setting option [Y/N] | AFZ1: Lid lock | AGA1: Automatic shutdown | AGB1: Acoustic signals | AGC1: Fan ventilation | AGD1: Display [LCD/Digital] | AGE1: Optional accessory Steamer insert [Y/N] | AGF1: Optional accessory Steak cage [Y/N] | AGG1: Optional rotisserie rotator [Y/N] | AGH1: Maximum capacity chicken [Kg] | AGI1: Maximum capacity diameter pizza [cm] | AGJ1: Capacity [L] | AGK1: Total number of program | AGL1: Steamer function [Y/N] | AGM1: Dehydration mode [Y/N] | AGN1: SEO Keyword1 (power)20 | AGO1: SEO Keyword2 (liters)21 | AGP1: Food processor jar capacity (L) | AGQ1: Food processor Material | AGR1: Blender jar Capacity (L) | AGS1: Blender Material | AGT1: Number of Blades | AGU1: Material blades | AGV1: Control (Manual/Digital) | AGW1: Revolution (RPM) | AGX1: Speed levels | AGY1: Pulse function | AGZ1: Programmes | AHA1: Self-cleaning function | AHB1: Dsiplay (LED, LCD, TFT) | AHC1: Adjustable Timer2 | AHD1: Diswasher safe parts | AHE1: Cutting disc(s) | AHF1: Dough blade | AHG1: Blender to go | AHH1: Capacity blender to go | AHI1: Juicer attachment | AHJ1: Cleaning Brush | AHK1: Antislip base | AHL1: Child lock | AHM1: Auto Shut-off | AHN1: Bag accesories | AHO1: Recipes provided | AHP1: SEO Keyword1 (Liters) | AHQ1: SEO Keyword2 (Power) | AHR1: Cooling method | AHS1: Modes | AHT1: Functions | AHU1: Keep cool function | AHV1: Yogurt function | AHW1: Juice Maker | AHX1: Smoothie Maker | AHY1: Container material | AHZ1: Display | AIA1: Controls | AIB1: Motor self-protection | AIC1: Coolant | AID1: Cooling temperature range | AIE1: Container dimensions (HxØ) (cm) | AIF1: Motor | AIG1: Interface Control | AIH1: Lid safety lock | AII1: Antislippery rubber feet | AIJ1: Recipes included | AIK1: Self cleaning | AIL1: Ice cream hardness selection | AIM1: Mixing function | AIN1: SEO Keyword2 (attachments) | AIO1: SEO Keyword4 (Flour capacity) | AIP1: Capacity dry flour (g) | AIQ1: Capacity (portions) | AIR1: Fully Automatic | AIS1: Material mixing paddle | AIT1: Control (Mechanic/Digital) | AIU1: Number of Attachments | AIV1: Type of attachments | AIW1: Dishwasher safe attachements | AIX1: Ravioli shape accessory | AIY1: Dishwasher safe ravioli accessory | AIZ1: Pastry cutter | AJA1: Dishwasher safe pastry cutter | AJB1: Measuring cup for flour | AJC1: Measuring cup for water | AJD1: Dishwasher safe cups | AJE1: Settings | AJF1: Adjustable thickness settings | AJG1: Pre-set progammes(gluten-free, wholewheat, etc.) | AJH1: Preparation time (minutes) | AJI1: Pasta finish time (minutes) | AJJ1: Integrated scale | AJK1: Storage compartment | AJL1: Auto-shut off | AJM1: SEO Keyword2 (no blades) | AJN1: Material feed screw | AJO1: Material tray | AJP1: Number of cutting plates | AJQ1: Types of cutting plates | AJR1: Material cutting plates | AJS1: Dishwasher safe cutting blades | AJT1: Sausage/Kibbe attachment | AJU1: Dishwasher safe sausage/kibbe attachment | AJV1: Cheese attachment | AJW1: Dishwasher safe cheese attachment | AJX1: Cookie/Pastry attachment | AJY1: Dishwasher safe cookie/pastry attachment | AJZ1: Vegetable slicer/shredder attachement | AKA1: Dishwasher safe vegetable attachment | AKB1: Fruit juicer attachement | AKC1: Dishwasher safe fruit juicer attachment | AKD1: Food pusher | AKE1: Reverse function | AKF1: Variable speed settings | AKG1: Motor (AC/DC/BLDC) | AKH1: Material motor | AKI1: Easy disassembly | AKJ1: Easy cleaning | AKK1: Type of display | AKL1: Capacity per minute (Kg) | AKM1: Auto Shut-Off3 | AKN1: Safety lock | AKO1: Non-slip operation | AKP1: Cable storage | AKQ1: Storage container | AKR1: Cooling method (Thermoelectrical/Compressor) | AKS1: Keg Capacity (L) | AKT1: 5L Pressured Keg | AKU1: 5L Common Keg | AKV1: Dispense system (Air Pump / CO₂ Cartridge) | AKW1: Lowest temperature | AKX1: Shelf life day count down indicator | AKY1: Temperature level indicator | AKZ1: Display (LED, LCD; TFT) | ALA1: Control (Button, Touch, Knob) | ALB1: Power button | ALC1: Removable dip tray | ALD1: Manual Keg installation | ALE1: Tap type (Lever / Push tap) | ALF1: Blender Jar Capacity (L)4 | ALG1: Blender Jar Material | ALH1: Number of programmes | ALI1: Pusher | ALJ1: Measuring cup | ALK1: Bowl Capacity (liters) | ALL1: Maximal dough (kg) | ALM1: Maximal flour (kg) | ALN1: Bowl Material | ALO1: Bowl dishwasher safe | ALP1: Rounds per minute MIN(RPM) | ALQ1: Rounds per minute MAXN(RPM) | ALR1: Maximum working time before cooling time needed in (min) | ALS1: Drive System (Gear) | ALT1: Planetary stirring system? | ALU1: Number of speed settings | ALV1: Digital Display | ALW1: Beater Included? | ALX1: Beater Material | ALY1: Beater Dishwasher safe | ALZ1: Dough Hook Included? | AMA1: Dough Hook Material | AMB1: Dough Hook Dishwasher safe | AMC1: Wire Whisk Included? | AMD1: Wire Whisk Material | AME1: Wire Whisk Dishwasher safe | AMF1: Splash guard Included? | AMG1: Splash guard Material | AMH1: Splash guard Dishwasher safe | AMI1: Meatgrinder Included? | AMJ1: Meatgrinder Material | AMK1: Meatgrinder Dishwasher safe | AML1: Vegetable cutter Included? | AMM1: Vegetable cutter Material | AMN1: Vegetable cutter Dishwasher safe | AMO1: Slicer included? | AMP1: Slicer Material | AMQ1: Slicer Dishwasher safe | AMR1: Salad Maker Included? | AMS1: Blender Included? | AMT1: Blender Size(liters) | AMU1: Blender Dishwasher safe | AMV1: Food Processor Included? | AMW1: Juicer Included? | AMX1: Pasta maker Included? | AMY1: Cookie mold Included? | AMZ1: Sausage maker Included? | ANA1: Mill grinder Included? | ANB1: Ice cream bowl Included? | ANC1: Automatic switch-off | AND1: Recipe book included | ANE1: Other accessories included? | ANF1: Accessory 6 - Description | ANG1: Accessory 6 - SKU | ANH1: Feeding Tube/Mouth (mm) | ANI1: Speed RPM | ANJ1: Capacity container (L) | ANK1: Capacity small container (L) | ANL1: BPA free container | ANM1: Single/Double auger | ANN1: Material Auger | ANO1: Pulp extractor | ANP1: Automatic self-cleaning | ANQ1: Material filter | ANR1: On/Off button5 | ANS1: Dishwasher safe parts | ANT1: Food Pusher6 | ANU1: Anti-slip feet | ANV1: Max. continuous operating time (mins) | ANW1: Over heat protection | ANX1: Lock system | ANY1: Horizontal/Vertical Juicer | ANZ1: Capacity (L).1 | AOA1: Electric powered | AOB1: Cooktop suitable | AOC1: Type of cooktop | AOD1: Number of Power seetings | AOE1: Power range (W) | AOF1: Thermostat | AOG1: Control temperature range (°C) | AOH1: Timer | AOI1: Brewing method (extract, all-grain) | AOJ1: Type of ingredients supported (Malt extract, hopped extract, grains, hops, yeast) | AOK1: Temperature indication | AOL1: Outlet valve included | AOM1: Pump included | AON1: Circulation system | AOO1: Automatic programs | AOP1: Removeable parts | AOQ1: Easy to clean | AOR1: Other accessories included | AOS1: Main function | AOT1: Power (W) | AOU1: Multi-purpose (Yes/No) | AOV1: Suitable for (which food type?: Pizza, meat, seafood, vegetables, bread etc.) | AOW1: Max Temperature (C°) | AOX1: Temperature range (C°) | AOY1: Preheat time to max temp (min) | AOZ1: Avg. Pizza baking Time | APA1: Heating technology (Top/bottom heating / Dual heating etc.) | APB1: Heating element material | APC1: Pizza stone included (Yes/No) | APD1: Pizza Stone material | APE1: Pizza Stone size | APF1: Stone removable (Yes/No) | APG1: Stone rotating (Yes/No) | APH1: Max pizza diameter | API1: Cooking chamber dimensions (W x D x H) (cm) | APJ1: Exhaust type (Open front / rear vent / chimney etc.) | APK1: Surface finish (Brushed / Polished / Shiny / Matt) | APL1: Control type (Knobs / Buttons / Touch panel etc.) | APM1: Display (LED, LCD, TFT) | APN1: Timer (Yes/No) | APO1: Ready to bake indicator (Yes/No) | APP1: Cool Touch surface (Yes/No) | APQ1: Auto shut-off (Yes/No) | APR1: Overheat protection (Yes/No) | APS1: Child lock (Yes/No) | APT1: Suitable for cast-iron pans (Yes/No) | APU1: Baking tray included (Yes/No) | APV1: Removable crumb tray / grease tray (Yes/No) | APW1: SEO Keyword1 (liter/day) | APX1: Dehumidification capacity [l/24h] | APY1: Room size (m2) | APZ1: Water tank capacity (L) | AQA1: Air circulation (m3/H) | AQB1: Carbon filter (Y/N) | AQC1: Nylon filter (Y/N) | AQD1: HEPA Filter (Y/N) | AQE1: Drain hose (Y/N) | AQF1: Target humidity range (%) | AQG1: Temp range (°C) | AQH1: Water tank full indication (Y/N) | AQI1: Internal Drying (Y/N) | AQJ1: Anti-Frost function (Y/N) | AQK1: Gas Type7 | AQL1: Gas weight [g] | AQM1: Auto swing (Y/N) | AQN1: Oscillation mode (Y/N) | AQO1: Remote Control [Y/N] | AQP1: Water Tank Detachable (y/n) | AQQ1: Automatic Switch-Off (y/n) | AQR1: Wheels (y/n) | AQS1: Night Mode (y/n) | AQT1: Max Power Output (W) | AQU1: Effective Heating Area (m²) | AQV1: Heating Element Type | AQW1: Adjustable Power Settings (Yes/No) | AQX1: Number of Power Settings | AQY1: Power Settings Detail (eg. 800W/1200W/2000W) | AQZ1: Mounting Type | ARA1: Heating Direction Type (Fixed/Adjustable/360°) | ARB1: Mounting Bracket Included (Yes/No) | ARC1: Adjustable Mounting Angle (Yes/No) | ARD1: Adjustable Angle Range (°) | ARE1: Adjustable Height (if standing) (Yes/No) | ARF1: Oscillation Function (Yes/No) | ARG1: Time to Reach Full Heat (sec/min) | ARH1: IP Rating | ARI1: Remote Control Included (Yes/No) | ARJ1: Timer Function (Yes/No) | ARK1: Timer Precision (1-24h) | ARL1: Energy-Saving/Eco-Mode (Yes/No) | ARM1: Motion Sensor (Auto On/Off) (Yes/No) | ARN1: LED/LCD Display Present (Yes/No) | ARO1: Integrated Light (Yes/No) | ARP1: LED Lamp Power (W) | ARQ1: Lighting Type (LED / RGB / Ambient) | ARR1: Adjustable Brightness (Dimmable) (Yes/No) | ARS1: LED Lighting Effects (eg. fade, flash) | ART1: Overheat Protection (Yes/No)13 | ARU1: Tip-Over Protection (Yes/No) | ARV1: Child Lock (Yes/No)9 | ARW1: Base Stand Material (if standing) | ARX1: Carry Handle (Yes/No) | ARY1: Protective Grill (Yes/No) | ARZ1: Protective Cover Included (Yes/No) | ASA1: Protective Cover Dimensions (cm) | ASB1: Assembly Required (Yes/No, with estimated time) | ASC1: Usage (Indoor/Outdoor/Indoor & Outdoor) | ASD1: Voice Control (Alexa/Google) (Yes/No) | ASE1: SEO Keyword2 (size) | ASF1: SEO Keyword3 (Design) | ASG1: Heating Technology (Infrared / Convection / Hybrid) | ASH1: Infrared Heating Ratio (%) | ASI1: Heating Element Type (Carbon, Quartz, Ceramic...) | ASJ1: Temperature Range (°C)8 | ASK1: Maximum Product Surface Temperature (°C) | ASL1: Time to Reach Full Heat (sec or min) | ASM1: Air Blower (Yes/No) | ASN1: Can the remote control two units at the same time? (Yes/No) | ASO1: Integrated Thermostat (Yes/No) | ASP1: Type of Thermostat (Mechanical / Electric) | ASQ1: Control Type (Touch Display / Buttons / Knob) | ASR1: Display (Yes/No) | ASS1: Room Temperature Indicator (Yes/No) | AST1: On/Off Switch (Yes/No) | ASU1: Timer Range (0-24h) | ASV1: Open Window Detection (Yes/No) | ASW1: Tip-over Protection (Yes/No)22 | ASX1: Frost Detection (Yes/No) | ASY1: Heat Sensor (Yes/No) | ASZ1: Operation Indicator Light (Yes/No) | ATA1: Light Color Options (Yes/No) | ATB1: Color Temperature min. | ATC1: Color Temperature max. | ATD1: Finish (Matte / Shiny) | ATE1: Frame Material (if applicable) | ATF1: Feet/Base Material (if applicable) | ATG1: Mounting Material Included (Yes/No) | ATH1: Mounting Orientation (Horizontal/Vertical/Both) | ATI1: Usage (Indoor/Outdoor/Both) | ATJ1: Bathroom Usability | ATK1: SEO Keyword2 (fins) | ATL1: Number of Fins | ATM1: IP Protection Class | ATN1: Display Type | ATO1: Toggle Switch | ATP1: Weekly Timer (Yes/No) | ATQ1: Lighting (Yes/No) | ATR1: Overheating protection (Yes/No)10 | ATS1: Tip over protection (Yes/No) | ATT1: Frost detection (Yes/No)11 | ATU1: Floor Rollers (Yes/No) | ATV1: Feet Material | ATW1: Form Factor (Wall Mounted/Freestanding/Wall & Freestanding/Ceiling Mounted) | ATX1: Main Body Material (Glass/Steel/Aluminium/Stone/Plastic/Mixed) | ATY1: Dimensions without the feet (WxDxH cm) | ATZ1: SEO Keyword1 (BTU) | AUA1: Cooling Capacity (BTU) | AUB1: Cooling Capacity (kW) | AUC1: Energy Efficiency Ratio | AUD1: Standby Power Consumption (W) | AUE1: Operating Modes (Cooler / Dehumidifier / Fan / Heating ) | AUF1: Fan Ventilation Levels (low, medium, high, auto ) | AUG1: Air volume direction (1 Way/ 2 Way/ 3 Way) | AUH1: Timer (till 24h)(h) | AUI1: Precision of Timer (h) | AUJ1: Sleep-Night Mode (Yes/No) | AUK1: Min Temp Setting (Celcius) | AUL1: Max Temp Setting (Celcius) | AUM1: Min Noise Level (dB) | AUN1: Max Noise Level (dB) | AUO1: Windflow( m3/h) | AUP1: Dust Filter | AUQ1: Full Water Tank Indicator | AUR1: Dehumidifier (Yes/No) | AUS1: Dehumidify capacity (l/h) | AUT1: Power consumption(kWh/60 min) | AUU1: Refrigerant Type (Gas) | AUV1: Caster/Roller Lock | AUW1: Vertical Swing Mode (Auto/Manual/None) | AUX1: Temperature display | AUY1: Air Cleaner Function (Yes/No) | AUZ1: Suitable Room Size (m2) | AVA1: Window sealing set (No / Optional / included) | AVB1: Exhaust air hose for Air Cooling (Yes / No) | AVC1: Extendable exhaust air hose length(m) | AVD1: Extendable exhaust air hose diameter(cm) | AVE1: Activated Carbon Filter (Yes/No) | AVF1: Heating Capacity (kW) | AVG1: Heating rating | AVH1: Heat Pump (Yes / No) | AVI1: Heat pump power | AVJ1: No. of Cooling Levels | AVK1: Tank Capacity litres | AVL1: Programmable (Yes/ No) | AVM1: Format (horizontal/vertical) | AVN1: Humidifier Function (Yes/ No) | AVO1: Remote Control | AVP1: SEO Keyword1 (Dia) | AVQ1: Fan Diameter (cm) | AVR1: Blade Quantity | AVS1: Blade Material | AVT1: Motor Housing Material | AVU1: Recommended Room Size (m²) | AVV1: Motor Type (AC/DC) | AVW1: Motor Power (W) | AVX1: Fan Wind Speed levels | AVY1: Max Airflow Rate (m³/h) | AVZ1: Max Airflow Rate (m³/min) | AWA1: Efficiency (m³/min/W) | AWB1: Max RPM (r/min) | AWC1: Max Air Velocity (m/s) | AWD1: Integrated Lamp (Yes/No) | AWE1: Lamp Type (Socket Type) | AWF1: Light Bulb Included | AWG1: Light Total Power (W) | AWH1: Light Output (Lumens) | AWI1: Energy Efficency Class of Lamp | AWJ1: Different Light Colours (Yes/No) | AWK1: Light Color/Temperature Options (K°) | AWL1: Material lampshade | AWM1: Reversible Airflow Mode (Winter/Summer) (Yes/No) | AWN1: Remote control (Yes/No)12 | AWO1: Wall Control Compatible (Yes/No) | AWP1: Timer (h) | AWQ1: Ceiling Mount Diameter (cm) | AWR1: Adjustable Height (Different Rod sizes) (Yes/No) | AWS1: Downrods Included | AWT1: Max Height (from ceiling to base of lamp) (cm) | AWU1: Mounting Type (Flush/Downrod/Angled/Dual) | AWV1: Slope Ceiling Compatible (Yes/No) | AWW1: Indoor/Outdoor Versatility | AWX1: SEO Keyword1 (Water tank liters) | AWY1: Water tank capacity (liter) | AWZ1: Max Airflow Capacity (m3/h) | AXA1: Operating Mode (normal, night, nature, intelligent) | AXB1: No of cooling levels | AXC1: Cooling Packs | AXD1: Horizontal oscillation (Yes/No) | AXE1: Horizontal oscillation (Automatic/Manual) | AXF1: Vertical oscillation (Auto/Manual) | AXG1: Caster/Roller | AXH1: Water Tank (Removable or fixed or Half Drawer) | AXI1: Ionizer (Yes/No) | AXJ1: Hepa Filter (Yes/No) | AXK1: Remote Control? | AXL1: Water level protection via acoustic beep | AXM1: Drain Plug | AXN1: Handle | AXO1: Display Light On/Off function | AXP1: Night mode | AXQ1: Room Size [m2] | AXR1: Min Noise Emission [dB] | AXS1: Max Noise Emission [dB] | AXT1: SEO Keyword2(room size) | AXU1: Heating Type (Convection / Infrared / Hybrid) | AXV1: Time to Reach Full Heat (seconds) | AXW1: Turbo Blower for Faster Circulation (Yes/No) | AXX1: Number of Light Colours | AXY1: Built-in fan heater (Yes/No) | AXZ1: Manual Control Panel (Yes/No) | AYA1: Control Type (Switches, Knob, Push Buttons, Touch Display, etc) | AYB1: Display Type (LED/LCD/Touch Display/None) | AYC1: Open window detection (Yes/No)14 | AYD1: Ambient Lighting/Backlight (Yes/No) | AYE1: Flame Illusion (Yes/No) | AYF1: Type of Flame Effects (LED/3D/Water Vapor) | AYG1: Adjustable Flame Brightness (Yes/No) | AYH1: Adjustable Flame Color (Yes/No) | AYI1: Glowing Logs (Yes/No) | AYJ1: Electric Stones (Yes/No) | AYK1: Crackling Sound Effect (Yes/No) | AYL1: Wood Log Storage (Yes/No) | AYM1: Viewing Window Size | AYN1: SEO Keyword1 (Room Size) | AYO1: SEO Keyword2 (CADR) | AYP1: SEO Keyword4 | AYQ1: CADR - Clean Air Delivery Rate (m³/h) | AYR1: Power Consumption (W) | AYS1: Airflow Direction / 360° Air Intake (Yes/No) | AYT1: Filter Type | AYU1: Number of Filtration Stages | AYV1: Type of Filtration Stages | AYW1: Filter Lifespan (months or hours) | AYX1: Filter Replacement Indicator (Yes/No) | AYY1: Filter Replacement Method | AYZ1: Air Quality Sensor (Yes/No) | AZA1: Type of Air Quality Sensor | AZB1: PM2.5 Real-Time Display (Yes/No) | AZC1: Dust Level Indicator (Yes/No) | AZD1: Air Quality Indicator Type (LED color ring, numeric, app-based) | AZE1: Number of Fan Speeds | AZF1: Fan Speed Levels (Low/Medium/High/Silent) | AZG1: Modes (Auto, Turbo, Manual…) | AZH1: Sleep Mode (Yes/No) | AZI1: Automatic Mode (Yes/No) | AZJ1: Timer Range (1-24h) | AZK1: Humidification Function (Yes/No) | AZL1: Humidification Rate (L/h) | AZM1: Water Tank Capacity (L)15 | AZN1: Auto-Drying Function (Yes/No) | AZO1: Aromatherapy Function (Yes/No) | AZP1: UV-C Light (Yes/No) | AZQ1: Touch Control (Yes/No) | AZR1: Target Pollutants/Applications (Hair, Pet Dander, Smoke, Wildfire, Pollen) | AZS1: Voice Control Support (Alexa/Google Assistant) (Yes/No) | AZT1: No. of Automaitc Watches | AZU1: No.of Mechanic watches | AZV1: Pillow/Holder | AZW1: Material pillow/holder | AZX1: Power options (AC vs. Battery) | AZY1: Watch diameter dimensions (mm) | AZZ1: Watch strap dimensions (cm) | BAA1: Motor type (Japanese mabuchi, other) | BAB1: Magetically shielded motors (Yes/No) | BAC1: Connection to other watch winder (Stackable winders) - Yes/No | BAD1: No. of rotation modes | BAE1: Rotation direction modes (clockwise, anitclockwise, bidirectional, etc.) | BAF1: No. of Turns per day modes | BAG1: Type of Turns Per Day | BAH1: Inner lining material | BAI1: Stop position | BAJ1: Dimensions | BAK1: LED lighting inside | BAL1: Display (LED, LCD, TFT, N/A) | BAM1: Control (Knob, switches, Digital, touchscreen) | BAN1: Watch holder angle ° | BAO1: Control watches separately | BAP1: Lock type (Key lock, fingerprint lock, N/A) | BAQ1: Integrated jewellery drawer | BAR1: Removal dividers in drawer | BAS1: Remote control included (Yes/No)23
A2: 10035547 | B2: Beerbelly 21L D Bl | D2: Shop | E2: Beerbelly | F2: 0 | G2: TK49 | L2: Large Appliances-Refrigerators-Portable Refrigerators | M2: Large Appliances | N2: Refrigerators | O2: Portable Refrigerators | Q2: Beerbelly | S2: M (21-30) | T2: Single | U2: Manual | V2: No | Y2: Beerbelly 21L D Bl | Z2: 19 | AB2: Capacity | AC2: 21 | AD2: Color | AE2: Blue | AJ2: 21 | AK2: Single | AL2: N | AM2: Thermo | AN2: n/a | AO2: n/a | AP2: SN, N | AQ2: Manual | AR2: Y | AS2: Y | AT2: 3 | AU2: 55 | AV2: 3℃～-55℃ | AW2: n/a | AX2: AC cable, DC cable, USB | AY2: 120 | AZ2: 120 | BA2: n/a | BB2: Y | BC2: N | BD2: N | BE2: n/a | BF2: n/a | BG2: PE | BH2: PU | BI2: Removable | BJ2: Top | BK2: PP | BL2: Y | BM2: N | BN2: PPHG | BO2: N | BP2: N | BQ2: N | BR2: Y | BS2: n/a | BT2: Manual | BU2: N | BV2: Y | BW2: N | BX2: N | BY2: n/a | BZ2: Y | CA2: n/a | CB2: Y | CC2: Y | CD2: N | CE2: N | CF2: 27x330ml | CG2: Blue | CI2: Bl | CJ2: No | CL2: Working control lights shows which function is chosen | CM2: power bank can as the power supply for the machine | CR2: D | CS2: 61 | CT2: 220-240 V ~ 50/60 Hz | CU2: Type C <2.5A - 2 pin (Europlug) | CV2: 1.2 | CW2: Class II | CX2: 60 | CY2: 26 | DB2: 34.8 | DC2: 45.7 | DD2: 28.8 | DE2: 4.6 | DF2: 25.7 | DG2: 38.4 | DH2: 19.6 | DI2: -- | DJ2: -- | DK2: -- | DL2: 34.8 * 45.7 * 28.8 | DU2: ISTA 1A | DV2: 1 | DW2: Item + Users Manual | EY2: TRUE | EZ2: TRUE | FA2: Portable Refrigerators - Attributes V3.0.xlsx | FB2: https://chaltecadmin.sharepoint.com/sites/ProductManagement/Shared Documents/02_Strategy/01_Portfolio Strategy/05_Product Passport/01_Large Appliances/
A3: 10035548 | B3: Beerbelly 21L D Grn | D3: Shop | E3: Beerbelly | F3: 0 | G3: TK49 | L3: Large Appliances-Refrigerators-Portable Refrigerators | M3: Large Appliances | N3: Refrigerators | O3: Portable Refrigerators | Q3: Beerbelly | S3: M (21-30) | T3: Single | U3: Manual | V3: No | Y3: Beerbelly 21L D Grn | Z3: 20 | AB3: Capacity | AC3: 21 | AD3: Color | AE3: Green | AJ3: 21 | AK3: Single | AL3: N | AM3: Thermo | AN3: n/a | AO3: n/a | AP3: SN, N | AQ3: Manual | AR3: Y | AS3: Y | AT3: 3 | AU3: 55 | AV3: 3℃～-55℃ | AW3: n/a | AX3: AC cable, DC cable, USB | AY3: 120 | AZ3: 120 | BA3: n/a | BB3: Y | BC3: N | BD3: N | BE3: n/a | BF3: n/a | BG3: PE | BH3: PU | BI3: Removable | BJ3: Top | BK3: PP | BL3: Y | BM3: N | BN3: PPHG | BO3: N | BP3: N | BQ3: N | BR3: Y | BS3: n/a | BT3: Manual | BU3: N | BV3: Y | BW3: N | BX3: N | BY3: n/a | BZ3: Y | CA3: n/a | CB3: Y | CC3: Y | CD3: N | CE3: N | CF3: 27x330ml | CG3: Green | CI3: Grn | CJ3: No | CL3: Working control lights shows which function is chosen | CM3: power bank can as the power supply for the machine | CR3: D | CS3: 61 | CT3: 220-240 V ~ 50/60 Hz | CU3: Type C <2.5A - 2 pin (Europlug) | CV3: 1.2 | CW3: Class II | CX3: 60 | CY3: 26 | DB3: 34.8 | DC3: 45.7 | DD3: 28.8 | DE3: 4.6 | DF3: 25.7 | DG3: 38.4 | DH3: 19.6 | DI3: -- | DJ3: -- | DK3: -- | DL3: 34.8 * 45.7 * 28.8 | DU3: ISTA 1A | DV3: 1 | DW3: Item + Users Manual | EY3: TRUE | EZ3: TRUE | FA3: Portable Refrigerators - Attributes V3.0.xlsx | FB3: https://chaltecadmin.sharepoint.com/sites/ProductManagement/Shared Documents/02_Strategy/01_Portfolio Strategy/05_Product Passport/01_Large Appliances/
A4: 10035550 | B4: Beerbelly 29L F Bl | D4: Shop | E4: Beerbelly | F4: 0 | G4: TK49 | L4: Large Appliances-Refrigerators-Portable Refrigerators | M4: Large Appliances | N4: Refrigerators | O4: Portable Refrigerators | Q4: Beerbelly | S4: M (21-30) | T4: Single | U4: Manual | V4: No | Y4: Beerbelly 29L F Bl | Z4: 19 | AB4: Capacity | AC4: 29 | AD4: Color | AE4: Blue | AJ4: 29 | AK4: Single | AL4: N | AM4: Thermo | AN4: n/a | AO4: n/a | AP4: SN, N | AQ4: Manual | AR4: Y | AS4: Y | AT4: 3 | AU4: 55 | AV4: 3℃～-55℃ | AW4: n/a | AX4: AC cable, DC cable, USB | AY4: 120 | AZ4: 120 | BA4: n/a | BB4: Y | BC4: N | BD4: N | BE4: n/a | BF4: n/a | BG4: PE | BH4: PU | BI4: Removable | BJ4: Top | BK4: PP | BL4: Y | BM4: N | BN4: PPHG | BO4: N | BP4: N | BQ4: N | BR4: Y | BS4: n/a | BT4: Manual | BU4: N | BV4: Y | BW4: N | BX4: N | BY4: n/a | BZ4: Y | CA4: n/a | CB4: Y | CC4: Y | CD4: N | CE4: N | CF4: 36x330 ml | CG4: Blue | CI4: Bl | CJ4: No | CL4: Working control lights shows which function is chosen | CM4: power bank can as the power supply for the machine | CR4: F | CS4: 95 | CT4: 220-240 V ~ 50/60 Hz | CU4: Type C <2.5A - 2 pin (Europlug) | CV4: 1.2 | CW4: Class II | CX4: 60 | CY4: 26 | DB4: 44.4 | DC4: 45.7 | DD4: 28.8 | DE4: 5.1 | DF4: 35.3 | DG4: 37.9 | DH4: 19.1 | DI4: -- | DJ4: -- | DK4: -- | DL4: 44.4 * 45.7 * 28.8 | DU4: ISTA 1A | DV4: 1 | DW4: Item + Users Manual | EY4: TRUE | EZ4: TRUE | FA4: Portable Refrigerators - Attributes V3.0.xlsx | FB4: https://chaltecadmin.sharepoint.com/sites/ProductManagement/Shared Documents/02_Strategy/01_Portfolio Strategy/05_Product Passport/01_Large Appliances/
A5: 10046212 | B5: PolarForce 28L E Blk | D5: Shop | E5: PolarForce | F5: 0 | G5: ICE4 | L5: Large Appliances-Refrigerators-Portable Refrigerators | M5: Large Appliances | N5: Refrigerators | O5: Portable Refrigerators | Q5: PolarForce | S5: M (21-30) | T5: Dual | U5: Manual | V5: Yes | Y5: PolarForce 28L E Blk | Z5: 21 | AB5: Capacity | AC5: 28 | AD5: Color | AE5: Black | AJ5: 28 | AK5: Dual | AL5: N | AM5: Compressor | AN5: R600a | AO5: 27 | AP5: SN, N, ST | AQ5: Drain | AR5: N | AS5: Y | AT5: -20 | AU5: n/a | AV5: 20℃～-20℃ | AW5: n/a | AX5: AC adapter + DC Cigarette power cord | AY5: 210 | AZ5: 240 | BA5: n/a | BB5: N | BC5: N | BD5: N | BE5: n/a | BF5: n/a | BG5: Plastic | BH5: n/a | BI5: Removable | BJ5: Top | BK5: Plastic | BL5: Y | BM5: Y | BN5: Plastic | BO5: Y | BP5: N | BQ5: N | BR5: N | BS5: LED | BT5: Manual | BU5: N | BV5: N | BW5: N | BX5: N | BY5: n/a | BZ5: Y | CA5: n/a | CB5: Y | CC5: Y | CD5: Y | CE5: Y | CF5: n/a | CG5: Black | CI5: Blk | CJ5: No | CR5: E | CS5: 142 | CT5: 220-240 V ~ 50/60 Hz | CU5: Type C 16A - 2 pin (Europlug) | CV5: 2.1 | CW5: Class II | CX5: 60 | CY5: 43 | DB5: 41.5 | DC5: 61 | DD5: 39 | DE5: 13.4 | DF5: 31.2 | DG5: 26.9 | DH5: 25 | DI5: 15 | DJ5: 17.8 | DK5: 25 | DL5: 41.5 * 61 * 39 | DU5: Other | DV5: 1 | DW5: Item + Users Manual | EY5: TRUE | EZ5: TRUE | FA5: Portable Refrigerators - Attributes V3.0.xlsx | FB5: https://chaltecadmin.sharepoint.com/sites/ProductManagement/Shared Documents/02_Strategy/01_Portfolio Strategy/05_Product Passport/01_Large Appliances/
A6: 10046213 | B6: PolarForce 37L E Blk | D6: Shop | E6: PolarForce | F6: 0 | G6: ICE4 | L6: Large Appliances-Refrigerators-Portable Refrigerators | M6: Large Appliances | N6: Refrigerators | O6: Portable Refrigerators | Q6: PolarForce | S6: L (31-40) | T6: Dual | U6: Manual | V6: Yes | Y6: PolarForce 37L E Blk | Z6: 21 | AB6: Capacity | AC6: 37 | AD6: Color | AE6: Black | AJ6: 37 | AK6: Dual | AL6: N | AM6: Compressor | AN6: R600a | AO6: 34 | AP6: SN, N, ST | AQ6: Drain | AR6: N | AS6: Y | AT6: -20 | AU6: n/a | AV6: 20℃～-20℃ | AW6: n/a | AX6: AC adapter + DC Cigarette power cord | AY6: 210 | AZ6: 240 | BA6: n/a | BB6: N | BC6: N | BD6: N | BE6: n/a | BF6: n/a | BG6: Plastic | BH6: n/a | BI6: Removable | BJ6: Top | BK6: Plastic | BL6: Y | BM6: Y | BN6: Plastic | BO6: Y | BP6: N | BQ6: N | BR6: N | BS6: LED | BT6: Manual | BU6: N | BV6: N | BW6: N | BX6: N | BY6: n/a | BZ6: Y | CA6: n/a | CB6: Y | CC6: Y | CD6: Y | CE6: Y | CF6: n/a | CG6: Black | CI6: Blk | CJ6: No | CR6: E | CS6: 144 | CT6: 220-240 V ~ 50/60 Hz | CU6: Type C 16A - 2 pin (Europlug) | CV6: 2.1 | CW6: Class II | CX6: 66 | CY6: 43 | DB6: 49.5 | DC6: 61 | DD6: 39 | DE6: 14.5 | DF6: 39.2 | DG6: 26.7 | DH6: 24.7 | DI6: 23 | DJ6: 17.8 | DK6: 24.7 | DL6: 49.5 * 61 * 39 | DU6: Other | DV6: 1 | DW6: Item + Users Manual | EY6: TRUE | EZ6: TRUE | FA6: Portable Refrigerators - Attributes V3.0.xlsx | FB6: https://chaltecadmin.sharepoint.com/sites/ProductManagement/Shared Documents/02_Strategy/01_Portfolio Strategy/05_Product Passport/01_Large Appliances/
A7: 10046214 | B7: PolarForce 50L E Blk | D7: Shop | E7: PolarForce | F7: 0 | G7: ICE4 | L7: Large Appliances-Refrigerators-Portable Refrigerators | M7: Large Appliances | N7: Refrigerators | O7: Portable Refrigerators | Q7: PolarForce | S7: XL (41-50) | T7: Dual | U7: Manual | V7: Yes | Y7: PolarForce 50L E Blk | Z7: 21 | AB7: Capacity | AC7: 50 | AD7: Color | AE7: Black | AJ7: 50 | AK7: Dual | AL7: N | AM7: Compressor | AN7: R600a | AO7: 39 | AP7: SN, N, ST | AQ7: Drain | AR7: N | AS7: Y | AT7: -20 | AU7: n/a | AV7: 20℃～-20℃ | AW7: n/a | AX7: AC adapter + DC Cigarette power cord | AY7: 210 | AZ7: 240 | BA7: n/a | BB7: N | BC7: N | BD7: N | BE7: n/a | BF7: n/a | BG7: Plastic | BH7: n/a | BI7: Removable | BJ7: Top | BK7: Plastic | BL7: Y | BM7: Y | BN7: Plastic | BO7: Y | BP7: N | BQ7: N | BR7: N | BS7: LED | BT7: Manual | BU7: N | BV7: N | BW7: N | BX7: N | BY7: n/a | BZ7: Y | CA7: n/a | CB7: Y | CC7: Y | CD7: Y | CE7: Y | CF7: n/a | CG7: Black | CI7: Blk | CJ7: No | CR7: E | CS7: 150 | CT7: 220-240 V ~ 50/60 Hz | CU7: Type C 16A - 2 pin (Europlug) | CV7: 2.1 | CW7: Class II | CX7: 72 | CY7: 43 | DB7: 53.1 | DC7: 65.4 | DD7: 44.1 | DE7: 16.3 | DF7: 42 | DG7: 26.9 | DH7: 28.9 | DI7: 24 | DJ7: 23 | DK7: 28.9 | DL7: 53.1 * 65.4 * 44.1 | DU7: Other | DV7: 1 | DW7: Item + Users Manual | EY7: TRUE | EZ7: TRUE | FA7: Portable Refrigerators - Attributes V3.0.xlsx | FB7: https://chaltecadmin.sharepoint.com/sites/ProductManagement/Shared Documents/02_Strategy/01_Portfolio Strategy/05_Product Passport/01_Large Appliances/
A8: 10046215 | B8: PolarForce 28L E DMs | D8: Shop | E8: PolarForce | F8: 0 | G8: ICE4 | L8: Large Appliances-Refrigerators-Portable Refrigerators | M8: Large Appliances | N8: Refrigerators | O8: Portable Refrigerators | Q8: PolarForce | S8: M (21-30) | T8: Dual | U8: Manual | V8: Yes | Y8: PolarForce 28L E DMs | Z8: 21 | AB8: Capacity | AC8: 28 | AD8: Color | AE8: Dark Moss | AJ8: 28 | AK8: Dual | AL8: N | AM8: Compressor | AN8: R600a | AO8: 27 | AP8: SN, N, ST | AQ8: Drain | AR8: N | AS8: Y | AT8: -20 | AU8: n/a | AV8: 20℃～-20℃ | AW8: n/a | AX8: AC adapter + DC Cigarette power cord | AY8: 210 | AZ8: 240 | BA8: n/a | BB8: N | BC8: N | BD8: N | BE8: n/a | BF8: n/a | BG8: Plastic | BH8: n/a | BI8: Removable | BJ8: Top | BK8: Plastic | BL8: Y | BM8: Y | BN8: Plastic | BO8: Y | BP8: N | BQ8: N | BR8: N | BS8: LED | BT8: Manual | BU8: N | BV8: N | BW8: N | BX8: N | BY8: n/a | BZ8: Y | CA8: n/a | CB8: Y | CC8: Y | CD8: Y | CE8: Y | CF8: n/a | CG8: Dark Moss | CI8: DMs | CJ8: No | CR8: E | CS8: 142 | CT8: 220-240 V ~ 50/60 Hz | CU8: Type C 16A - 2 pin (Europlug) | CV8: 2.1 | CW8: Class II | CX8: 60 | CY8: 43 | DB8: 41.5 | DC8: 61 | DD8: 39 | DE8: 13.4 | DF8: 31.2 | DG8: 26.9 | DH8: 25 | DI8: 15 | DJ8: 17.8 | DK8: 25 | DL8: 41.5 * 61 * 39 | DU8: Other | DV8: 1 | DW8: Item + Users Manual | EY8: TRUE | EZ8: TRUE | FA8: Portable Refrigerators - Attributes V3.0.xlsx | FB8: https://chaltecadmin.sharepoint.com/sites/ProductManagement/Shared Documents/02_Strategy/01_Portfolio Strategy/05_Product Passport/01_Large Appliances/
A9: 10046216 | B9: PolarForce 37L E DMs | D9: Shop | E9: PolarForce | F9: 0 | G9: ICE4 | L9: Large Appliances-Refrigerators-Portable Refrigerators | M9: Large Appliances | N9: Refrigerators | O9: Portable Refrigerators | Q9: PolarForce | S9: L (31-40) | T9: Dual | U9: Manual | V9: Yes | Y9: PolarForce 37L E DMs | Z9: 21 | AB9: Capacity | AC9: 37 | AD9: Color | AE9: Dark Moss | AJ9: 37 | AK9: Dual | AL9: N | AM9: Compressor | AN9: R600a | AO9: 34 | AP9: SN, N, ST | AQ9: Drain | AR9: N | AS9: Y | AT9: -20 | AU9: n/a | AV9: 20℃～-20℃ | AW9: n/a | AX9: AC adapter + DC Cigarette power cord | AY9: 210 | AZ9: 240 | BA9: n/a | BB9: N | BC9: N | BD9: N | BE9: n/a | BF9: n/a | BG9: Plastic | BH9: n/a | BI9: Removable | BJ9: Top | BK9: Plastic | BL9: Y | BM9: Y | BN9: Plastic | BO9: Y | BP9: N | BQ9: N | BR9: N | BS9: LED | BT9: Manual | BU9: N | BV9: N | BW9: N | BX9: N | BY9: n/a | BZ9: Y | CA9: n/a | CB9: Y | CC9: Y | CD9: Y | CE9: Y | CF9: n/a | CG9: Dark Moss | CI9: DMs | CJ9: No | CR9: E | CS9: 144 | CT9: 220-240 V ~ 50/60 Hz | CU9: Type C 16A - 2 pin (Europlug) | CV9: 2.1 | CW9: Class II | CX9: 66 | CY9: 43 | DB9: 49.5 | DC9: 61 | DD9: 39 | DE9: 14.5 | DF9: 39.2 | DG9: 26.7 | DH9: 24.7 | DI9: 23 | DJ9: 17.8 | DK9: 24.7 | DL9: 49.5 * 61 * 39 | DU9: Other | DV9: 1 | DW9: Item + Users Manual | EY9: TRUE | EZ9: TRUE | FA9: Portable Refrigerators - Attributes V3.0.xlsx | FB9: https://chaltecadmin.sharepoint.com/sites/ProductManagement/Shared Documents/02_Strategy/01_Portfolio Strategy/05_Product Passport/01_Large Appliances/
A10: 10046217 | B10: PolarForce 50L E DMs | D10: Shop | E10: PolarForce | F10: 0 | G10: ICE4 | L10: Large Appliances-Refrigerators-Portable Refrigerators | M10: Large Appliances | N10: Refrigerators | O10: Portable Refrigerators | Q10: PolarForce | S10: XL (41-50) | T10: Dual | U10: Manual | V10: Yes | Y10: PolarForce 50L E DMs | Z10: 21 | AB10: Capacity | AC10: 50 | AD10: Color | AE10: Dark Moss | AJ10: 50 | AK10: Dual | AL10: N | AM10: Compressor | AN10: R600a | AO10: 39 | AP10: SN, N, ST | AQ10: Drain | AR10: N | AS10: Y | AT10: -20 | AU10: n/a | AV10: 20℃～-20℃ | AW10: n/a | AX10: AC adapter + DC Cigarette power cord | AY10: 210 | AZ10: 240 | BA10: n/a | BB10: N | BC10: N | BD10: N | BE10: n/a | BF10: n/a | BG10: Plastic | BH10: n/a | BI10: Removable | BJ10: Top | BK10: Plastic | BL10: Y | BM10: Y | BN10: Plastic | BO10: Y | BP10: N | BQ10: N | BR10: N | BS10: LED | BT10: Manual | BU10: N | BV10: N | BW10: N | BX10: N | BY10: n/a | BZ10: Y | CA10: n/a | CB10: Y | CC10: Y | CD10: Y | CE10: Y | CF10: n/a | CG10: Dark Moss | CI10: DMs | CJ10: No | CR10: E | CS10: 150 | CT10: 220-240 V ~ 50/60 Hz | CU10: Type C 16A - 2 pin (Europlug) | CV10: 2.1 | CW10: Class II | CX10: 72 | CY10: 43 | DB10: 53.1 | DC10: 65.4 | DD10: 44.1 | DE10: 16.3 | DF10: 42 | DG10: 26.9 | DH10: 28.9 | DI10: 24 | DJ10: 23 | DK10: 28.9 | DL10: 53.1 * 65.4 * 44.1 | DU10: Other | DV10: 1 | DW10: Item + Users Manual | EY10: TRUE | EZ10: TRUE | FA10: Portable Refrigerators - Attributes V3.0.xlsx | FB10: https://chaltecadmin.sharepoint.com/sites/ProductManagement/Shared Documents/02_Strategy/01_Portfolio Strategy/05_Product Passport/01_Large Appliances/
A11: 10046244 | B11: SwiftFrost 12L A Bl | D11: Shop | E11: SwiftFrost | F11: 0 | G11: HEA25 | L11: Large Appliances-Refrigerators-Portable Refrigerators | M11: Large Appliances | N11: Refrigerators | O11: Portable Refrigerators | Q11: SwiftFrost | S11: S (up to 20) | T11: Single | U11: Digital | V11: No | Y11: SwiftFrost 12L A Bl | Z11: 20 | AB11: Color | AC11: Blue | AJ11: 12 | AK11: Single | AL11: N | AM11: Compressor | AN11: R600a | AO11: 11 | AP11: SN, N, ST, T | AQ11: Manual | AR11: N | AS11: Y | AT11: -20 | AU11: 20 | AV11: 20℃～-20℃ | AW11: The time from 32℃ to 0±3℃ is ≤30min | AX11: AC cable, DC cable | AY11: 350 | AZ11: 200 | BA11: n/a | BB11: Y | BC11: N | BD11: N | BE11: n/a | BF11: n/a | BG11: HDPE+ABS+HIPS | BH11: Polyurethane foam | BI11: Hinged | BJ11: Top | BK11: HDPE | BL11: Y | BM11: N | BN11: PP+ABS | BO11: N | BP11: N | BQ11: N | BR11: N | BS11: LED | BT11: Digital | BU11: N | BV11: N | BW11: N | BX11: Y | BY11: n/a | BZ11: Y | CA11: n/a | CB11: Y | CC11: Y | CD11: N | CE11: Y | CF11: 16x330ml | CG11: Blue | CI11: Bl | CJ11: No | CL11: with bottle opener | CM11: with seat belt buckle | CR11: A | CS11: 30 | CT11: 220-240 V ~ 50/60 Hz | CU11: Plug on External Adapter | CV11: 2 | CW11: Class II | CX11: 55 | CY11: 45 | DB11: 47.8 | DC11: 38.3 | DD11: 31.1 | DE11: 8.2 | DF11: 23.2 | DG11: 25.4 | DH11: 19 | DI11: -- | DJ11: -- | DK11: -- | DL11: 47.8 * 38.3 * 31.1 | DU11: ISTA 1A | DV11: 1 | DW11: Item + Users Manual | EY11: TRUE | EZ11: TRUE | FA11: Portable Refrigerators - Attributes V3.0.xlsx | FB11: https://chaltecadmin.sharepoint.com/sites/ProductManagement/Shared Documents/02_Strategy/01_Portfolio Strategy/05_Product Passport/01_Large Appliances/
A12: 10046245 | B12: SwiftFrost 12L A Wht | D12: Shop | E12: SwiftFrost | F12: 0 | G12: HEA25 | L12: Large Appliances-Refrigerators-Portable Refrigerators | M12: Large Appliances | N12: Refrigerators | O12: Portable Refrigerators | Q12: SwiftFrost | S12: S (up to 20) | T12: Single | U12: Digital | V12: No | Y12: SwiftFrost 12L A Wht | Z12: 21 | AB12: Color | AC12: White | AJ12: 12 | AK12: Single | AL12: N | AM12: Compressor | AN12: R600a | AO12: 11 | AP12: SN, N, ST, T | AQ12: Manual | AR12: N | AS12: Y | AT12: -20 | AU12: 20 | AV12: 20℃～-20℃ | AW12: The time from 32℃ to 0±3℃ is ≤30min | AX12: AC cable, DC cable | AY12: 350 | AZ12: 200 | BA12: n/a | BB12: Y | BC12: N | BD12: N | BE12: n/a | BF12: n/a | BG12: HDPE+ABS+HIPS | BH12: Polyurethane foam | BI12: Hinged | BJ12: Top | BK12: HDPE | BL12: Y | BM12: N | BN12: PP+ABS | BO12: N | BP12: N | BQ12: N | BR12: N | BS12: LED | BT12: Digital | BU12: N | BV12: N | BW12: N | BX12: Y | BY12: n/a | BZ12: Y | CA12: n/a | CB12: Y | CC12: Y | CD12: N | CE12: Y | CF12: 16x330ml | CG12: White | CI12: Wht | CJ12: No | CL12: with bottle opener | CM12: with seat belt buckle | CR12: A | CS12: 30 | CT12: 220-240 V ~ 50/60 Hz | CU12: Plug on External Adapter | CV12: 2 | CW12: Class II | CX12: 55 | CY12: 45 | DB12: 47.8 | DC12: 38.3 | DD12: 31.1 | DE12: 8.2 | DF12: 23.2 | DG12: 25.4 | DH12: 19 | DI12: -- | DJ12: -- | DK12: -- | DL12: 47.8 * 38.3 * 31.1 | DU12: ISTA 1A | DV12: 1 | DW12: Item + Users Manual | EY12: TRUE | EZ12: TRUE | FA12: Portable Refrigerators - Attributes V3.0.xlsx | FB12: https://chaltecadmin.sharepoint.com/sites/ProductManagement/Shared Documents/02_Strategy/01_Portfolio Strategy/05_Product Passport/01_Large Appliances/
A13: 10048652 | B13: Arctiq 27L Uno C Bl | D13: Shop | E13: 0 | F13: 0 | G13: HEA | L13: Large Appliances-Refrigerators-Portable Refrigerators | M13: Large Appliances | N13: Refrigerators | O13: Portable Refrigerators | Q13: Arctiq | S13: M (21-30) | T13: Single | U13: Digital | V13: No | Y13: Arctiq 27L C Blk | Z13: 17 | AB13: Size | AC13: M (21-30) | AI13: CB30S | AJ13: 27 | AK13: Single | AL13: N | AM13: Compressor | AN13: R600a | AO13: 15 | AP13: N | AQ13: Drain | AR13: N | AS13: Y | AT13: -20 | AU13: 20 | AV13: 20℃～-20℃ | AW13: 0.4℃/min | AX13: Power/Cigarette | AY13: 1600 | AZ13: 2500 | BA13: n/a | BB13: N | BC13: N | BD13: N | BE13: n/a | BF13: n/a | BG13: PCM | BH13: cyclopentane | BI13: Hinged | BJ13: Top | BK13: PCM | BL13: Y | BM13: N | BN13: ABS | BO13: N | BP13: N | BQ13: N | BR13: N | BS13: LED | BT13: Digital | BU13: N | BV13: N | BW13: N | BX13: N | BY13: IPX0 | BZ13: Y | CA13: N | CB13: Y | CC13: Y | CD13: Y | CE13: N | CF13: 37 | CG13: Black | CI13: Blk | CJ13: No | CR13: C | CS13: 49 | CT13: 220-240 V ~ 50/60 Hz | CU13: Type E/F - 2 pin (German) - Schuko | CV13: 1.6 | CW13: Class II | CY13: 41 | DB13: 39 | DC13: 60 | DD13: 33.7 | DE13: 13 | DF13: 42.9 | DG13: 25.8 | DH13: 31.3 | DL13: 39 * 60 * 33.7 | DU13: ISTA 1A | DV13: 1 | DW13: Item + Users Manual | EL13: Capacity (Liters) | EM13: Temperature Range / Control Type | EN13: Zone (Single) | EO13: Eco Mode | EP13: Energy Class | ES13: Capacity + versatility of storage (Liters, number of zones) | ET13: Cooling performance (temperature range, thermostat type, consistency) | EU13: Convenience & usage areas (Ideal for Camping and Road Trips) | EV13: Different power supply options: power cable and cigarette cable | EW13: Design & build (LED display, metal body, sleek design) | EY13: TRUE | EZ13: TRUE | FA13: Portable Refrigerators - Attributes V3.0.xlsx | FB13: https://chaltecadmin.sharepoint.com/sites/ProductManagement/Shared Documents/02_Strategy/01_Portfolio Strategy/05_Product Passport/01_Large Appliances/
A14: 10048650 | B14: Arctiq 43L Duo D Blk | D14: Shop | E14: 0 | F14: 0 | G14: HEA | L14: Large Appliances-Refrigerators-Portable Refrigerators | M14: Large Appliances | N14: Refrigerators | O14: Portable Refrigerators | Q14: Arctiq | S14: XL (41-50) | T14: Dual | U14: Digital | V14: No | Y14: Arctiq 43L D Blk | Z14: 17 | AB14: Size | AC14: XL (41-50) | AI14: CR45 | AJ14: 43 | AK14: Dual | AL14: Y | AM14: Compressor | AN14: R600a | AO14: 15 | AP14: N | AQ14: Drain | AR14: N | AS14: Y | AT14: -18 | AU14: 20 | AV14: 20℃～-18℃ | AW14: 0.4℃/min | AX14: Power/Cigarette | AY14: 1600 | AZ14: 2500 | BA14: n/a | BB14: N | BC14: N | BD14: N | BE14: n/a | BF14: n/a | BG14: PCM | BH14: cyclopentane | BI14: Hinged | BJ14: Top | BK14: ABS | BL14: Y | BM14: N | BN14: ABS | BO14: N | BP14: N | BQ14: N | BR14: N | BS14: LED | BT14: Digital | BU14: Y | BV14: N | BW14: N | BX14: N | BY14: IPX0 | BZ14: Y | CA14: N | CB14: Y | CC14: Y | CD14: Y | CE14: N | CF14: 58 | CG14: Black | CI14: Blk | CJ14: No | CR14: D | CS14: 60 | CT14: 220-240 V ~ 50/60 Hz | CU14: Type E/F - 2 pin (German) - Schuko | CV14: 1.6 | CW14: Class II | CY14: 41 | DB14: 46.5 | DC14: 78 | DD14: 40 | DE14: 20 | DF14: 34.9 | DG14: 29.4 | DH14: 37 | DL14: 46.5 * 78 * 40 | DU14: ISTA 1A | DV14: 1 | DW14: Item + Users Manual | EL14: Capacity (Liters) | EM14: Temperature Range / Control Type | EN14: Zone (Dual) | EO14: Eco Mode | EP14: Energy Class | ES14: Capacity + versatility of storage (Liters, number of zones) | ET14: Cooling performance (temperature range, thermostat type, consistency) | EU14: Convenience & usage areas (Ideal for Camping and Road Trips) | EV14: Energy efficiency & eco-friendliness (energy class, refrigerant type) | EW14: Design & build (LED display, metal body, sleek design) | EY14: TRUE | EZ14: TRUE | FA14: Portable Refrigerators - Attributes V3.0.xlsx | FB14: https://chaltecadmin.sharepoint.com/sites/ProductManagement/Shared Documents/02_Strategy/01_Portfolio Strategy/05_Product Passport/01_Large Appliances/
A15: 10049074 | B15: TrinityCook 4 Zone Ind Blk/Slv | D15: Shop | E15: 0 | F15: 0 | G15: CP4 | Q15: TrinityCook | R15: MDA26007 | Z15: 0 | CG15: Black | CH15: Silver | CI15: Blk / Slv | CJ15: No | CS15: 188.5 | CT15: 220-240V，50-60Hz | CU15: Schuko plug | CV15: 1.5 | CW15: Class I | CX15: 0.34 | CY15: 55 | CZ15: 50-60 | DB15: 8.2 | DC15: 59 | DD15: 52 | DE15: 10.3 | DL15: 8.2 * 59 * 52 | DN15: 0 | DU15: ISTA 3A | DV15: 1 | EY15: TRUE | EZ15: TRUE | FA15: Tabletop Hobs - Attributes V3.0.xlsx | FB15: https://chaltecadmin.sharepoint.com/sites/ProductManagement/Shared Documents/02_Strategy/01_Portfolio Strategy/05_Product Passport/01_Large Appliances/ | FC15: Replacement | FD15: 10035361 | FI15: IF3508SF-2B1B2B1B | FK15: 60 | FL15: 3800 | FM15: 3500 | FN15: 4 | FO15: N | FP15: Y | FQ15: Y | FR15: zone 1,2,3,4 | FS15: 2000 | FT15: 2600 | FU15: 18 | FV15: 1500 | FW15: 1800 | FX15: 16 | FY15: 2000 | FZ15: 2600 | GA15: 18 | GB15: 1500 | GC15: 1800 | GD15: 16 | GE15: N/A | GF15: N/A | GG15: N/A | GH15: N/A | GI15: N/A | GJ15: N/A | GK15: N/A | GL15: N/A | GM15: N/A | GN15: N/A | GO15: N/A | GP15: N/A | GQ15: N/A | GR15: N/A | GS15: Aluminum alloy | GT15: Y | GU15: Y | GV15: Y | GW15: N | GX15: Y | GY15: Chinese glass | GZ15: 1 | HA15: RED | HB15: TOUCH | HC15: N/A | HD15: N/A | HE15: Yes
A16: 10049072 | B16: Mistercook Single Zone VTC Blk/Slv | D16: Shop | E16: 0 | F16: 0 | G16: CP6 | Z16: 0 | CI16: 0 | DL16: * * | EY16: TRUE | EZ16: TRUE | FA16: Tabletop Hobs - Attributes V3.0.xlsx | FB16: https://chaltecadmin.sharepoint.com/sites/ProductManagement/Shared Documents/02_Strategy/01_Portfolio Strategy/05_Product Passport/01_Large Appliances/
A17: 10049073 | B17: Mistercook Double Zone VTC Blk/Slv | D17: Shop | E17: 0 | F17: 0 | G17: CP6 | Z17: 0 | CG17: Black | CH17: Silver | CI17: Blk / Slv | CS17: 188 | CT17: 220-240V, 50/60Hz | CU17: VDE | CV17: 1.5 | CX17: 3100 | DB17: 5.6 | DC17: 56.4 | DD17: 35.1 | DE17: 4.2 | DL17: 56.4 x 35.1 x 5.6 | DN17: 0 | DU17: ISTA 3A | DV17: 1 | DW17: product, pearlfoam(left+right),polybag, pearlfoam sheetx2pcs | EY17: TRUE | EZ17: TRUE | FA17: Tabletop Hobs - Attributes V3.0.xlsx | FB17: https://chaltecadmin.sharepoint.com/sites/ProductManagement/Shared Documents/02_Strategy/01_Portfolio Strategy/05_Product Passport/01_Large Appliances/ | FI17: JDL-HS31B4-ZB | FJ17: infrared heating | FM17: 3100 | FN17: 2 | FO17: No | FQ17: 2 hours | FR17: 18 | FS17: 1800 | FU17: 18 | FV17: 1300 | GS17: Plastic | GT17: Yes | GU17: Yes | GV17: No | GW17: Yes | GX17: Yes | GY17: Glass | GZ17: 2 | HA17: Red | HB17: Touch | HE17: No
A18: 10031902 | D18: Shop | L18: Large Appliances-Range Hoods-Angled Hoods | M18: Large Appliances | N18: Range Hoods | O18: Angled Hoods | Q18: Balzac | S18: 60 | T18: Non-IoT | U18: 500 - 700 m³/h | V18: B | Y18: Balzac 60cm B Class Slv | Z18: 23 | AB18: Energy Efficiency Class | AC18: B | CG18: Silver | CI18: Slv | CJ18: No | CR18: B | CS18: 58.7 | CT18: 220-240 V ~ 50/60 Hz | CU18: Type E/F - 2 pin (German) - Schuko | CV18: 1.3 | CW18: Class I | CX18: 193 | CY18: 71 | DB18: 100.5 | DC18: 60 | DD18: 34.5 | DE18: 13.5 | DL18: 100.5 * 60 * 34.5 | DU18: ISTA 3A | DV18: 1 | EY18: TRUE | EZ18: TRUE | FA18: Angled Hoods - Attributes V3.0.xlsx | FB18: https://chaltecadmin.sharepoint.com/sites/ProductManagement/Shared Documents/02_Strategy/01_Portfolio Strategy/05_Product Passport/01_Large Appliances/ | HF18: 60 | HG18: 607 | HH18: Silver | HI18: B | HJ18: 60 | HK18: -- | HL18: 607 | HM18: 355 | HN18: D | HO18: C | HP18: A | HQ18: 3 | HR18: 2 | HS18: Ø17,5* 3,5cm | HT18: 160 | HU18: 10032843 | HV18: 26*31.9*0.9cm | HW18: 160 | HX18: 10035416 | HY18: Yes | HZ18: 150 | IA18: 800 | IB18: 400 | IC18: -- | ID18: 71 | IE18: 55 | IF18: 2 | IG18: 5 | IH18: No | II18: -- | IJ18: LED | IK18: 1.5W | IL18: Touch | IM18: AC | IN18: 190 | IO18: No | IP18: No | IQ18: No | IR18: Stainless Steel | IS18: Yes | IT18: Yes
A19: 10035466 | B19: Balzac 60cm A Class Slv | D19: Shop | E19: Balzac | F19: 0 | G19: CGCH3 | L19: Large Appliances-Range Hoods-Angled Hoods | M19: Large Appliances | N19: Range Hoods | O19: Angled Hoods | Q19: Balzac | S19: 60 | T19: Non-IoT | U19: 500 - 700 m³/h | V19: A | Y19: Balzac 60cm A Class Slv | Z19: 23 | AB19: Energy Efficiency Class | AC19: A | CG19: Silver | CI19: Slv | CR19: A | CS19: 44.4 | CT19: 220-240 V ~ 50/60 Hz | CU19: Type E/F - 2 pin (German) - Schuko | CV19: 1.3 | CW19: Class I | CX19: 253 | CY19: 71 | DB19: 100.5 | DC19: 60 | DD19: 34.5 | DE19: 13.5 | DL19: 100.5 * 60 * 34.5 | DU19: ISTA 3A | DV19: 1 | EY19: TRUE | EZ19: TRUE | FA19: Angled Hoods - Attributes V3.0.xlsx | FB19: https://chaltecadmin.sharepoint.com/sites/ProductManagement/Shared Documents/02_Strategy/01_Portfolio Strategy/05_Product Passport/01_Large Appliances/ | HF19: 60 | HG19: 605 | HH19: Silver | HI19: A | HJ19: 60 | HK19: 605 | HL19: 484 | HM19: 285 | HN19: D | HO19: A | HP19: A | HQ19: 3+booster | HR19: 2 | HS19: Ø17,5* 3,5cm | HT19: 160 | HU19: 10032843 | HV19: 26*31.9*0.9cm | HW19: 160 | HX19: 10035416 | HY19: Yes | HZ19: 150 | IA19: 800 | IB19: 400 | IC19: 65 | ID19: 60 | IE19: 47 | IF19: 2 | IG19: 5 | IH19: No | II19: -- | IJ19: LED | IK19: 1.5W | IL19: Touch | IM19: AC | IN19: 250 | IO19: No | IP19: No | IQ19: No | IR19: Stainless Steel | IS19: Yes | IT19: Yes
A20: 10031904 | B20: Aurica 60cm B Class Blk | D20: Shop | E20: Aurica | F20: 0 | G20: CGCH3 | L20: Large Appliances-Range Hoods-Angled Hoods | M20: Large Appliances | N20: Range Hoods | O20: Angled Hoods | Q20: Aurica | S20: 60 | T20: Non-IoT | U20: 500 - 700 m³/h | V20: B | Y20: Aurica 60cm B Class Blk | Z20: 23 | AB20: Width | AC20: 60 | AD20: Color | AE20: Black | AF20: Color | AG20: 0 | CG20: Black | CI20: Blk | CJ20: No | CR20: B | CS20: 58.7 | CT20: 220-240 V ~ 50/60 Hz | CU20: Type E/F - 2 pin (German) - Schuko | CV20: 1.3 | CW20: Class I | CX20: 193 | CY20: 71 | DB20: 106.2 | DC20: 60 | DD20: 31 | DE20: 16.5 | DL20: 106.2 * 60 * 31 | DU20: ISTA 3A | DV20: 1 | EY20: TRUE | EZ20: TRUE | FA20: Angled Hoods - Attributes V3.0.xlsx | FB20: https://chaltecadmin.sharepoint.com/sites/ProductManagement/Shared Documents/02_Strategy/01_Portfolio Strategy/05_Product Passport/01_Large Appliances/ | HF20: 60 | HG20: 607 | HH20: Black | HI20: B | HJ20: 60 | HK20: -- | HL20: 607 | HM20: 355 | HN20: D | HO20: C | HP20: A | HQ20: 3 | HR20: 2 | HS20: Ø17,5* 3,5cm | HT20: 160 | HU20: 10032843 | HV20: 26*31.9*0.9cm | HW20: 160 | HX20: 10035416 | HY20: Yes | HZ20: 150 | IA20: 590 | IB20: 300 | IC20: -- | ID20: 71 | IE20: 55 | IF20: 2 | IG20: 5 | IH20: No | II20: -- | IJ20: LED | IK20: 1.5W | IL20: Touch | IM20: AC | IN20: 190 | IO20: No | IP20: No | IQ20: No | IR20: Stainless Steel | IS20: Yes | IT20: Yes
A21: 10032766 | B21: Aurica 90cm B Class Blk | D21: Shop | E21: Aurica | F21: 0 | G21: CGCH3 | L21: Large Appliances-Range Hoods-Angled Hoods | M21: Large Appliances | N21: Range Hoods | O21: Angled Hoods | Q21: Aurica | S21: 90 | T21: Non-IoT | U21: 500 - 700 m³/h | V21: B | Y21: Aurica 90cm B Class Blk | Z21: 23 | AB21: Width | AC21: 90 | AD21: Color | AE21: Black | CG21: Black | CI21: Blk | CJ21: No | CR21: B | CS21: 58.7 | CT21: 220-240 V ~ 50/60 Hz | CU21: Type E/F - 2 pin (German) - Schuko | CV21: 1.3 | CW21: Class I | CX21: 193 | CY21: 71 | DB21: 106.2 | DC21: 90 | DD21: 31 | DE21: 21.5 | DL21: 106.2 * 90 * 31 | DU21: ISTA 3A | DV21: 1 | EY21: TRUE | EZ21: TRUE | FA21: Angled Hoods - Attributes V3.0.xlsx | FB21: https://chaltecadmin.sharepoint.com/sites/ProductManagement/Shared Documents/02_Strategy/01_Portfolio Strategy/05_Product Passport/01_Large Appliances/ | HF21: 90 | HG21: 607 | HH21: Black | HI21: B | HJ21: 90 | HK21: -- | HL21: 607 | HM21: 355 | HN21: D | HO21: C | HP21: A | HQ21: 3 | HR21: 2 | HS21: Ø17,5* 3,5cm | HT21: 160 | HU21: 10032843 | HV21: 26*31.9*0.9cm | HW21: 160 | HX21: 10035416 | HY21: Yes | HZ21: 150 | IA21: 590 | IB21: 300 | IC21: -- | ID21: 71 | IE21: 55 | IF21: 2 | IG21: 5 | IH21: No | II21: -- | IJ21: LED | IK21: 1.5W | IL21: Touch | IM21: AC | IN21: 190 | IO21: No | IP21: No | IQ21: No | IR21: Stainless Steel | IS21: Yes | IT21: Yes
A22: 10032767 | B22: Aurica 90cm B Class Wht | D22: Shop | E22: Aurica | F22: 0 | G22: CGCH3 | L22: Large Appliances-Range Hoods-Angled Hoods | M22: Large Appliances | N22: Range Hoods | O22: Angled Hoods | Q22: Aurica | S22: 90 | T22: Non-IoT | U22: 500 - 700 m³/h | V22: B | Y22: Aurica 90cm B Class Wht | Z22: 23 | AB22: Width | AC22: 90 | AD22: Color | AE22: White | CG22: White | CI22: Wht | CJ22: No | CR22: B | CS22: 58.7 | CT22: 220-240 V ~ 50/60 Hz | CU22: Type E/F - 2 pin (German) - Schuko | CV22: 1.3 | CW22: Class I | CX22: 193 | CY22: 71 | DB22: 106.2 | DC22: 90 | DD22: 31 | DE22: 21.5 | DL22: 106.2 * 90 * 31 | DU22: ISTA 3A | DV22: 1 | EY22: TRUE | EZ22: TRUE | FA22: Angled Hoods - Attributes V3.0.xlsx | FB22: https://chaltecadmin.sharepoint.com/sites/ProductManagement/Shared Documents/02_Strategy/01_Portfolio Strategy/05_Product Passport/01_Large Appliances/ | HF22: 90 | HG22: 607 | HH22: White | HI22: B | HJ22: 90 | HK22: -- | HL22: 607 | HM22: 355 | HN22: D | HO22: C | HP22: A | HQ22: 3 | HR22: 2 | HS22: Ø17,5* 3,5cm | HT22: 160 | HU22: 10032843 | HV22: 26*31.9*0.9cm | HW22: 160 | HX22: 10035416 | HY22: Yes | HZ22: 150 | IA22: 590 | IB22: 300 | IC22: -- | ID22: 71 | IE22: 55 | IF22: 2 | IG22: 5 | IH22: No | II22: -- | IJ22: LED | IK22: 1.5W | IL22: Touch | IM22: AC | IN22: 190 | IO22: No | IP22: No | IQ22: No | IR22: Stainless Steel | IS22: Yes | IT22: Yes
A23: 10032765 | B23: Aurica 60cm B Class Wht | D23: Shop | E23: Aurica | F23: 0 | G23: CGCH3 | L23: Large Appliances-Range Hoods-Angled Hoods | M23: Large Appliances | N23: Range Hoods | O23: Angled Hoods | Q23: Aurica | S23: 60 | T23: Non-IoT | U23: 500 - 700 m³/h | V23: B | Y23: Aurica 60cm B Class Wht | Z23: 23 | AB23: Width | AC23: 60 | AD23: Color | AE23: White | CG23: White | CI23: Wht | CR23: B | CS23: 58.7 | CT23: 220-240 V ~ 50/60 Hz | CU23: Type E/F - 2 pin (German) - Schuko | CV23: 1.3 | CW23: Class I | CX23: 193 | CY23: 71 | DB23: 106.2 | DC23: 60 | DD23: 31 | DE23: 16.5 | DL23: 106.2 * 60 * 31 | DU23: ISTA 3A | DV23: 1 | EY23: TRUE | EZ23: TRUE | FA23: Angled Hoods - Attributes V3.0.xlsx | FB23: https://chaltecadmin.sharepoint.com/sites/ProductManagement/Shared Documents/02_Strategy/01_Portfolio Strategy/05_Product Passport/01_Large Appliances/ | HF23: 60 | HG23: 607 | HH23: White | HI23: B | HJ23: 60 | HK23: -- | HL23: 607 | HM23: 355 | HN23: D | HO23: C | HP23: A | HQ23: 3 | HR23: 2 | HS23: Ø17,5* 3,5cm | HT23: 160 | HU23: 10032843 | HV23: 26*31.9*0.9cm | HW23: 160 | HX23: 10035416 | HY23: Yes | HZ23: 150 | IA23: 590 | IB23: 300 | IC23: -- | ID23: 71 | IE23: 55 | IF23: 2 | IG23: 5 | IH23: No | II23: -- | IJ23: LED | IK23: 1.5W | IL23: Touch | IM23: AC | IN23: 190 | IO23: No | IP23: No | IQ23: No | IR23: Stainless Steel | IS23: Yes | IT23: Yes
A24: 10031905 | B24: Annabelle 60cm A+ Class Blk | D24: Shop | E24: Annabelle | F24: 0 | G24: TK15 | L24: Large Appliances-Range Hoods-Angled Hoods | M24: Large Appliances | N24: Range Hoods | O24: Angled Hoods | Q24: Annabelle | S24: 60 | T24: Non-IoT | U24: 500 - 700 m³/h | V24: A+ | Y24: Annabelle 60cm A+ Class Blk | Z24: 27 | AB24: Width | AC24: 60 | AD24: Color | AE24: Black | CG24: Black | CI24: Blk | CR24: A+ | CS24: 16.8 | CT24: 220-240 V ~ 50/60 Hz | CU24: Type E/F - 2 pin (German) - Schuko | CV24: 2 | CW24: Class I | CX24: 78 | CY24: 66 | DB24: 118 | DC24: 60 | DD24: 43.5 | DE24: 13.8 | DL24: 118 * 60 * 43.5 | DU24: Non 1A | DV24: 1 | EY24: TRUE | EZ24: TRUE | FA24: Angled Hoods - Attributes V3.0.xlsx | FB24: https://chaltecadmin.sharepoint.com/sites/ProductManagement/Shared Documents/02_Strategy/01_Portfolio Strategy/05_Product Passport/01_Large Appliances/ | HF24: 60 | HG24: 642 | HH24: Black | HI24: A+ | HJ24: 60 | HK24: -- | HL24: 641.7 | HM24: 237.9 | HN24: E | HO24: A | HP24: A | HQ24: 3 | HR24: 0 | HS24: φ150（+1,0） | HT24: 300 | HU24: 10027530 | HV24: 230.5*259.5*9 | HW24: 250 | HX24: 10030465 | HY24: Yes | HZ24: 150 | IA24: 780 | IB24: 400 | IC24: -- | ID24: 66 | IE24: 40 | IF24: 2 | IG24: 2 | IH24: No | II24: -- | IJ24: LED | IK24: 2*1.5W | IL24: Touch | IM24: DC | IN24: 75 | IO24: Yes | IP24: No | IQ24: No | IR24: Coated Steel | IS24: Yes | IT24: No
A25: 10032683 | B25: Annabelle 90cm A+ Class Blk | D25: Shop | E25: Annabelle | F25: 0 | G25: TK15 | L25: Large Appliances-Range Hoods-Angled Hoods | M25: Large Appliances | N25: Range Hoods | O25: Angled Hoods | Q25: Annabelle | S25: 90 | T25: Non-IoT | U25: 500 - 700 m³/h | V25: A+ | Y25: Annabelle 90cm A+ Class Blk | Z25: 27 | AB25: Width | AC25: 90 | AD25: Color | AE25: Black | CG25: Black | CI25: Blk | CR25: A+ | CS25: 16.8 | CT25: 220-240 V ~ 50/60 Hz | CU25: Type E/F - 2 pin (German) - Schuko | CV25: 2 | CW25: Class I | CX25: 78 | CY25: 66 | DB25: 118 | DC25: 90 | DD25: 43.5 | DE25: 15.3 | DL25: 118 * 90 * 43.5 | DU25: Non 1A | DV25: 1 | EY25: TRUE | EZ25: TRUE | FA25: Angled Hoods - Attributes V3.0.xlsx | FB25: https://chaltecadmin.sharepoint.com/sites/ProductManagement/Shared Documents/02_Strategy/01_Portfolio Strategy/05_Product Passport/01_Large Appliances/ | HF25: 90 | HG25: 642 | HH25: Black | HI25: A+ | HJ25: 90 | HK25: -- | HL25: 641.7 | HM25: 237.9 | HN25: E | HO25: A | HP25: A | HQ25: 3 | HR25: 0 | HS25: φ150（+1,0） | HT25: 300 | HU25: 10027530 | HV25: 230.5*259.5*9 | HW25: 250 | HX25: 10030465 | HY25: Yes | HZ25: 150 | IA25: 780 | IB25: 400 | IC25: -- | ID25: 66 | IE25: 40 | IF25: 2 | IG25: 2 | IH25: No | II25: -- | IJ25: LED | IK25: 2*1.5W | IL25: Touch | IM25: DC | IN25: 75 | IO25: Yes | IP25: No | IQ25: No | IR25: Coated Steel | IS25: Yes | IT25: No
A26: 10032684 | B26: Annabelle 60cm A+ Class Wht | D26: Shop | E26: Annabelle | F26: 0 | G26: TK15 | L26: Large Appliances-Range Hoods-Angled Hoods | M26: Large Appliances | N26: Range Hoods | O26: Angled Hoods | Q26: Annabelle | S26: 60 | T26: Non-IoT | U26: 500 - 700 m³/h | V26: A+ | Y26: Annabelle 60cm A+ Class Wht | Z26: 27 | AB26: Width | AC26: 60 | AD26: Color | AE26: White | CG26: White | CI26: Wht | CR26: A+ | CS26: 16.8 | CT26: 220-240 V ~ 50/60 Hz | CU26: Type E/F - 2 pin (German) - Schuko | CV26: 2 | CW26: Class I | CX26: 78 | CY26: 66 | DB26: 118 | DC26: 60 | DD26: 43.5 | DE26: 13.8 | DL26: 118 * 60 * 43.5 | DU26: Non 1A | DV26: 1 | EY26: TRUE | EZ26: TRUE | FA26: Angled Hoods - Attributes V3.0.xlsx | FB26: https://chaltecadmin.sharepoint.com/sites/ProductManagement/Shared Documents/02_Strategy/01_Portfolio Strategy/05_Product Passport/01_Large Appliances/ | HF26: 60 | HG26: 642 | HH26: White | HI26: A+ | HJ26: 60 | HK26: -- | HL26: 641.7 | HM26: 237.9 | HN26: E | HO26: A | HP26: A | HQ26: 3 | HR26: 0 | HS26: φ150（+1,0） | HT26: 300 | HU26: 10027530 | HV26: 230.5*259.5*9 | HW26: 250 | HX26: 10030465 | HY26: Yes | HZ26: 150 | IA26: 780 | IB26: 400 | IC26: -- | ID26: 66 | IE26: 40 | IF26: 2 | IG26: 2 | IH26: No | II26: -- | IJ26: LED | IK26: 2*1.5W | IL26: Touch | IM26: DC | IN26: 75 | IO26: Yes | IP26: No | IQ26: No | IR26: Coated Steel | IS26: Yes | IT26: No
A27: 10033116 | B27: Mirage 60cm A++ Class Blk | D27: Shop | E27: Mirage | F27: 0 | G27: CGCH3 | L27: Large Appliances-Range Hoods-Angled Hoods | M27: Large Appliances | N27: Range Hoods | O27: Angled Hoods | Q27: Mirage | S27: 60 | T27: Non-IoT | U27: 500 - 700 m³/h | V27: A++ | Y27: Mirage 60cm A++ Class Blk | Z27: 25 | AB27: Width | AC27: 60 | AD27: Color | AE27: Black | CG27: Black | CI27: Blk | CJ27: No | CR27: A++ | CS27: 12.5 | CT27: 220-240 V ~ 50/60 Hz | CU27: Type E/F - 2 pin (German) - Schuko | CV27: 1.3 | CW27: Class I | CX27: 79 | CY27: 59 | DB27: 108.6 | DC27: 60 | DD27: 32.5 | DE27: 17.5 | DL27: 108.6 * 60 * 32.5 | DU27: ISTA 3A | DV27: 1 | EY27: TRUE | EZ27: TRUE | FA27: Angled Hoods - Attributes V3.0.xlsx | FB27: https://chaltecadmin.sharepoint.com/sites/ProductManagement/Shared Documents/02_Strategy/01_Portfolio Strategy/05_Product Passport/01_Large Appliances/ | HF27: 60 | HG27: 515 | HH27: Black | HI27: A++ | HJ27: 60 | HK27: -- | HL27: 515 | HM27: 320 | HN27: E | HO27: A | HP27: A | HQ27: 3 | HR27: 2 | HS27: Ø17,5* 3,5cm | HT27: 160 | HU27: 10032843 | HV27: 26*31.9*0.9cm | HW27: 160 | HX27: 10035416 | HY27: Yes | HZ27: 150 | IA27: 590 | IB27: 300 | IC27: -- | ID27: 59 | IE27: 48 | IF27: 2 | IG27: 5 | IH27: Yes | II27: 9 | IJ27: LED | IK27: 1.5W | IL27: Touch | IM27: DC | IN27: 70 | IO27: No | IP27: No | IQ27: No | IR27: Coated Steel | IS27: Yes | IT27: Yes
A28: 10033117 | B28: Mirage 90cm A++ Class Blk | D28: Shop | E28: Mirage | F28: 0 | G28: CGCH3 | L28: Large Appliances-Range Hoods-Angled Hoods | M28: Large Appliances | N28: Range Hoods | O28: Angled Hoods | Q28: Mirage | S28: 90 | T28: Non-IoT | U28: 500 - 700 m³/h | V28: A++ | Y28: Mirage 90cm A++ Class Blk | Z28: 25 | AB28: Width | AC28: 90 | AD28: Color | AE28: Black | CG28: Black | CI28: Blk | CJ28: No | CR28: A++ | CS28: 12.5 | CT28: 220-240 V ~ 50/60 Hz | CU28: Type E/F - 2 pin (German) - Schuko | CV28: 1.3 | CW28: Class I | CX28: 79 | CY28: 59 | DB28: 108.6 | DC28: 90 | DD28: 32.5 | DE28: 19.5 | DL28: 108.6 * 90 * 32.5 | DU28: ISTA 3A | DV28: 1 | EY28: TRUE | EZ28: TRUE | FA28: Angled Hoods - Attributes V3.0.xlsx | FB28: https://chaltecadmin.sharepoint.com/sites/ProductManagement/Shared Documents/02_Strategy/01_Portfolio Strategy/05_Product Passport/01_Large Appliances/ | HF28: 90 | HG28: 515 | HH28: Black | HI28: A++ | HJ28: 90 | HK28: -- | HL28: 515 | HM28: 320 | HN28: E | HO28: A | HP28: A | HQ28: 3 | HR28: 2 | HS28: Ø17,5* 3,5cm | HT28: 160 | HU28: 10032843 | HV28: 26*31.9*0.9cm | HW28: 160 | HX28: 10035416 | HY28: Yes | HZ28: 150 | IA28: 590 | IB28: 300 | IC28: -- | ID28: 59 | IE28: 48 | IF28: 2 | IG28: 5 | IH28: Yes | II28: 9 | IJ28: LED | IK28: 1.5W | IL28: Touch | IM28: DC | IN28: 70 | IO28: No | IP28: No | IQ28: No | IR28: Coated Steel | IS28: Yes | IT28: Yes
A29: 10034151 | B29: Mirage 60cm A++ Class Wht | D29: Shop | E29: Mirage | F29: 0 | G29: CGCH3 | L29: Large Appliances-Range Hoods-Angled Hoods | M29: Large Appliances | N29: Range Hoods | O29: Angled Hoods | Q29: Mirage | S29: 60 | T29: Non-IoT | U29: 500 - 700 m³/h | V29: A++ | Y29: Mirage 60cm A++ Class Wht | Z29: 25 | AB29: Width | AC29: 60 | AD29: Color | AE29: White | CG29: White | CI29: Wht | CJ29: No | CR29: A++ | CS29: 12.5 | CT29: 220-240 V ~ 50/60 Hz | CU29: Type E/F - 2 pin (German) - Schuko | CV29: 1.3 | CW29: Class I | CX29: 79 | CY29: 59 | DB29: 108.6 | DC29: 60 | DD29: 32.5 | DE29: 17.5 | DL29: 108.6 * 60 * 32.5 | DU29: ISTA 3A | DV29: 1 | EY29: TRUE | EZ29: TRUE | FA29: Angled Hoods - Attributes V3.0.xlsx | FB29: https://chaltecadmin.sharepoint.com/sites/ProductManagement/Shared Documents/02_Strategy/01_Portfolio Strategy/05_Product Passport/01_Large Appliances/ | HF29: 60 | HG29: 515 | HH29: White | HI29: A++ | HJ29: 60 | HK29: -- | HL29: 515 | HM29: 320 | HN29: E | HO29: A | HP29: A | HQ29: 3 | HR29: 2 | HS29: Ø17,5* 3,5cm | HT29: 160 | HU29: 10032843 | HV29: 26*31.9*0.9cm | HW29: 160 | HX29: 10035416 | HY29: Yes | HZ29: 150 | IA29: 590 | IB29: 300 | IC29: -- | ID29: 59 | IE29: 48 | IF29: 2 | IG29: 5 | IH29: Yes | II29: 9 | IJ29: LED | IK29: 1.5W | IL29: Touch | IM29: DC | IN29: 70 | IO29: No | IP29: No | IQ29: No | IR29: Coated Steel | IS29: Yes | IT29: Yes
A30: 10034152 | B30: Mirage 90cm A++ Class Wht | D30: Shop | E30: Mirage | F30: 0 | G30: CGCH3 | L30: Large Appliances-Range Hoods-Angled Hoods | M30: Large Appliances | N30: Range Hoods | O30: Angled Hoods | Q30: Mirage | S30: 90 | T30: Non-IoT | U30: 500 - 700 m³/h | V30: A++ | Y30: Mirage 90cm A++ Class Wht | Z30: 25 | AB30: Width | AC30: 90 | AD30: Color | AE30: White | CG30: White | CI30: Wht | CJ30: No | CR30: A++ | CS30: 12.5 | CT30: 220-240 V ~ 50/60 Hz | CU30: Type E/F - 2 pin (German) - Schuko | CV30: 1.3 | CW30: Class I | CX30: 79 | CY30: 59 | DB30: 108.6 | DC30: 90 | DD30: 32.5 | DE30: 19.5 | DL30: 108.6 * 90 * 32.5 | DU30: ISTA 3A | DV30: 1 | EY30: TRUE | EZ30: TRUE | FA30: Angled Hoods - Attributes V3.0.xlsx | FB30: https://chaltecadmin.sharepoint.com/sites/ProductManagement/Shared Documents/02_Strategy/01_Portfolio Strategy/05_Product Passport/01_Large Appliances/ | HF30: 90 | HG30: 515 | HH30: White | HI30: A++ | HJ30: 90 | HK30: -- | HL30: 515 | HM30: 320 | HN30: E | HO30: A | HP30: A | HQ30: 3 | HR30: 2 | HS30: Ø17,5* 3,5cm | HT30: 160 | HU30: 10032843 | HV30: 26*31.9*0.9cm | HW30: 160 | HX30: 10035416 | HY30: Yes | HZ30: 150 | IA30: 590 | IB30: 300 | IC30: -- | ID30: 59 | IE30: 48 | IF30: 2 | IG30: 5 | IH30: Yes | II30: 9 | IJ30: LED | IK30: 1.5W | IL30: Touch | IM30: DC | IN30: 70 | IO30: No | IP30: No | IQ30: No | IR30: Coated Steel | IS30: Yes | IT30: Yes
A31: 10033777 | B31: Silver Lining 60cm A Class Slv | D31: Shop | E31: Silver Lining | F31: 0 | G31: CGCH2 | L31: Large Appliances-Range Hoods-Angled Hoods | M31: Large Appliances | N31: Range Hoods | O31: Angled Hoods | Q31: Silver Lining | S31: 60 | T31: Non-IoT | U31: 500 - 700 m³/h | V31: A | Y31: Silver Lining 60cm A Class Slv | Z31: 30 | AB31: Width | AC31: 60 | AD31: EEL | AE31: 60 | CG31: Silver | CI31: Slv | CR31: A | CS31: 42 | CT31: 220-240 V ~ 50/60 Hz | CU31: Type E/F - 2 pin (German) - Schuko | CV31: 1.5 | CW31: Class I | CX31: 165 | CY31: 67 | DB31: 61-89cm | DC31: 60cm | DD31: 43cm | DE31: 12 | DL31: 61-89cm * 60cm * 43cm | DU31: ISTA 1A | DV31: 1 | EY31: TRUE | EZ31: TRUE | FA31: Angled Hoods - Attributes V3.0.xlsx | FB31: https://chaltecadmin.sharepoint.com/sites/ProductManagement/Shared Documents/02_Strategy/01_Portfolio Strategy/05_Product Passport/01_Large Appliances/ | HF31: 60 | HG31: 542 | HH31: Silver | HI31: A | HJ31: 60 | HK31: -- | HL31: 542 | HM31: 410 | HN31: D | HP31: B | HQ31: 3 | HR31: 0 | HS31: 17.6*3.5cm | HT31: 160 | HU31: 10030983 | HV31: 22.2*31.9cm | HW31: 135 | HX31: 10032226 | HY31: Yes | HZ31: 150 | IA31: 600 | IB31: 300 | IC31: -- | ID31: 67 | IE31: 61 | IF31: 2 | IG31: 3 | IH31: No | II31: -- | IJ31: LED | IK31: 3W | IL31: Push button | IM31: AC | IN31: 165 | IO31: Yes | IP31: No | IQ31: No | IR31: Stainless Steel | IS31: No | IT31: No
A32: 10035318 | B32: Silver Lining 90cm A Class Slv | D32: Shop | E32: Silver Lining | F32: 0 | G32: CGCH2 | L32: Large Appliances-Range Hoods-Angled Hoods | M32: Large Appliances | N32: Range Hoods | O32: Angled Hoods | Q32: Silver Lining | S32: 90 | T32: Non-IoT | U32: 500 - 700 m³/h | V32: A | Y32: Silver Lining 90cm A Class Slv | Z32: 30 | AB32: Width | AC32: 90 | AD32: EEL | AE32: 90 | CG32: Silver | CI32: Slv | CR32: A | CS32: 42 | CT32: 220-240 V ~ 50/60 Hz | CU32: Type E/F - 2 pin (German) - Schuko | CV32: 1.5 | CW32: Class I | CX32: 165 | CY32: 67 | DB32: 61-89cm | DC32: 60cm | DD32: 43cm | DE32: 14 | DL32: 61-89cm * 60cm * 43cm | DU32: ISTA 1A | DV32: 1 | EY32: TRUE | EZ32: TRUE | FA32: Angled Hoods - Attributes V3.0.xlsx | FB32: https://chaltecadmin.sharepoint.com/sites/ProductManagement/Shared Documents/02_Strategy/01_Portfolio Strategy/05_Product Passport/01_Large Appliances/ | HF32: 90 | HG32: 542 | HH32: Silver | HI32: A | HJ32: 90 | HK32: -- | HL32: 542 | HM32: 410 | HN32: D | HP32: B | HQ32: 3 | HR32: 0 | HS32: 17.6*3.5cm | HT32: 160 | HU32: 10030983 | HV32: 22.2*31.9cm | HW32: 135 | HX32: 10032226 | HY32: Yes | HZ32: 150 | IA32: 600 | IB32: 300 | IC32: -- | ID32: 67 | IE32: 61 | IF32: 2 | IG32: 3 | IH32: No | II32: -- | IJ32: LED | IK32: 3W | IL32: Push button | IM32: AC | IN32: 165 | IO32: Yes | IP32: No | IQ32: No | IR32: Stainless Steel | IS32: No | IT32: No
A33: 10048661 | D33: Shop | L33: Large Appliances-Range Hoods-Angled Hoods | M33: Large Appliances | N33: Range Hoods | O33: Angled Hoods | Q33: Silver Lining | S33: 60 | T33: Non-IoT | U33: 500 - 700 m³/h | V33: A++ | Y33: Silver Lining 60cm A++ Class Slv | Z33: 32 | AB33: Width | AC33: 60 | AD33: EEL | AE33: 60 | AI33: Y216010051 | CG33: Silver | CI33: Slv | CJ33: No | CR33: A++ | CS33: 12.3 | CT33: 220-240 V ~ 50/60 Hz | CU33: Type E/F - 2 pin (German) - Schuko | CV33: 1.1 | CW33: Class I | CX33: 83 | CY33: 62 | DB33: 76.7～112.7 | DC33: 59.5 | DD33: 40 | DE33: 9.5 | DL33: 76.7～112.7 * 59.5 * 40 | DU33: ISTA 3A | DV33: 1 | EA33: 2x Carbon Filter | EC33: 9*Plastic Wall Plug | EE33: 9*Self-tapping Scr | EG33: 6*Taptite Screw | EI33: 1*lower chimney bracket | EL33: 60cm Angled Hood | EM33: A++ EEEL | EN33: max 597m3/h flow rate | EO33: Stainless Steel Panel | EP33: Led Illumination | ER33: 60cm Angled Hood | ES33: A++ EEL | ET33: max 597m3/h flow rate with 3 speed levels | EU33: 52 to 62 dB noise emission | EV33: Included Carbon Filter and Aluminum Filter | EW33: Led Light | EY33: TRUE | EZ33: TRUE | FA33: Angled Hoods - Attributes V3.0.xlsx | FB33: https://chaltecadmin.sharepoint.com/sites/ProductManagement/Shared Documents/02_Strategy/01_Portfolio Strategy/05_Product Passport/01_Large Appliances/ | HF33: 60 | HG33: 597 | HH33: Silver | HI33: A++ | HJ33: 60 | HK33: - | HL33: 597.4 | HM33: 364.4 | HN33: G | HO33: A++ | HP33: A | HQ33: 3 | HR33: 2 | HS33: 17.6x3.55 | HT33: 180 | HU33: Y302020004 | HV33: 31.9x25.1x0.9 | HW33: 110 | HX33: Y301010207 | HY33: No | HZ33: 150 | IA33: 800 | IB33: 400 | IC33: - | ID33: 62 | IE33: 52 | IF33: 2 | IG33: 3 | IH33: No | II33: - | IJ33: LED | IK33: 2*1.5W | IL33: Push button | IM33: DC | IN33: 80 | IO33: Yes | IP33: No | IQ33: No | IR33: Stainless Steel | IS33: No | IT33: Yes
A34: 10048662 | D34: Shop | L34: Large Appliances-Range Hoods-Angled Hoods | M34: Large Appliances | N34: Range Hoods | O34: Angled Hoods | Q34: Silver Lining | S34: 90 | T34: Non-IoT | U34: 500 - 700 m³/h | V34: A++ | Y34: Silver Lining 90cm A++ Class Slv | Z34: 32 | AB34: Width | AC34: 90 | AD34: EEL | AE34: 90 | AI34: Y216010052 | CG34: Silver | CI34: Slv | CJ34: No | CR34: A++ | CS34: 12.3 | CT34: 220-240 V ~ 50/60 Hz | CU34: Type E/F - 2 pin (German) - Schuko | CV34: 1.1 | CW34: Class I | CX34: 83 | CY34: 62 | DB34: 76.7～112.7 | DC34: 59.5 | DD34: 40 | DE34: 9.5 | DL34: 76.7～112.7 * 59.5 * 40 | DU34: ISTA 3A | DV34: 1 | EA34: 2x Carbon Filter | EC34: 9*Plastic Wall Plug | EE34: 9*Self-tapping Scr | EG34: 6*Taptite Screw | EI34: 1*lower chimney bracket | EL34: 90cm Angled Hood | EM34: A++ EEEL | EN34: max 597m3/h flow rate | EO34: Stainless Steel Panel | EP34: Led Illumination | ER34: 90cm Angled Hood | ES34: A++ EEL | ET34: max 597m3/h flow rate with 3 speed levels | EU34: 52 to 62 dB noise emission | EV34: Included Carbon Filter and Aluminum Filter | EW34: Led Light | EY34: TRUE | EZ34: TRUE | FA34: Angled Hoods - Attributes V3.0.xlsx | FB34: https://chaltecadmin.sharepoint.com/sites/ProductManagement/Shared Documents/02_Strategy/01_Portfolio Strategy/05_Product Passport/01_Large Appliances/ | HF34: 90 | HG34: 597 | HH34: Silver | HI34: A++ | HJ34: 90 | HK34: - | HL34: 597.4 | HM34: 364.4 | HN34: G | HO34: A++ | HP34: A | HQ34: 3 | HR34: 2 | HS34: 17.6x3.55 | HT34: 180 | HU34: Y302020004 | HW34: 110 | HX34: Y301010207 | HY34: No | HZ34: 150 | IA34: 800 | IB34: 400 | IC34: - | ID34: 62 | IE34: 52 | IF34: 2 | IG34: 3 | IH34: No | II34: - | IJ34: LED | IK34: 2*1.5W | IL34: Push button | IM34: DC | IN34: 80 | IO34: Yes | IP34: No | IQ34: No | IR34: Stainless Steel | IS34: No | IT34: Yes
A35: 10034100 | B35: Helena 60cm A Class Blk | D35: Shop | E35: Helena | F35: 0 | G35: CGCH3 | L35: Large Appliances-Range Hoods-Angled Hoods | M35: Large Appliances | N35: Range Hoods | O35: Angled Hoods | Q35: Helena | S35: 60 | T35: Non-IoT | U35: 500 - 700 m³/h | V35: A | Y35: Helena 60cm A Class Blk | Z35: 23 | AB35: Width | AC35: 60 | AD35: Color | AE35: Black | CG35: Black | CI35: Blk | CJ35: No | CR35: A | CS35: 40.4 | CT35: 220-240 V ~ 50/60 Hz | CU35: Type E/F - 2 pin (German) - Schuko | CV35: 1.3 | CW35: Class I | CX35: 174 | CY35: 63 | DB35: 106.2 | DC35: 60 | DD35: 31 | DE35: 16.5 | DL35: 106.2 * 60 * 31 | DU35: ISTA 3A | DV35: 1 | EY35: TRUE | EZ35: TRUE | FA35: Angled Hoods - Attributes V3.0.xlsx | FB35: https://chaltecadmin.sharepoint.com/sites/ProductManagement/Shared Documents/02_Strategy/01_Portfolio Strategy/05_Product Passport/01_Large Appliances/ | HF35: 60 | HG35: 594 | HH35: Black | HI35: A | HJ35: 60 | HK35: -- | HL35: 594 | HM35: 415 | HN35: D | HO35: A | HP35: A | HQ35: 3 | HR35: 2 | HS35: Ø17,5* 3,5cm | HT35: 160 | HU35: 10032843 | HV35: 26*31.9*0.9cm | HW35: 160 | HX35: 10035416 | HY35: Yes | HZ35: 150 | IA35: 590 | IB35: 300 | IC35: -- | ID35: 63 | IE35: 59 | IF35: 2 | IG35: 5 | IH35: Yes | II35: 9 | IJ35: LED | IK35: 1.5W | IL35: Touch | IM35: AC | IN35: 165 | IO35: No | IP35: No | IQ35: No | IR35: Coated Steel | IS35: Yes | IT35: Yes
A36: 10034101 | B36: Helena 60cm A Class Wht | D36: Shop | E36: Helena | F36: 0 | G36: CGCH3 | L36: Large Appliances-Range Hoods-Angled Hoods | M36: Large Appliances | N36: Range Hoods | O36: Angled Hoods | Q36: Helena | S36: 60 | T36: Non-IoT | U36: 500 - 700 m³/h | V36: A | Y36: Helena 60cm A Class Wht | Z36: 23 | AB36: Width | AC36: 60 | AD36: Color | AE36: White | CG36: White | CI36: Wht | CJ36: No | CR36: A | CS36: 40.4 | CT36: 220-240 V ~ 50/60 Hz | CU36: Type E/F - 2 pin (German) - Schuko | CV36: 1.3 | CW36: Class I | CX36: 174 | CY36: 63 | DB36: 106.2 | DC36: 60 | DD36: 31 | DE36: 16.5 | DL36: 106.2 * 60 * 31 | DU36: ISTA 3A | DV36: 1 | EY36: TRUE | EZ36: TRUE | FA36: Angled Hoods - Attributes V3.0.xlsx | FB36: https://chaltecadmin.sharepoint.com/sites/ProductManagement/Shared Documents/02_Strategy/01_Portfolio Strategy/05_Product Passport/01_Large Appliances/ | HF36: 60 | HG36: 594 | HH36: White | HI36: A | HJ36: 60 | HK36: -- | HL36: 594 | HM36: 415 | HN36: D | HO36: A | HP36: A | HQ36: 3 | HR36: 2 | HS36: Ø17,5* 3,5cm | HT36: 160 | HU36: 10032843 | HV36: 26*31.9*0.9cm | HW36: 160 | HX36: 10035416 | HY36: Yes | HZ36: 150 | IA36: 590 | IB36: 300 | IC36: -- | ID36: 63 | IE36: 59 | IF36: 2 | IG36: 5 | IH36: Yes | II36: 9 | IJ36: LED | IK36: 1.5W | IL36: Touch | IM36: AC | IN36: 165 | IO36: No | IP36: No | IQ36: No | IR36: Coated Steel | IS36: Yes | IT36: Yes
A37: 10034102 | D37: Shop | L37: Large Appliances-Range Hoods-Angled Hoods | M37: Large Appliances | N37: Range Hoods | O37: Angled Hoods | Q37: Helena | S37: 90 | T37: Non-IoT | U37: 500 - 700 m³/h | V37: A | Y37: Helena 90cm A Class Blk | Z37: 23 | AB37: Width | AC37: 90 | AD37: Color | AE37: Black | CG37: Black | CI37: Blk | CJ37: No | CR37: A | CS37: 40.4 | CT37: 220-240 V ~ 50/60 Hz | CU37: Type E/F - 2 pin (German) - Schuko | CV37: 1.3 | CW37: Class I | CX37: 174 | CY37: 63 | DB37: 106.2 | DC37: 90 | DD37: 31 | DE37: 21.5 | DL37: 106.2 * 90 * 31 | DU37: ISTA 3A | DV37: 1 | EY37: TRUE | EZ37: TRUE | FA37: Angled Hoods - Attributes V3.0.xlsx | FB37: https://chaltecadmin.sharepoint.com/sites/ProductManagement/Shared Documents/02_Strategy/01_Portfolio Strategy/05_Product Passport/01_Large Appliances/ | HF37: 90 | HG37: 594 | HH37: Black | HI37: A | HJ37: 90 | HK37: -- | HL37: 594 | HM37: 415 | HN37: D | HO37: A | HP37: A | HQ37: 3 | HR37: 2 | HS37: Ø17,5* 3,5cm | HT37: 160 | HU37: 10032843 | HV37: 26*31.9*0.9cm | HW37: 160 | HX37: 10035416 | HY37: Yes | HZ37: 150 | IA37: 590 | IB37: 300 | IC37: -- | ID37: 63 | IE37: 59 | IF37: 2 | IG37: 5 | IH37: Yes | II37: 9 | IJ37: LED | IK37: 1.5W | IL37: Touch | IM37: AC | IN37: 165 | IO37: No | IP37: No | IQ37: No | IR37: Coated Steel | IS37: Yes | IT37: Yes
A38: 10034103 | D38: Shop | L38: Large Appliances-Range Hoods-Angled Hoods | M38: Large Appliances | N38: Range Hoods | O38: Angled Hoods | Q38: Helena | S38: 90 | T38: Non-IoT | U38: 500 - 700 m³/h | V38: A | Y38: Helena 90cm A Class Wht | Z38: 23 | AB38: Width | AC38: 90 | AD38: Color | AE38: White | CG38: White | CI38: Wht | CJ38: No | CR38: A | CS38: 40.4 | CT38: 220-240 V ~ 50/60 Hz | CU38: Type E/F - 2 pin (German) - Schuko | CV38: 1.3 | CW38: Class I | CX38: 174 | CY38: 63 | DB38: 106.2 | DC38: 90 | DD38: 31 | DE38: 21.5 | DL38: 106.2 * 90 * 31 | DU38: ISTA 3A | DV38: 1 | EY38: TRUE | EZ38: TRUE | FA38: Angled Hoods - Attributes V3.0.xlsx | FB38: https://chaltecadmin.sharepoint.com/sites/ProductManagement/Shared Documents/02_Strategy/01_Portfolio Strategy/05_Product Passport/01_Large Appliances/ | HF38: 90 | HG38: 594 | HH38: White | HI38: A | HJ38: 90 | HK38: -- | HL38: 594 | HM38: 415 | HN38: D | HO38: A | HP38: A | HQ38: 3 | HR38: 2 | HS38: Ø17,5* 3,5cm | HT38: 160 | HU38: 10032843 | HV38: 26*31.9*0.9cm | HW38: 160 | HX38: 10035416 | HY38: Yes | HZ38: 150 | IA38: 590 | IB38: 300 | IC38: -- | ID38: 63 | IE38: 59 | IF38: 2 | IG38: 5 | IH38: Yes | II38: 9 | IJ38: LED | IK38: 1.5W | IL38: Touch | IM38: AC | IN38: 165 | IO38: No | IP38: No | IQ38: No | IR38: Coated Steel | IS38: Yes | IT38: Yes
A39: 10034258 | D39: Shop | L39: Large Appliances-Range Hoods-Angled Hoods | M39: Large Appliances | N39: Range Hoods | O39: Angled Hoods | Q39: Sofia | S39: 60 | T39: Non-IoT | U39: < 500 m³/h | V39: B | Y39: Sofia 60cm B Class Blk | Z39: 22 | AB39: Color | AC39: Black | CG39: black | CI39: Blk | CJ39: No | CR39: B | CS39: 25.9 | CT39: 220-240 V ~ 50/60 Hz | CU39: Type E/F - 2 pin (German) - Schuko | CV39: 1.85 | CW39: Class I | CX39: 65 | CY39: 67 | DB39: 105 | DC39: 59.7 | DD39: 40 | DE39: 14 | DL39: 105 * 59.7 * 40 | DU39: ISTA 1A | DV39: 1 | DW39: / | DX39: / | EA39: Mounting Screw Assembly | EC39: Smoke Exhaust Pipe Assembly | EE39: User Manual | EG39: Mounting Bracket | EY39: TRUE | EZ39: TRUE | FA39: Angled Hoods - Attributes V3.0.xlsx | FB39: https://chaltecadmin.sharepoint.com/sites/ProductManagement/Shared Documents/02_Strategy/01_Portfolio Strategy/05_Product Passport/01_Large Appliances/ | HF39: 60 | HG39: 300 | HH39: black | HI39: B | HJ39: 60 | HK39: -- | HL39: 300 | HM39: 180 | HN39: D | HO39: E | HP39: B | HQ39: 3 | HR39: 0 | HV39: 25.8*23.05*0.9 | HY39: Yes | HZ39: 150 | IA39: 1050 | IB39: 760 | IC39: -- | ID39: 67 | IE39: 56 | IF39: 1 | IG39: 1 | IH39: No | II39: -- | IJ39: LED | IK39: 1.5 | IL39: Touch | IM39: AC | IN39: 65 | IO39: Yes | IP39: No | IQ39: No | IR39: Aluminum foil | IS39: No | IT39: No
A40: 10034259 | D40: Shop | L40: Large Appliances-Range Hoods-Angled Hoods | M40: Large Appliances | N40: Range Hoods | O40: Angled Hoods | Q40: Sofia | S40: 60 | T40: Non-IoT | U40: < 500 m³/h | V40: B | Y40: Sofia 60cm B Class Wht | Z40: 22 | AB40: Color | AC40: White | CG40: White | CI40: Wht | CJ40: No | CR40: B | CS40: 25.9 | CT40: 220-240 V ~ 50/60 Hz | CU40: Type E/F - 2 pin (German) - Schuko | CV40: 1.85 | CW40: Class I | CX40: 65 | CY40: 67 | DB40: 105 | DC40: 59.7 | DD40: 40 | DE40: 14 | DL40: 105 * 59.7 * 40 | DU40: ISTA 1A | DV40: 1 | DW40: / | DX40: / | EA40: Mounting Screw Assembly | EC40: Smoke Exhaust Pipe Assembly | EE40: User Manual | EG40: Mounting Bracket | EY40: TRUE | EZ40: TRUE | FA40: Angled Hoods - Attributes V3.0.xlsx | FB40: https://chaltecadmin.sharepoint.com/sites/ProductManagement/Shared Documents/02_Strategy/01_Portfolio Strategy/05_Product Passport/01_Large Appliances/ | HF40: 60 | HG40: 300 | HH40: White | HI40: B | HJ40: 60 | HK40: -- | HL40: 300 | HM40: 180 | HN40: D | HO40: E | HP40: B | HQ40: 3 | HR40: 0 | HV40: 25.8*23.05*0.9 | HY40: Yes | HZ40: 150 | IA40: 1050 | IB40: 760 | IC40: -- | ID40: 67 | IE40: 56 | IF40: 1 | IG40: 1 | IH40: No | II40: -- | IJ40: LED | IK40: 1.5 | IL40: Touch | IM40: AC | IN40: 65 | IO40: Yes | IP40: No | IQ40: No | IR40: Aluminum foil | IS40: No | IT40: No
A41: 10035280 | B41: Amelia 60cm Class Blk | D41: Shop | E41: Amelia | F41: 0 | G41: CGCH6 | L41: Large Appliances-Range Hoods-Angled Hoods | M41: Large Appliances | N41: Range Hoods | O41: Angled Hoods | Q41: Amelia | S41: 60 | T41: Non-IoT | U41: 500 - 700 m³/h | V41: 0 | Y41: Amelia 60cm C Class Blk | Z41: 23 | AB41: Color | AC41: Black | CG41: Black | CI41: Blk | CJ41: No | CR41: C | CS41: 65.5 | CT41: 220-240 V ~ 50/60 Hz | CU41: Type E/F - 2 pin (German) - Schuko | CV41: 1.93 | CW41: Class I | CX41: 128 | CY41: 66 | DB41: 117 | DC41: 59.8 | DD41: 23.3 | DE41: 14 | DL41: 117 * 59.8 * 23.3 | DU41: ISTA 1A | DV41: 1 | EA41: Installation kits | EB41: 09010600234058 | EC41: manual book | ED41: 09800001219 | EY41: TRUE | EZ41: TRUE | FA41: Angled Hoods - Attributes V3.0.xlsx | FB41: https://chaltecadmin.sharepoint.com/sites/ProductManagement/Shared Documents/02_Strategy/01_Portfolio Strategy/05_Product Passport/01_Large Appliances/ | HF41: 60 | HG41: 587 | HH41: Black | HI41: C | HJ41: 60 | HK41: 586.9 | HL41: 547.7 | HM41: 297.2 | HN41: E | HO41: D | HP41: B | HQ41: 3 | HR41: 1 | HS41: 2.3*1 | HT41: 210 | HU41: 10035284 | HV41: 34*27.4 | HW41: 50 | HX41: 09780000022 | HY41: Yes | HZ41: 150 | IA41: 780 | IB41: 400 | IC41: -- | ID41: 66 | IE41: 58 | IF41: 1 | IG41: 3 | IH41: No | II41: -- | IJ41: LED | IK41: 3 | IL41: Illuminated LED knob | IM41: AC | IN41: 125 | IO41: No | IP41: No | IQ41: No | IR41: Coated Steel | IS41: No | IT41: No
A42: 10035282 | B42: Amelia 60cm Class Wht | D42: Shop | E42: Amelia | F42: 0 | G42: CGCH6 | L42: Large Appliances-Range Hoods-Angled Hoods | M42: Large Appliances | N42: Range Hoods | O42: Angled Hoods | Q42: Amelia | S42: 60 | T42: Non-IoT | U42: 500 - 700 m³/h | V42: 0 | Y42: Amelia 60cm C Class Wht | Z42: 23 | AB42: Color | AC42: White | CG42: White | CI42: Wht | CJ42: No | CR42: C | CS42: 65.5 | CT42: 220-240 V ~ 50/60 Hz | CU42: Type E/F - 2 pin (German) - Schuko | CV42: 1.93 | CW42: Class I | CX42: 128 | CY42: 66 | DB42: 117 | DC42: 59.8 | DD42: 23.3 | DE42: 14 | DL42: 117 * 59.8 * 23.3 | DU42: ISTA 1A | DV42: 1 | EA42: Installation kits | EB42: 09010600234058 | EC42: manual book | ED42: 09800001219 | EY42: TRUE | EZ42: TRUE | FA42: Angled Hoods - Attributes V3.0.xlsx | FB42: https://chaltecadmin.sharepoint.com/sites/ProductManagement/Shared Documents/02_Strategy/01_Portfolio Strategy/05_Product Passport/01_Large Appliances/ | HF42: 60 | HG42: 587 | HH42: White | HI42: C | HJ42: 60 | HK42: 586.9 | HL42: 547.7 | HM42: 297.2 | HN42: E | HO42: D | HP42: B | HQ42: 3 | HR42: 1 | HS42: 2.3*1 | HT42: 210 | HU42: 10035284 | HV42: 34*27.4 | HW42: 50 | HX42: 09780000022 | HY42: Yes | HZ42: 150 | IA42: 780 | IB42: 400 | IC42: -- | ID42: 66 | IE42: 58 | IF42: 1 | IG42: 3 | IH42: No | II42: -- | IJ42: LED | IK42: 3 | IL42: Illuminated LED knob | IM42: AC | IN42: 125 | IO42: No | IP42: No | IQ42: No | IR42: Coated Steel | IS42: No | IT42: No
A43: 10035380 | B43: Eleonora 60cm A++ Class Blk | D43: Shop | E43: Eleonora | F43: 0 | G43: TK15 | L43: Large Appliances-Range Hoods-Angled Hoods | M43: Large Appliances | N43: Range Hoods | O43: Angled Hoods | Q43: Eleonora | S43: 60 | T43: Non-IoT | U43: < 500 m³/h | V43: A++ | Y43: Eleonora 60cm A++ Class Blk | Z43: 27 | AB43: Width | AC43: 60 | AD43: Color | AE43: Black | CG43: Black | CI43: Blk | CR43: A++ | CS43: 10 | CT43: 220-240 V ~ 50/60 Hz | CU43: Type E/F - 2 pin (German) - Schuko | CV43: 2 | CW43: Class I | CX43: 76 | CY43: 60 | DB43: 114 | DC43: 60 | DD43: 43.5 | DE43: 13.8 | DL43: 114 * 60 * 43.5 | DU43: ISTA 1A | DV43: 1 | EY43: TRUE | EZ43: TRUE | FA43: Angled Hoods - Attributes V3.0.xlsx | FB43: https://chaltecadmin.sharepoint.com/sites/ProductManagement/Shared Documents/02_Strategy/01_Portfolio Strategy/05_Product Passport/01_Large Appliances/ | HF43: 60 | HG43: 456 | HH43: Black | HI43: A++ | HJ43: 60 | HK43: -- | HL43: 455.8 | HM43: 155.1 | HN43: D | HO43: A | HP43: A | HQ43: 3 | HR43: 0 | HS43: φ160（+1,0） | HT43: 300 | HU43: 10035386 | HV43: 220*292.5*9 | HW43: 250 | HX43: 10030471 | HY43: Yes | HZ43: 150 | IA43: 780 | IB43: 400 | IC43: -- | ID43: 60 | IE43: 43 | IF43: 2 | IG43: 1 | IH43: Yes | II43: 4 | IJ43: LED | IK43: 2*1.5W | IL43: Touch | IM43: DC | IN43: 73 | IO43: Yes | IP43: No | IQ43: No | IR43: Coated Steel | IS43: No | IT43: No
A44: 10035381 | B44: Eleonora 60cm A++ Class Wht | D44: Shop | E44: Eleonora | F44: 0 | G44: TK15 | L44: Large Appliances-Range Hoods-Angled Hoods | M44: Large Appliances | N44: Range Hoods | O44: Angled Hoods | Q44: Eleonora | S44: 60 | T44: Non-IoT | U44: < 500 m³/h | V44: A++ | Y44: Eleonora 60cm A++ Class Wht | Z44: 27 | AB44: Width | AC44: 60 | AD44: Color | AE44: White | CG44: White | CI44: Wht | CR44: A++ | CS44: 10 | CT44: 220-240 V ~ 50/60 Hz | CU44: Type E/F - 2 pin (German) - Schuko | CV44: 2 | CW44: Class I | CX44: 76 | CY44: 60 | DB44: 114 | DC44: 60 | DD44: 43.5 | DE44: 13.8 | DL44: 114 * 60 * 43.5 | DU44: ISTA 1A | DV44: 1 | EY44: TRUE | EZ44: TRUE | FA44: Angled Hoods - Attributes V3.0.xlsx | FB44: https://chaltecadmin.sharepoint.com/sites/ProductManagement/Shared Documents/02_Strategy/01_Portfolio Strategy/05_Product Passport/01_Large Appliances/ | HF44: 60 | HG44: 456 | HH44: White | HI44: A++ | HJ44: 60 | HK44: -- | HL44: 455.8 | HM44: 155.1 | HN44: D | HO44: A | HP44: A | HQ44: 3 | HR44: 0 | HS44: φ160（+1,0） | HT44: 300 | HU44: 10035386 | HV44: 220*292.5*9 | HW44: 250 | HX44: 10030471 | HY44: Yes | HZ44: 150 | IA44: 780 | IB44: 400 | IC44: -- | ID44: 60 | IE44: 43 | IF44: 2 | IG44: 1 | IH44: Yes | II44: 4 | IJ44: LED | IK44: 2*1.5W | IL44: Touch | IM44: DC | IN44: 73 | IO44: Yes | IP44: No | IQ44: No | IR44: Coated Steel | IS44: No | IT44: No
A45: 10035382 | B45: Eleonora 90cm A++ Class Blk | D45: Shop | E45: Eleonora | F45: 0 | G45: TK15 | L45: Large Appliances-Range Hoods-Angled Hoods | M45: Large Appliances | N45: Range Hoods | O45: Angled Hoods | Q45: Eleonora | S45: 90 | T45: Non-IoT | U45: < 500 m³/h | V45: A++ | Y45: Eleonora 90cm A++ Class Blk | Z45: 27 | AB45: Width | AC45: 90 | AD45: Color | AE45: Black | CG45: Black | CI45: Blk | CR45: A++ | CS45: 9.8 | CT45: 220-240 V ~ 50/60 Hz | CU45: Type E/F - 2 pin (German) - Schuko | CV45: 2 | CW45: Class I | CX45: 76 | CY45: 59 | DB45: 114 | DC45: 90 | DD45: 43.5 | DE45: 15.5 | DL45: 114 * 90 * 43.5 | DU45: ISTA 1A | DV45: 1 | EY45: TRUE | EZ45: TRUE | FA45: Angled Hoods - Attributes V3.0.xlsx | FB45: https://chaltecadmin.sharepoint.com/sites/ProductManagement/Shared Documents/02_Strategy/01_Portfolio Strategy/05_Product Passport/01_Large Appliances/ | HF45: 90 | HG45: 452 | HH45: Black | HI45: A++ | HJ45: 90 | HK45: -- | HL45: 451.5 | HM45: 184.2 | HN45: D | HO45: A | HP45: A | HQ45: 3 | HR45: 0 | HS45: φ160（+1,0） | HT45: 300 | HU45: 10035386 | HV45: 220*292.5*9 | HW45: 250 | HX45: 10030471 | HY45: Yes | HZ45: 150 | IA45: 780 | IB45: 400 | IC45: -- | ID45: 59 | IE45: 42 | IF45: 2 | IG45: 1 | IH45: Yes | II45: 4 | IJ45: LED | IK45: 2*1.5W | IL45: Touch | IM45: DC | IN45: 73 | IO45: Yes | IP45: No | IQ45: No | IR45: Coated Steel | IS45: No | IT45: No
